Workbook

Sheet Epics
A1: ID | B1: Title | C1: Work Item Type
A2: 251 | B2: Proyecto WAPSA 2024 - 3 | C2: Epic
A3: 252 | B3: Pases a Producción | C3: Epic
A4: 253 | B4: WAPSA BI | C4: Epic
A5: 210 | B5: Proyecto WAPSA 2024 - 2 | C5: Epic
A6: 412 | B6: Proyecto WAPSA 2025 - 1 | C6: Epic
A7: 161 | B7: Soporte | C7: Epic
A8: 175 | B8: Mejoras WAPSA | C8: Epic
A9: 177 | B9: Mejoras Guias Electronicas | C9: Epic
A10: 181 | B10: Proyecto WAPSA 2024 - 1 | C10: Epic
A11: 457 | B11: Proyecto WAPSA 2025 - 2 | C11: Epic

Sheet Hoja1
A1: ID | B1: Title | C1: Work Item Type | D1: Iteration Path | E1: Tipo Caso | F1: Estados | G1: Tags | H1: Start Date | I1: Finish Date | J1: Aplicación | K1: Ticket Chinalco | L1: Ticket SyC | M1: Assigned To | N1: Description | O1: Parent
A2: 226 | B2: Ticket 336 - Wapsa BI - La ejecucion a demanda del reporte de BI de Pesos y Leyes no actualiza data | C2: Ticket | D2: WAPSA\Sprint - Abril -2024 | E2: Repetitivo-en-proceso | F2: Cerrado | H2: 45397 | I2: 45416 | K2: 105868 | L2: 336 | M2: Cristian Pastor Artigas | N2: [Image] El error no se puede replicar en ningun ambiente. 10/04 @Cristian Pastor Artigas Por ende se solicita reunion a Alexander con el DBA 19/04 @Cristian Pastor Artigas Luego de la revision con el DBA se detecta que el script de mover datos de Wapsa a BI esta correcto, se concluye que la falta de data es un problema de logica del script 19/04 @Cristian Pastor Artigas Se soluciona error cambiando el filtro del script para utilizar a la fecha de proceso de MIna y no de Volteo 19/04 @Cristian Pastor Artigas Se preparara formato para enviar ticket 23/04 @Cristian Pastor Artigas Se envia formato para firma de Alejandro 24/04 @Cristian Pastor Artigas Se envio a TICA 01/05 @Cristian Pastor Artigas Alexander envia para formas internas 04/05 @Cristian Pastor Artigas Ticket Ejecutado | O2: WAPSA BI
A3: 241 | B3: Ticket 348 - Valores repetidos en Reporte de Pesos y Leyes del BI | C3: Ticket | D3: WAPSA\Sprint - Mayo -2024 | E3: Nuevo | F3: Cerrado | H3: 45428 | I3: 45440 | J3: Wapsa BI | K3: 107784 | L3: 348 | M3: Cristian Pastor Artigas | N3: Luis Casas inidca que la data del reporte se duplica por lote 15/05 @Cristian Pastor Artigas Se corrige script en BD BI y se prerara script para ejecucion manuald e Wapsa 16/05 @Cristian Pastor Artigas Se prepara formato de Ticket y se envia a AM 16/05 @Cristian Pastor Artigas Enviado a TICA 29/05 @Cristian Pastor Artigas Ejecutado y Cerrado | O3: WAPSA BI
A4: 314 | B4: Ticket 377 - Wapsa BI- Ejecución Manual - Resta copiar guias sin volteo en el reporte de datos de mina | C4: Ticket | D4: WAPSA\Sprint - Octubre - 2024 | E4: Repetitivo-en-proceso | F4: Cerrado | H4: 45540 | I4: 45540 | J4: Wapsa Web | K4: 118265 | L4: 377 | M4: Cristian Pastor Artigas | N4: Luis casas reporta: 1. Falta informacion de Pesos de mina en Reporte de Mina 05/09 @Cristian Pastor Artigas Para firmas | O4: WAPSA BI
A5: 203 | B5: Ticket 322 - Wapsa BI - Reproceso de tabla de Humedades, pesos y leyes Correccion en Wapsa | C5: Ticket | D5: WAPSA\Sprint - Marzo 2024 | F5: Cerrado | H5: 45331 | J5: Wapsa BI | K5: 100715 | L5: 322 | M5: Cristian Pastor Artigas | N5: Ticket 322 - Wapsa BI - Reproceso de tabla de Humedades, pesos y leyes. Script de actualizacion de copia de datos para ejecucion a demanda de humedades, pesos y leyes 20/02 Este ticket depende del 298 se debe enviar el mismo script a Pord de Wapsa 27/02 Se preparan formatos para la firma y enviar ticket 29/02 Enviado a TICA @Cristian Pastor Artigas 01/03 Alexander envia Ticket a Mesa de Servicios @Cristian Pastor Artigas 04/03 Se consulta por el estado del Ticker no se obtiene respuesta @Cristian Pastor Artigas 11/03 Se consulta por el estado del Ticker no se obtiene respuesta @Cristian Pastor Artigas | O5: WAPSA BI
A6: 169 | B6: Ticket 298 - WAPSA BI - Reproceso del dashboard del 01 al 07 enero | C6: Ticket | D6: WAPSA\Sprint - Marzo 2024 | E6: Nuevo | F6: Cerrado | H6: 45315 | J6: WAPSA BI | L6: 298 | M6: Cristian Pastor Artigas | N6: Descripción: Reproceso del dashboard del 01 al 07 enero Sin permisos a la base de datos 30/01 Se tuvo problemas con el usuario 07/02 Se revisa y e total de Guias de enero coinciden con los de Wapsa Se programa reunion con Luis Casas para revisar su BI 08/02 Luego de la reunion se detecta que es un error de rango de fechas en la busqueda de datos en el Wapsa; se corrige y se deja ejecutando para el lote 2301 a la espera de la validacion de LC 16/02 Se tiene script pero el usaurio esta bloqueado para hacer las pruebas 27/02 Se envia script en base de BI y se validara en la siguiente ejecucion automatica. | O6: WAPSA BI
A7: 216 | B7: Ticket 328 - Wapsa BI - Error ejecucion a demanda Humedades, pesos y leyes | C7: Ticket | D7: WAPSA\Sprint - Abril -2024 | E7: Nuevo | F7: Cerrado | H7: 45370 | J7: Wapsa BI | K7: 103122 | L7: 328 | M7: Cristian Pastor Artigas | N7: 19/03 Se envia para firma de Alejandro | O7: WAPSA BI
A8: 235 | B8: Ticket 345: Solicitud de Pase a Producción Wapsa/WapsaUE v2.16 | C8: Ticket | D8: WAPSA\Sprint - Mayo -2024 | E8: Nuevo | F8: Cerrado | G8: [Ver. 2.16] | H8: 45415 | I8: 45432 | J8: Wapsa Web | L8: 345 | M8: Cristian Pastor Artigas | N8: Pase a producción Wapsa V 2.16 Ticket 330 https://dev.azure.com/SycSistemas/WAPSA/_boards/board/t/WAPSA%20Team/Stories/?workitem=218 Ticket 340 https://dev.azure.com/SycSistemas/WAPSA/_workitems/edit/230 Ticket 339 https://dev.azure.com/SycSistemas/WAPSA/_workitems/edit/229 Ticket 331 https://dev.azure.com/SycSistemas/WAPSA/_workitems/edit/219 Ticket 338 https://dev.azure.com/SycSistemas/WAPSA/_workitems/edit/228 03/05 @Cristian Pastor Artigas se crea y se envía documentación para firmas de AM 03/05 @Cristian Pastor Artigas se envia pase a producción 10/05 @Cristian Pastor Artigas Se sube archivo de Manual de Usuario Actualizado 15/06 @Cristian Pastor Artigas Se suben sustentos Casos de prueba, y Alexander envia scripts a DBA para su ejecucion del pase final, a la espera de definir dia | O8: Pases a Producción
A9: 245 | B9: Ticket 351: Solicitud de Pase a Producción Wapsa/WapsaUE v2.16.1 | C9: Ticket | D9: WAPSA\Sprint - Mayo -2024 | E9: Nuevo | F9: Cerrado | G9: [2.16.1] | H9: 45415 | I9: 45441 | J9: Wapsa Web | L9: 351 | M9: Cristian Pastor Artigas | N9: Pase a producción Wapsa V 2.16.1 Ticket 350 https://dev.azure.com/SycSistemas/WAPSA/_boards/board/t/WAPSA%20Team/Stories/?workitem=243 Ticket 352 https://dev.azure.com/SycSistemas/WAPSA/_boards/board/t/WAPSA%20Team/Stories/?workitem=244 22/05 @Cristian Pastor Artigas se crea y se envía documentación para firmas de AM 23/05 @Cristian Pastor Artigas Enviado a TICA 27/05 @Cristian Pastor Artigas WM adjunta evidencias de pruebas. Se esta a la espera de definir por parte de TICA el dia y hora de hacer los cambios en producción 29/05 @Cristian Pastor Artigas Cerrado | O9: Pases a Producción
A10: 285 | B10: Ticket 366: Solicitud de Pase a Producción Wapsa/WapsaUE v2.17 | C10: Ticket | D10: WAPSA\Sprint - Septiembre - 2024 | E10: Nuevo | F10: Cerrado | G10: [Ver. 2.17] | H10: 45488 | J10: Wapsa Web | K10: 102342 | L10: 366 | M10: Cristian Pastor Artigas | N10: Pase a producción Wapsa V 2.17 Ticket 307 - Proyecto WAPSA 2024 - 2 - Mejoras en el cuadre en Wapsa https://dev.azure.com/SycSistemas/WAPSA/_boards/board/t/WAPSA%20Team/Stories/?workitem=186 Ticket 353 - Mina - Lista de Despachos-Se generó un registro duplicado al preasignar vagón por intervención del usuario https://dev.azure.com/SycSistemas/WAPSA/_boards/board/t/WAPSA%20Team/Stories/?workitem=246 Ticket 346 - Guias Electronicas - Proyecto Mejoras WAPSA - 2 - Nuevo Modulo "Emisión de Guias Impala 01" https://dev.azure.com/SycSistemas/WAPSA/_boards/board/t/WAPSA%20Team/Stories/?workitem=236 Ticket 364 - Callao - Lista de Despachos - El filtro por IE's en estado abierto no muestra las que tiene peso = 0 https://dev.azure.com/SycSistemas/WAPSA/_boards/board/t/WAPSA%20Team/Stories/?workitem=282 Ticket 347 - Guias Electronicas - Proyecto Mejoras WAPSA - 2 - GRE Impresión Guías - Hipervinculos https://dev.azure.com/SycSistemas/WAPSA/_boards/board/t/WAPSA%20Team/Stories/?workitem=237 15/07 @Cristian Pastor Artigas Creando documentos 16/07 @Cristian Pastor Artigas Se envia para firmas de AM 18/07 @Cristian Pastor Artigas Enviado a TICA | O10: Pases a Producción
A11: 316 | B11: Ticket 379 - Wapsa - Solicitud de Pase a Producción Wapsa/WapsaUE v2.18 | C11: Ticket | D11: WAPSA\Sprint - Octubre - 2024 | E11: Nuevo | F11: Cerrado | G11: [Ver. 2.18] | H11: 45545 | J11: Wapsa Web | K11: 120145 | L11: 379 | M11: Cristian Pastor Artigas | N11: Pase a producción Wapsa V 2.18 Ticket 302 - Guias Electronicas - Proyecto Mejoras WAPSA - 2 - Entregas Directas - Cambiar como se registra el destinatario, que no sea desde el maestro. https://dev.azure.com/SycSistemas/WAPSA/_boards/board/t/WAPSA%20Team/Stories/?workitem=178 Ticket 372 - Modulo Mina - Pesaje Manual - Mejora-Ver vagones observados https://dev.azure.com/SycSistemas/WAPSA/_boards/board/t/WAPSA%20Team/Stories/?workitem=308 Ticket 373 - Modulo Mina - Pesaje - Mejora correos supervisores https://dev.azure.com/SycSistemas/WAPSA/_boards/board/t/WAPSA%20Team/Stories/?workitem=309 Ticket 375 - Modulo Pesaje - Vagones observados - no filtra por los estados https://dev.azure.com/SycSistemas/WAPSA/_boards/board/t/WAPSA%20Team/Stories/?workitem=311 Ticket 376 - Modulo Pesaje - Registro cambio check auto/manual peso tara https://dev.azure.com/SycSistemas/WAPSA/_boards/board/t/WAPSA%20Team/Stories/?workitem=312 Ticket 383 - Callao - Volteo - Link para descargar PDF en Guias Electronicas | O11: Pases a Producción
A12: 290 | B12: Ticket 367: Solicitud de Pase a Producción Servicio Movil Wapsa v1.1 | C12: Ticket | D12: WAPSA\Sprint - Agosto - 2024 | E12: Nuevo | F12: En Produccion | G12: [Ver. 1.1] | H12: 45491 | J12: Wapsa Web | L12: 367 | M12: Cristian Pastor Artigas | N12: Pase a producción Servicio Movil Wapsa v1.1 Ticket 346 - Proyecto WAPSA 2024 - 2 - Mejoras en el Inspeccion WAPSA movil https://dev.azure.com/SycSistemas/WAPSA/_boards/board/t/WAPSA%20Team/Stories/?workitem=238 Ticket 308 - Proyecto WAPSA 2024 - 2 - Mejoras en el cuadre en Wapsa Movil https://dev.azure.com/SycSistemas/WAPSA/_boards/board/t/WAPSA%20Team/Stories/?workitem=187 18/07 @Cristian Pastor Artigas Se envia para firma de AM | O12: Pases a Producción
A13: 213 | B13: Ticket 326 Pase a Produccion Wapsa/WapsaUE v2.15 | C13: Ticket | D13: WAPSA\Sprint - Marzo 2024 | F13: Cerrado | G13: [Ver. 2.15] | H13: 45365 | J13: Wapsa | K13: 102342 | L13: 326 | M13: Cristian Pastor Artigas | N13: Pase a produccion Version 2.15 Ticket 303 - Proyecto WAPSA 2024 - 1 - Mejoras Embarque a Granel"Extraporturario" Lista despacho. Ticket 305 - Proyecto WAPSA 2024 - 1 - Mejoras Reporte TMH, TMS,HUMEDAD Lista despacho. · Ticket 326 - El registro de Pesaje de Mina Muestra ventana dediferencias de peso tara al momento de preasignar. Ticket 313 - Proyecto WAPSA 2024 - 1 - Aprobación Supervisor por ladiferencia de peso tara en mina. Ticket 327 - Corrección error al hacer la aprobación de Pesaje ManualMódulo. Ticket 314 - Proyecto WAPSA 2024 - 1 - Alerta Lista Despacho. 14/03 Se envian documentos para firma de AM @Cristian Pastor Artigas 18/03 AM responde documentos firmados 18/03 Se envia Ticket a TICA para iniciar pase @Cristian Pastor Artigas 20/03 TICA pasa a testing 20/03 Wally revisa y envia correcciones sobre los tickets #192 y #182 20/03 TICA asigna ticket MCP #102342 | O13: Pases a Producción
A14: 207 | B14: Ticket 324 - Pase a Produccion Wapsa Servicio Ver. 2.4 | C14: Ticket | D14: WAPSA\Sprint - Febrero 2024 | F14: Cerrado | G14: [Ver.2.4] | H14: 45338 | I14: 45343 | L14: 324 | M14: Cristian Pastor Artigas | N14: Pase a Produccion Wapsa Servicio Ver. 2.4 15/02: Se moven cambio para preparar version PR 171: Correccion servicio ver 2.4 16/02: @Cristian Pastor Artigas Se envian formatos a firma de AM 20/02 Aprobo Alexander el pase 22/02 TICA realizo el pase a Produccion son documentacion de casos de pruebas @Cristian Pastor Artigas | O14: Pases a Producción
A15: 200 | B15: Ticket 318 - Pase a Producción Wapsa Ver 2.14 | C15: Ticket | D15: WAPSA\Sprint - Febrero 2024 | F15: Cerrado | G15: [Ver.2.14] | H15: 45328 | I15: 45355 | J15: Wapsa | K15: #100230 | L15: 319 | M15: Cristian Pastor Artigas | N15: Pase a produción Wapsa UE y Wapsa * Ticket 319 - Modulo Mina - Mover opciones de aprobación por guía a la pestaña de observados * Ticket 295 - Modulo Mina Pesaje - Nuevo filtro en la vista de vagones observados * Ticket 293 - Modulo mina - los adjuntos para Diferencia de peso tara se estan guardando mal * Ticket 294 - Modulo Mina - Vista de Vagones observados no filtra ni exporta correctamente * Ticket 316 - Modulo Mina - No deja adjuntar las evidencias para duplicidad de precintos * Ticket 301 - Modulo Callao - DIFERENCIA DE PESOS BRUTOS CALLAO * Ticket 296 - Modulo Callao Lista Despacho - Corregir "ITEM" cuando das click en ver "Detalle" por una IE 5/02: Recibidos documentos firmado por Alejandro 6/02: Documentos y mail enviados a TICA 9/02: Disponible en Testing para las pruebas 12/02: Pruebas con Wally: -Volteo: Solo se tomará en cuenta para obervar el vagon si es que los pesos brutos si es que la diferencia de pesos de Callao y Mina es inferior al factor. -Inspeccion callao: Correccion de error al agregar sustento al editar el vagon. PR 169: Cambio de Factor y correccion adjuntar editar vagon inspeccion 13/02 Revision con WM se aprueban todas las correciones del CP Se solicita corregir un texto en la evidencias del pesaje de mina 14/02 Correccion texto en la evidencias del pesaje de mina PR 170: Correcciones para texto en adjuntos y corregir error de adjuntado en diferencia de pesos mina 16/02 Se envian a Wally las evidencias del pase. Quedamos a la espera de una ultima prueba al pesaje por parte de Wally para cerrar el pase 19/02 Se solicita a Julio que envie el link para que Wally suba las evidencias. Se queda la espera de fecha del pase 23//02 Alexander asigna el pase a Produccion a Saul para que inidque el dia y hora. 26/02 El pase es reasignado a Julio, en un mail indica que esta por firmas de documentos. 27/02 @Cristian Pastor Artigas Se solicita actualizacion de estado del pase 01/03 Julio realiza pase pero solo de Wapsa falta WapsaEU @Cristian Pastor Artigas | O15: Pases a Producción
A16: 248 | B16: Ticket 355 Proyecto - Agregar grupos de Ensayo en Wapsa | C16: Ticket | D16: WAPSA\Sprint - Enero - 2025 | E16: Nuevo | F16: En Desarrollo | J16: Wapsa Web | L16: 355 | N16: Luis Casas solicita: En la transmision de leyes de Cotecna e importacion: - Habilitar 4 columnas de información en el reporte de H2OyLey Callao de Wapsa; grupos (G1,G2,G3,G4) para recibir la data de Cotecna - Generar el maestro: "Grupos de análisis" para seleccionar a qué grupo pertenece cada analito. - Actualizar el reporte en Excel de H2OyLey Callao incluyendo los Grupos. - Habilitar las 4 columnas en el dashboard (HumedadesyLeyes) 28/05 @Cristian Pastor Artigas Se adjunta documento resultante de la reunion | O16: Proyecto WAPSA 2024 - 3
A17: 194 | B17: Ticket 315 - Proyecto WAPSA 2024 - 1 - Mejoras Logs | C17: Ticket | D17: WAPSA | E17: Nuevo | F17: Nuevo | H17: 45540 | J17: WAPSA web | L17: 315 | M17: Cristian Pastor Artigas | N17: Modulo Log 1.1 Listado Log * Mejorar el performance del modulo de logs es demasiado lento * Desarrollar funcioanlidad para guardar los datos del request cuadno se realizan ejemplo si se guardan leyes que valores estan siendo enviados al WAPSA para grabarse. * Modificar scripts para soportar esta nueva columna que obtendrá los datos de datos enviados * Crear nuevas tablas para manejar las llaves y adjuntos * Modificar la UI para poder ver esta nueva columna * Realizar pruebas | O17: Proyecto WAPSA 2024 - 3
A18: 223 | B18: Ticket 333 - Proyecto Wapsa - Rountrip con GPS | C18: Ticket | D18: WAPSA\Sprint - Enero - 2025 | E18: Nuevo | F18: Nuevo | H18: 45392 | J18: Wapsa Web | K18: 333 | N18: 10/04 @Cristian Pastor Artigas Reunion con el proveedor CLS Peru en la cual se concretaron los siguientes puntos: -En la aplicacion de CLS que le permite a MIna monitorear los vagones via GPS se registrar el Nro de Guia de Remision en el campo conductor, de momento manualmente lo hara el equipo de Edwin Rios MCP. -El equipo de Edwin registrara la guias desde el Jueves 11/04 hasta el dia lunes para que luego de eso SyC Sistemas podra 15/04 consultar utilizando el API. -EL dia 15/04 SyC probara haciendo consultas utilizando el API para devolver los datos filtrando por el campo conductor-Guia de remision, -La proxima reunion sera el dia 18 o 19/04 -Se concretara una reunion con Wally a posterior para ver internamnete en Wapsa cuales seran las mejoras una vez podamos consultar la informacion correctamnete desde el API -CLS indico cual es la documentacion que se debe consultar. https://sdk.wialon.com/wiki/en/sidebar/remoteapi/apiref/report/cleanup_result @Cristian Pastor Artigas Video de la reunion en los adjuntos del Ticket 15/04 Edwin Rios inidca que ya se esta cargando los Numeros de Guias desde Mina 16/04 @Cristian Pastor Artigas Se envia consulta a la Empresa del GPS para consultar sobre como obtener los ID's para obtener lueo los reportes 23/04 @Cristian Pastor Artigas CLS responde mail enviando las credenciales de acceso 29/04 @Cristian Pastor Artigas Se envia consulta a CLS porque no se puede obtener la informacion de los puntos del GPS , se solicita reunion | O18: Proyecto WAPSA 2024 - 3
A19: 190 | B19: Ticket 311 - Proyecto WAPSA 2024 - 1 - Envío de información a Impala a través de un servicio | C19: Ticket | D19: WAPSA | E19: Nuevo | F19: Nuevo | J19: WAPSA servicio | L19: 311 | N19: 1.Agregar nuevo controlador para enviar informacion a IMPALA Envio de datos * Crear scripts para obtener los datos * Crear logica en el controlador para enviar los mensajes Validaciones * Crear validaciones para los ejes * Modificar el WAPSA para mostrar las validaciones * Crear logica para identificar cuando se reasigno la ruma para actualizar los datos de impala * Realizar pruebas 2.Ejes de Ruma Liberacion de ejes * Crear logica apra librerar ejes * Modificar el WAPSA para usar esta validación * Realizar pruebas 3.Reportes * Crear reporte de ejes de ruma donde se mostraran los eje en uso y los que esten libres para asignación | O19: Proyecto WAPSA 2024 - 3
A20: 183 | B20: Ticket 304 - Proyecto WAPSA 2024 - 1 - Modificar Proceso Lista despacho | C20: Ticket | D20: WAPSA | E20: Nuevo | F20: Nuevo | J20: WAPSA web | L20: 305 | N20: Descripción: 1.1 Pesos Lista Despacho * Modicar codigo en el momento que se modifiquen pesos se deben eliminar las leyes y humedades existentes. * Modificar UI para consumir nuevo proceso * Realizar pruebas 1.2 Humedades Lista Despacho * Modicar codigo en el momento que se modifiquen pesos se deben eliminar las leyes. * Modificar UI para consumir nuevo proceso * Realizar pruebas Solución: | O20: Proyecto WAPSA 2024 - 3
A21: 191 | B21: Ticket 312 - Proyecto WAPSA 2024 - 1 - Ajuste final y Repeso total | C21: Ticket | D21: WAPSA | E21: Nuevo | F21: Nuevo | J21: WAPSA web | L21: 312 | N21: Ajuste final y Repeso total 1.1 Ajuste final * Modificar lógica para creación de ajuste para validar lo siguiente: al realizar el ajuste la fecha y hora debe ser mayor al último movimiento (ingreso, salida, junta). * Modificar la UI para mostrar el mensaje y consumir la validación * Realizar pruebas 1.2 REPESO TOTAL * Modificar lógica para creación de ajuste para validar lo siguiente: al realizar el ajuste la fecha y hora debe ser mayor al último movimiento (ingreso, salida, junta). * Modificar la UI para mostrar el mensaje y consumir la validación * Realizar pruebas 1.3 Validaciones adicionales * Crear validacion para poder crear un bloqueo de pesos en tmh si se genera un "Ajuste en TMH" * Crear validacion para poder crear un bloqueo de pesos en tms si se genera un "Ajuste en TMS" * Modificar cada punto de creación de pesos (TMH,TMS) para consumir la validación * Modifcar la UI para consumir estas validaciones * Realizar pruebas | O21: Proyecto WAPSA 2024 - 3
A22: 189 | B22: Ticket 310 - Proyecto WAPSA 2024 - 1 - Arribo a Mina y a Callao con GPS | C22: Ticket | D22: WAPSA | E22: Nuevo | F22: Nuevo | J22: WAPSA web | L22: 310 | N22: Crear una API 1.1 Crear proceso automatico para leer datos del GPS * Creacion de scripts * Desarrollo del codigo con logica 1.2 Modificar el wapsa * Modificar el WAPSA para soportar una lectura del gps o manual * Realizar pruebas | O22: Proyecto WAPSA 2024 - 3
A23: 185 | B23: Ticket 306 - Proyecto WAPSA 2024 - 1 - Mantenimiento Equipos-Pesajes | C23: Ticket | D23: WAPSA | E23: Nuevo | F23: Nuevo | J23: WAPSA web | L23: 306 | N23: Mantenimiento de tablas 1.1 Registro de Equipos * Registro de los equipos * Configurar cuenta de correo 1.2 Mantenimiento de tablas * Tipos de mantenimiento * Tipos de averias * Empresas * Ubicación Registro de la programación 2.1 Registro de programación * Registro de programación * Registro de evidencias * Envío de la notificación 2.2 Registro de mantenimiento correctivo * Registro del evento * Registro de las evidencias Reportes * Reporte de programación * Reporte de Mantenimiento Correctivo | O23: Proyecto WAPSA 2024 - 3
A24: 218 | B24: Ticket 330 - Mejora WAPSA Lista Despacho Diferencias Peso - Embarque Granel | C24: Ticket | D24: WAPSA\Sprint - Mayo -2024 | E24: Nuevo | F24: Cerrado | G24: [Ver. 2.16] | H24: 45383 | J24: WAPSA web | L24: 330 | M24: Cristian Pastor Artigas | N24: Descripción: Se requiere que el WAPSA en la lista despacho se tenga un nuevo filtro para saber si estan observador por el nuevo factor para los casos de "Embarque a Granel" y adicional se requeire cambio de los titulos. Diferencia Balanzas (Almacén 2 - Almacen) Si / No Diferencia Balanzas (Puerto - Almacen) Si / No Ahora: Extraportuario Nuevo: Extraportuario / Balanza 2 Ahora: Almacen Nuevo: Almacen / Balanza 1 Solicitado por Wally Moscoso 20/03 Solución: @Cristian Pastor Artigas Se crea nuevas columnas en el listado y excel con la logica para mostrar el valor de Si/No, pendiente el filtro @Cristian Pastor Artigas Se crea filtro 02/04 @Cristian Pastor Artigas Se envia a 06/04 Wally para revision inidca lo siguiente: -Ajustar nombre de columnas -Agregar una configuracion para indicar el codigo del la IE a partir de la cual debe iniciar a funcionar el filtro de diferencias @Cristian Pastor Artigas Se crea configuracion para que el usuario pueda indicar la IE, se ajustan nombres de campos | O24: Proyecto WAPSA 2024 - 2
A25: 240 | B25: Tickets 347 - Actualizar Manual Usuario de Wapsa | C25: Ticket | D25: WAPSA\Sprint - Mayo -2024 | E25: Nuevo | F25: Cerrado | H25: 45419 | I25: 45422 | J25: Wapsa Web | L25: 347 | M25: Cristian Pastor Artigas | N25: Por solicitud de TICA(Alexander) en reunion del 07/05 se solicita actualizar el Manual de Usuario de Wapsa 07/05 @Cristian Pastor Artigas Se actualiza manual y se sube al servidor de SyC | O25: Proyecto WAPSA 2024 - 2
A26: 250 | B26: Ticket 356 - Servicios Web Callao | C26: Ticket | D26: WAPSA\Sprint - Enero - 2025 | E26: Nuevo | F26: Nuevo | G26: [Ver. 1.3] | H26: 45447 | J26: WAPSA web | L26: 356 | M26: Cristian Pastor Artigas | N26: Descripción: [Image] Solución: 05/06 @Cristian Pastor Artigas Se modifica servicio primeros cambios Volteo Callao. 10/06 @Cristian Pastor Artigas Se crean lo cambios para que marque con diferencias cuando el peso de Callao excede el de Mina segun factor. 14/06 @Cristian Pastor Artigas Se revisa y se hacen los cambios para el servicio de recepcion de pesos para: Contenerdor Directo, Extraportuario, Traslado Entre establacimientos y Granel Resta revisar Humedades 19/06 @Cristian Pastor Artigas Esta creado un servicio para los pesos pero puede cambiarse a que se reciban por la GRE, falta definir si Impala enviara la IE por el servicio de GRE. Reunion 20/06 20/06 @Cristian Pastor Artigas En reunion: Se envia informacion a impala sobre los servicios y a lo interno van a definir los tiempos que tomaría el desarrollo. Impala queda en enviarnos el TAG dentro del cual no esta enviando la IE d eImpala al momento de crear la GRE. A la espera de la informacion de Impala para hacer los cambio en servicio de la GRE para grabar los pesos. | O26: Proyecto WAPSA 2024 - 2
A27: 178 | B27: Ticket 302 - Guias Electronicas - Proyecto Mejoras WAPSA - 2 - Entregas Directas - Cambiar como se registra el destinatario, que no sea desde el maestro. (mejora posterior | C27: Ticket | D27: WAPSA\Sprint - Octubre - 2024 | E27: Nuevo | F27: Cerrado | G27: [Ver. 2.18] | H27: 45446 | J27: WAPSA web | L27: 302 | M27: Cristian Pastor Artigas | N27: los Descripción: o Para entregas directas: Cambiar como se registra el destinatario, que no sea desde el maetro. (mejora posterior) [Image] Solución: 03/06 @Cristian Pastor Artigas -Creado Lote automatico 28/06 @Cristian Pastor Artigas Punto 1,2,3,4 Terminado 02/07 @Cristian Pastor Artigas En proceso Punto 5, Se revisó requerimiento con Michael. esta al 100% 24/07 @Cristian Pastor Artigas Se implementa cambio en el servicio externo para que grabe correctamente el tipo de Venta de las GRE emitidas por Impala | O27: Proyecto WAPSA 2024 - 2
A28: 186 | B28: Ticket 307 - Proyecto WAPSA 2024 - 2 - Mejoras en el cuadre en Wapsa | C28: Ticket | D28: WAPSA\Sprint - Septiembre - 2024 | E28: Nuevo | F28: Cerrado | G28: [Ver. 2.17] | H28: 45418 | I28: 45425 | J28: WAPSA Web | L28: 307 | M28: Cristian Pastor Artigas | N28: 1.1 Callao-Cuadre scripts * Modificación de scripts 1.2 Callao-Cuadre interfaz * Modificar interfaz para colocar la columna(Ruma) nuevas en la grilla * Modificar "input select" para filtrar solo vagones en arribo y agregar al vagon la ruma * Pruebas Logs * Modificar script del log para mostrar los estados correctamente y describir los datos de los errores * Pruebas en el modulo 06/05 @Cristian Pastor Artigas Se realizan los cambios 10/05 @Cristian Pastor Artigas Se realizan cambios en la App movil para igualar con el Wapsa Web | O28: Proyecto WAPSA 2024 - 2
A29: 239 | B29: Ticket 238: Ticket 347 - Actualizar documentacion de Wapsa | C29: Ticket | D29: WAPSA\Sprint - Mayo -2024 | E29: Nuevo | F29: Cerrado | H29: 45419 | I29: 45422 | J29: Wapsa Web | L29: 347 | M29: Cristian Pastor Artigas | N29: Actualizar documentacion de Wapsa (Manual de Usuario) @Cristian Pastor Artigas Se actualiza el manual y se adjunta en el ticket https://dev.azure.com/SycSistemas/WAPSA/_boards/board/t/WAPSA%20Team/Stories/?workitem=235 | O29: Proyecto WAPSA 2024 - 2
A30: 238 | B30: Ticket 346 - Proyecto WAPSA 2024 - 2 - Mejoras en el Inspeccion WAPSA movil | C30: Ticket | D30: WAPSA\Sprint - Agosto - 2024 | E30: Nuevo | F30: En Produccion | G30: [Ver. 1.1] | H30: 45421 | I30: 45422 | J30: Wapsa Movil | L30: 346 | M30: Cristian Pastor Artigas | N30: La inspeccion en la app movil no funciona solo permite registrar inspecciones sin fotos. 10/05 @Cristian Pastor Artigas Se corrige: -Registro de Convoy -Listar vagones para inspeccion' -Registro de Vagones con sustentos -Se iguala el flujo de registro de vagones observados para que genere la aprobacion con la foto que se toma con la camara, con el flujo del Wapsa Web -Listado de Vagones por convoy ! | O30: Proyecto WAPSA 2024 - 2
A31: 237 | B31: Ticket 347 - Guias Electronicas - Proyecto Mejoras WAPSA - 2 - GRE Impresión Guías - Hipervinculos | C31: Ticket | D31: WAPSA\Sprint - Agosto - 2024 | E31: Nuevo | F31: En Testing | G31: [Ver. 2.17] | H31: 45440 | I31: 45483 | J31: WAPSA web | L31: 347 | M31: Frank Macavilca | N31: Descripción: [Image] [Image] Solución: | O31: Proyecto WAPSA 2024 - 2
A32: 236 | B32: Ticket 346 - Guias Electronicas - Proyecto Mejoras WAPSA - 2 - Nuevo Modulo "Emisión de Guias Impala 01" | C32: Ticket | D32: WAPSA\Sprint - Septiembre - 2024 | E32: Nuevo | F32: Cerrado | G32: [Ver. 2.17] | H32: 45427 | J32: WAPSA web | L32: 346 | M32: Cristian Pastor Artigas | N32: Descripción: [Image] Solución: 20/05 @Cristian Pastor Artigas Se realiza creacion de modulo agregando las vistas y controlador, de momento muestra la misma informacion del que modulo de ED 28/05 @Cristian Pastor Artigas Se finaliza desarrollo y se enviará a testing para revision con Michael 29/05 @Cristian Pastor Artigas Se envia a testing para pruebas. A la espera que TICA actualice el ambien para verlo con MC. 11/06 @Cristian Pastor Artigas Se cambia a estado en desarrollo. Se revisa con Wally y se solicita cambiar: Origen por: ALMACÉN DE MCP (MARIÁTEGUI) Destino: IMPALA 01 Guías de Venta por solo Guía Se debe enviar formato de PDF de GUIA MCP (Antiguo) para que MC proponga los cambios al formato. Se debe enviar formato el TXT de la GRE para que MC lo valide con NeoGrid y envie sus comentarios. 11/06 @Cristian Pastor Artigas Se realizan los cambios. PR 189: Principal PR Modulo de Impresion de Guias Impala 01 Ticket 346 y Parte 1 Ticket 356 Se envian formatos para validacion de MC Se deja Ticket en Desarollo hasta obtener respuesta de MC 09/07 @Cristian Pastor Artigas Se envia a testing cambis en TXT y PDF y para validacion final a MC. | O32: Proyecto WAPSA 2024 - 2
A33: 187 | B33: Ticket 308 - Proyecto WAPSA 2024 - 2 - Mejoras en el cuadre en Wapsa Movil | C33: Ticket | D33: WAPSA\Sprint - Agosto - 2024 | E33: Nuevo | F33: En Produccion | G33: [Ver. 1.3] | H33: 45421 | I33: 45425 | J33: WAPSA movil | L33: 309 | M33: Cristian Pastor Artigas | N33: 2.1 Callao-Cuadre interfaz * Modificar aplicación para agregar el cambio * Modificar "input select" para filtrar solo vagones en arribo y agregar al vagon la ruma * Realizar pruebas @Cristian Pastor Artigas Se implementan los cambios | O33: Proyecto WAPSA 2024 - 2
A34: 193 | B34: Ticket 314 - Proyecto WAPSA 2024 - 1 - Alerta Lista Despacho | C34: Ticket | D34: WAPSA\Sprint - Abril -2024 | E34: Nuevo | F34: Cerrado | G34: [Ver. 2.15] | H34: 45356 | I34: 45376 | J34: WAPSA web | L34: 314 | M34: Frank Macavilca | N34: Modulo Lista Despacho 1.1 Nuevo proceso * crear un factor nuevo para usarlo en el Peso de la IE en el WAPSA * Modificar la UI para poder crear el nuevo flujo de aprobación para la IE que tiene valor en peso 0 pasado 7 días(configurable) - luego enviar un correo diario 7 am * Desarrollar codigo para las notifiaciones por correo o WAPSA * Realizar pruebas | O34: Proyecto WAPSA 2024 - 1
A35: 192 | B35: Ticket 313 - Proyecto WAPSA 2024 - 1 - Aprobación Supervisor por la diferencia de peso tara en mina | C35: Ticket | D35: WAPSA\Sprint - Marzo 2024 | E35: Nuevo | F35: Cerrado | G35: [Ver. 2.15] | H35: 45356 | J35: WAPSA web | L35: 313 | M35: Cristian Pastor Artigas | N35: Modulo Mina - Pesaje 1.1 Proceso Peso Tara * crear script para nueva columna para aprobación para un segundo supervisor * Modificar script de Listar,Insert, Update para soportar nueva columna * Modificar codigo para utilizar el nuevo campo * Modificar la UI para que pueda aprobar el segundo supervisor * Crear nuevo proceso para enviar correo para el segundo supervisor * Realizar pruebas 11/03 Se finaliza la implementacion quedando en cola para pruebas | O35: Proyecto WAPSA 2024 - 1
A36: 184 | B36: Ticket 305 - Proyecto WAPSA 2024 - 1 - Mejoras Reporte TMH,TMS, HUMEDAD Lista despacho | C36: Ticket | D36: WAPSA\Sprint - Marzo 2024 | E36: Nuevo | F36: Cerrado | G36: [Ver. 2.15] | J36: WAPSA web | L36: 306 | M36: Frank Macavilca | N36: Descripción: 1.1 Store Procedures * Modificacion de scripts en la lógica 1.2 Interfaz WAPSA * Modificación de javascript para mostrar los datos correctos en la vista de "Leyes" por IE * Realizar pruebas Solución: | O36: Proyecto WAPSA 2024 - 1
A37: 182 | B37: Ticket 303 - Proyecto WAPSA 2024 - 1 - Mejoras Embarque a Granel "Extraporturario" Lista despacho | C37: Ticket | D37: WAPSA\Sprint - Marzo 2024 | E37: Nuevo | F37: Cerrado | G37: [Ver. 2.15] | J37: WAPSA web | L37: 304 | M37: Frank Macavilca | N37: Descripción: 1.1 Store Procedures * Script para crear nueva columna * Modificar script de Listar,Insert, Update para soportar nueva columna 1.2 Interfaz WAPSA * Modificación de javascript para mostrar los datos * Modificar el código para soportar esta nueva columna agregada al modelo de datos Realizar pruebas 1.3 Notificación * crear un factor nuevo para usarlo en el Peso de la IE en el WAPSA * Modificar la UI para poder crear el nuevo flujo de aprobación para la IE en la diferencia de pesos es mayor que el factor definido * Crear codigo para crear los flujos de aprobación * Crear nuevas tablas para manejar las llaves y adjuntos * Desarrollar código para las notificaciones por correo o WAPSA * Realizar pruebas Ver Adjunto de Referencia | O37: Proyecto WAPSA 2024 - 1
A38: 179 | B38: Ticket 303- Guias Electronicas - Contenedores/Traslados Externos - Realizar mejora en el peso de las guías de Impala, dado que el peso está en kg | C38: Ticket | D38: WAPSA\Sprint - Enero 2024 | E38: Nuevo | F38: Cerrado | G38: [Ver.2.13] | H38: 45315 | I38: 45315 | J38: WAPSA web | L38: 303 | M38: Frank Macavilca | N38: Descripción: Guias Electronicas - Contenedores/Traslados Externos - Realizar mejora en el peso de las guías de Impala, dado que el peso está en kg Solución: | O38: Mejoras Guias Electronicas
A39: 166 | B39: Ticket 295 - Modulo Mina Pesaje - Nuevo filtro en la vista de vagones observados | C39: Ticket | D39: WAPSA\Sprint - Febrero 2024 | E39: Nuevo | F39: Cerrado | G39: [Ver.2.14] | H39: 45315 | J39: WAPSA web | L39: 295 | M39: Cristian Pastor Artigas | N39: Descripción: Mina/despacho, vagones observado: filtros de la vista de vagones observados, debe haber dos estatus (aprobados, pendientes *) *pendientes: hasta que tenga algo pendiente de aprobar Solución: Se corrige filtro por estado, se agrega filtro para ver si hay aprobaciones pendientes: 1-Pend. Aut. Tara 2-Pend. Aut. Bruto 3-Pend. Aut. Uso Peso. Man. Tara 4-Pend. Aut. Uso Peso. Man. Bruto 5-Pend. Aut. Uso Precintos Duplicados 6-Todos | O39: Mejoras WAPSA
A40: 222 | B40: Ticket 332 - Callao-Lista de Despachos-Error en plantilla correo de JOB Factor Pesos | C40: Ticket | D40: WAPSA\Sprint - Abril -2024 | E40: Nuevo | F40: Cerrado | H40: 45389 | J40: Wapsa Web | K40: 103860 | L40: 332 | M40: Cristian Pastor Artigas | N40: EL JOB en produccion envia el mail periodicamente pero con error al mostrar la plantilla [Image] 08/04: @Frank Macavilca Corrige script para enviarlo como Ticket 08/04 @Cristian Pastor Artigas Se envia a Alejandro para firma 09/04 @Cristian Pastor Artigas Enviado a TICA | O40: Soporte
A41: 224 | B41: Ticket 334 - Error en el listado de vagones observados en Mina | C41: Ticket | D41: WAPSA\Sprint - Abril -2024 | E41: Repetitivo-en-proceso | F41: Cerrado | H41: 45393 | I41: 45400 | J41: Wapsa Web | K41: 104784 | L41: 334 | M41: Cristian Pastor Artigas | N41: No se muestran los datos iguales en la misma pantalla de vagones normales y observados Observados: [Image] Normales: [Image] 11/04 @Cristian Pastor Artigas Se envia Formato para la firma 15/04 @Cristian Pastor Artigas Se recibe firma por parte de AM, se envia a TICA | O41: Soporte
A42: 227 | B42: Ticket 337 - Alerta despachos pesos 0 no manda todas las IE's de los dos ultimos meses | C42: Ticket | D42: WAPSA\Sprint - Abril -2024 | E42: Repetitivo-en-proceso | F42: Cerrado | H42: 45398 | I42: 45398 | J42: WAPSA Web | K42: 104786 | L42: 337 | M42: Cristian Pastor Artigas | N42: Descripción: El usuario notifico que no se estan enviando todas las IE's con peso 0 de los utimos dos meses Solución: Se valido en el script que se estaban usando valores en duro para consultar los lotes, se procedio a hacerlos dinamicos y que coja los dos ultimos lotes | O42: Soporte
A43: 233 | B43: Ticket 343 - Callao- Lista de Despachos - Error en el listado de detalle de pesos de la IE 0052/24 | C43: Ticket | D43: WAPSA\Sprint - Abril -2024 | E43: Repetitivo-en-proceso | F43: Cerrado | H43: 45408 | I43: 45414 | J43: Wapsa | K43: 105866 | L43: 343 | M43: Cristian Pastor Artigas | N43: [Image] 26-04 @Cristian Pastor Artigas Se intenta listar la IE 280/24 si sale la lista vacia se crea validacion para que liste correctamente 26-04 @Cristian Pastor Artigas Se soluciona el Ticket y se envia formato a AM para firma 29-04 @Cristian Pastor Artigas Se envia PDF firmado por AM a TICA 02/05 @Cristian Pastor Artigas Alexander envia para firmas internas 02/05 @Cristian Pastor Artigas Resuelto | O43: Soporte
A44: 229 | B44: Ticket 339 - Mina-Lista de Despacho- Error en el listado de vagones observados listado por lote-fecha | C44: Ticket | D44: WAPSA\Sprint - Mayo -2024 | E44: Nuevo | F44: Cerrado | G44: [Ver. 2.16] | J44: Wapsa Web | L44: 339 | M44: Cristian Pastor Artigas | N44: El usuario indica que no le lista correctamente al utilizar el filtro por fechas Se debe revisara el script si fue ejecutado en el pase 17/04 @Cristian Pastor Artigas Se revisa script para listado por lote y la correccion va en el ticket #224 . 17/07 @Cristian Pastor Artigas La correccion para el listado de fechas debe ser en la proxima version v2.16 | O44: Soporte
A45: 232 | B45: Ticket 342 - Ajuste Mensual - Error en datos de la IE 280/24 Ruma R24-004 | C45: Ticket | D45: WAPSA\Sprint - Abril -2024 | E45: Repetitivo-en-proceso | F45: Cerrado | H45: 45408 | I45: 45408 | J45: Wapsa | L45: 342 | M45: Cristian Pastor Artigas | N45: [Image] 26-04 @Cristian Pastor Artigas Se revisa con @Frank Macavilca y el error se debe a que han importado con datos incorrectos los datos de los pesos para la IE 280/24 \ | O45: Soporte
A46: 228 | B46: Ticket 338 - Mina-Lista de Despacho- Cambiar Texto de Estado de Dif. Peso Tara | C46: Ticket | D46: WAPSA\Sprint - Mayo -2024 | E46: Nuevo | F46: Cerrado | G46: [Ver. 2.16] | J46: Wapsa Web | L46: 338 | M46: Cristian Pastor Artigas | N46: Cuando se genera un pesaje cuyo peso tara no genera diferencia el sistema le asigna el texto APROBADO, deberia indicar DENTRO DEL RANGO [Image] 18/04 @Cristian Pastor Artigas Se graba en inicialmente en Dentro del Rango pero se cambiar a Aprobado una vez se registra el Peso Bruto por que se esta cambiando de valor una variable que no debe 18/04 @Cristian Pastor Artigas Se colocara como cambio en proxima version de Wapsa | O46: Soporte
A47: 219 | B47: Ticket 331 - Callao-Volteo Nuevos campos de auditoria | C47: Ticket | D47: WAPSA\Sprint - Mayo -2024 | E47: Nuevo | F47: Cerrado | G47: [Ver. 2.16] | H47: 45389 | J47: Wapsa Web | L47: 331 | M47: Cristian Pastor Artigas | N47: Agregar dos columnas para que el proceso pueda ser auditado directamente [Image] 08/04 @Cristian Pastor Artigas se crea columnas de auditoria adicionales en branch https://dev.azure.com/SycSistemas/833274e7-44d5-4093-8f90-9bab7903e605/_git/WAPSA?version=GBcambios/filtra_lista_despacho | O47: Soporte
A48: 230 | B48: Ticket 340 - Callao -Lista de Despacho- El listado no filtra por IE's abiertas | C48: Ticket | D48: WAPSA\Sprint - Mayo -2024 | E48: Nuevo | F48: Cerrado | G48: [Ver. 2.16] | H48: 45425 | I48: 45426 | J48: Wapsa Web | L48: 340 | M48: Cristian Pastor Artigas | N48: El usuario indica que no le lista correctamente al utilizar el filtro por IE's abiertos 19/04 @Cristian Pastor Artigas El Listado funciona en desarrollo y en Produccion (WAPSAES), resta comprobar con Wally si el proble es especifico en Wapsa MCP de produccion. Si esta correcto se debe cerrar el ticket | O48: Soporte
A49: 243 | B49: Ticket 350 -Callao-Lista de Despacho- El filtro de Dif de Pesos no coloca los textos de diferencia y por ende no filtra correctamente | C49: Ticket | D49: WAPSA\Sprint - Mayo -2024 | E49: Nuevo | F49: Cerrado | G49: [2.16.1] | H49: 45433 | I49: 45433 | L49: 350 | M49: Cristian Pastor Artigas | N49: Wally indica que no se muestra cuando un embarque a granel no tiene diferencia. Debe mostrarte en las columnas para diferencia en No 21/05 @Cristian Pastor Artigas En proceso de revision 22/05 @Cristian Pastor Artigas Se corrige el error PR 187: Correccion para que liste las iE's con TMH 0 y marque los filtros de IEs Gran... | O49: Soporte
A50: 244 | B50: Ticket 352 -Callao-Lista de Despacho- El filtro de carga las IE's con Peso TMH = 0 | C50: Ticket | D50: WAPSA\Sprint - Mayo -2024 | E50: Nuevo | F50: Cerrado | G50: [2.16.1] | H50: 45434 | I50: 45434 | J50: Wapsa Web | L50: 352 | M50: Cristian Pastor Artigas | N50: Diego Cxardenas detecta que no muestra las IEs con Peso TMH = 0 se queda cargando y no finaliza 22/05 @Cristian Pastor Artigas Se genera correccion PR 187: Correccion para que liste las iE's con TMH 0 y marque los filtros de IEs Gran... | O50: Soporte
A51: 225 | B51: Ticket 335 - Mejora Alerta IE's sin leyes | C51: Ticket | D51: WAPSA\Sprint - Mayo -2024 | E51: Nuevo | F51: Cerrado | H51: 45397 | I51: 45436 | J51: WAPSA Web | K51: 107778 | L51: 335 | M51: Cristian Pastor Artigas | N51: Descripción: 1. Debe estar alineada al semáforo, si está en rojo o amarillo debe de listarse 2. Si estuvo en verde y pasa a amarillo o rojo debe de volver a listarse. [Image] Solución: 23/04 @Cristian Pastor Artigas Script modifcado para listar todas las IE's en rojo o amarillo 06/05 @Cristian Pastor Artigas En espera de crear formato para enviar ticket 15/05 @Cristian Pastor Artigas Se envia documento para firma de Alejandro 16/05 @Cristian Pastor Artigas Se envia a TICA | O51: Soporte
A52: 324 | B52: Ticket 380 - Wapsa - Consulta sobre Cierre IE con peso 0 (YCC0172/23) | C52: Ticket | D52: WAPSA\Sprint - Noviembre - 2024 | E52: Nuevo | F52: Cerrado | J52: Wapsa Web | L52: 380 | M52: Cristian Pastor Artigas | N52: Wally Reporta [Image] [Image] | O52: Soporte
A53: 254 | B53: Ticket 357 - Revisar datos del Reporte de Leyes del BI para los meses de Mayo y Junio | C53: Ticket | D53: WAPSA\Sprint - Julio - 2024 | E53: Repetitivo-en-proceso | F53: Cerrado | H53: 45454 | I53: 45454 | J53: Wapsa BI | K53: 109586 | L53: 357 | M53: Cristian Pastor Artigas | N53: Luis Casas indica en la reunion de 11/06 que el reporte de Mayo no le muestra informacion y para Junio le faltan datos de leyes sobre algunas guias. 12/06 @Cristian Pastor Artigas Se revisa Mayo y Junio y no se muestra la informacion completa porque el script filtra solo por Guias en estado 1 y debe hacerlo para 1 y 2 (preasignado y con Peso Bruto). Se corrige scripit en BI Se corrige script para ejecucion manual en Wapsa se enviara a TICA cambios dentro del Ticket 360 https://dev.azure.com/SycSistemas/WAPSA/_boards/board/t/WAPSA%20Team/Stories/?workitem=257 08/07 @Cristian Pastor Artigas Enviado a TICA | O53: Soporte
A54: 268 | B54: Ticket 361 - Callao - Ajuste Mensual - Problema en ajuste en línea R24-013 - JUNIO | C54: Ticket | D54: WAPSA\Sprint - Junio 2024 | E54: Nuevo | F54: Cerrado | H54: 45467 | I54: 45467 | J54: Wapsa Web | L54: 361 | M54: Cristian Pastor Artigas | N54: Diego Cardenas reporta [Image] 24/06 @Cristian Pastor Artigas Se detecta un repeso total duplicado: [Image] @Frank Macavilca Responde via mail [Image] | O54: Soporte
A55: 291 | B55: Ticket 368 - Copia de Base de datos de WAPSA y TRADER de Testing y Desarrollo | C55: Ticket | D55: WAPSA\Sprint - Agosto - 2024 | E55: Nuevo | F55: Cerrado | H55: 45491 | K55: 112853 | L55: 368 | N55: Nicolas Solicita: [Image] | O55: Soporte
A56: 296 | B56: Ticket 370 - Mina - Despachos - Texto incorrecto en el campo Tipo de Pesaje Manual Tara | C56: Ticket | D56: WAPSA\Sprint - Agosto - 2024 | E56: Nuevo | F56: Cerrado | H56: 45506 | I56: 45506 | J56: Wapsa Web | K56: 115970 | L56: 370 | M56: Cristian Pastor Artigas | N56: Luis Casas Reporta [Image] @Cristian Pastor Artigas Preparar Formatos Tickets 08/08 @Cristian Pastor Artigas Enviado a TICA | O56: Soporte
A57: 297 | B57: Ticket 371 - Wapsa BI- Ejecución Manual - Corregir y cargar data antigua de leyes y datos del Volteo del 2018-2024 | C57: Ticket | D57: WAPSA\Sprint - Septiembre - 2024 | E57: Repetitivo-en-proceso | F57: Cerrado | H57: 45518 | I57: 45518 | J57: Wapsa Web | K57: 117280 | L57: 371 | M57: Cristian Pastor Artigas | N57: Luis casas reporta: 1. Desde hace una semana aprox, no se está cargando la información automáticamente, se está ejecutando manualmente. 2. En la tabla HumedadesPesosyLeyes no hay información de antes de Noviembre 2023: 3. En la misma tabla anterior el valor vcLoteCallao está cargando a su vez el sublote en algunas guías, debería ser solo el valor del mes. 27/08 @Cristian Pastor Artigas Falta enviar scripts en ticket para ejecución manual 02/09 @Cristian Pastor Artigas Ticket enviados para firmas 02/09 @Cristian Pastor Artigas Enviado a TICA | O57: Soporte
A58: 256 | B58: Ticket 359-Callao-Lista de Despachos-Error al listar pesos de IE's de tipo Contenedor Directo | C58: Ticket | D58: WAPSA\Sprint - Julio - 2024 | E58: Nuevo | F58: Cerrado | H58: 45461 | I58: 45462 | J58: Wapsa Web | K58: 112573 | L58: 359 | M58: Cristian Pastor Artigas | N58: El listado de Pesos de este tipo de IE's de queda cargando [undefined] 17/16 @Cristian Pastor Artigas Se debe corregir script [eq].[EQ_VerDetallexLote_pa] Error: Division By Zero. A la espera de usuario citrix para pruebas TC #109995. 18/06 @Cristian Pastor Artigas Correccion realizada a la espera de formato para firmas. Adjunto al Ticket el script 08/07 @Cristian Pastor Artigas Enviado a TICA | O58: Soporte
A59: 257 | B59: Ticket 360 - Alerta despachos pesos 0 no manda datos sobre todas las IE's | C59: Ticket | D59: WAPSA\Sprint - Julio - 2024 | E59: Nuevo | F59: Cerrado | H59: 45462 | I59: 45462 | J59: Wapsa Web | K59: 114413 | L59: 360 | M59: Cristian Pastor Artigas | N59: Wally reporta [Image] Poner IES en una misma lista 19/06 @Cristian Pastor Artigas Se corrige el script quitando restriccion de dias para atras para que utilice los lotes. Adjunto script. queda a la espera de formato para enviarlo. 08/07 @Cristian Pastor Artigas Enviado a TICA 18/07 @Cristian Pastor Artigas El correo no muestra el numero de IE | O59: Soporte
A60: 281 | B60: Ticket 363 - Mina - Despachos - Columna Estado Diferencia muestra datos no relacionados entre si | C60: Ticket | D60: WAPSA\Sprint - Julio - 2024 | F60: Cerrado | H60: 45482 | I60: 45482 | J60: Wapsa web | L60: 363 | M60: Cristian Pastor Artigas | N60: Wally Reporta: [Image] SI no hay diferencias no deberia indicar ESTADO DIF PESO TARA = Aprobado deberia decir DENTRO DEL RANGO | O60: Soporte
A61: 282 | B61: Ticket 364 - Callao - Lista de Despachos - El filtro por IE's en estado abierto no muestra las que tiene peso = 0 | C61: Ticket | D61: WAPSA\Sprint - Agosto - 2024 | F61: Cerrado | G61: [Ver. 2.17] | H61: 45482 | I61: 45482 | J61: Wapsa Web | L61: 364 | M61: Cristian Pastor Artigas | N61: Wally Reporta [Image] 09/07 @Cristian Pastor Artigas Corregido. Se agrega archivo script a la espera de enviar correcion a TICA | O61: Soporte
A62: 255 | B62: Ticket 358 - Informacion sobre propuesta de mejoras para los Pases a produccion, tickets y ambientes de pruebas | C62: Ticket | D62: WAPSA\Sprint - Junio 2024 | E62: Nuevo | F62: Cerrado | H62: 45454 | I62: 45455 | L62: 358 | M62: Cristian Pastor Artigas | N62: Nicolas solicitar completar infromacion resulotante de uan reunion con Chnalco sobre propuestas de mejoras acerca de los Pases a produccion, tickets y ambientes de pruebas [Image] 11/06 @Cristian Pastor Artigas Reunion con NV y DM para revisar propuestas de mejoras. 12/06 @Cristian Pastor Artigas Se envian propuestas a evaluacion de NV | O62: Soporte
A63: 242 | B63: Ticket 349 - Mina -Stock- Error al registrar Stock Mina el valor del TMH del dia anterior es incorrecto | C63: Ticket | D63: WAPSA\Sprint - Mayo -2024 | E63: Nuevo | F63: Cerrado | H63: 45433 | I63: 45433 | L63: 349 | M63: Cristian Pastor Artigas | N63: [Image] 21/05 @Cristian Pastor Artigas Hay un diferencia de 54.86 debido a que un despacho fue registrado con producto=Molibdeno Nro Guia=T018-0006837 21/05 @Cristian Pastor Artigas Se corrige el despacho cambiando el producto por cobre | O63: Soporte
A64: 308 | B64: Ticket 372 - Modulo Mina - Pesaje Manual - Mejora-Ver vagones observados | C64: Ticket | D64: WAPSA\Sprint - Octubre - 2024 | E64: Nuevo | F64: Cerrado | G64: [Ver. 2.18] | H64: 45548 | J64: WAPSA | L64: 372 | M64: Cristian Pastor Artigas | N64: Descripción: En la lista de vagones que han sido aprobadospara no destarar (pesaje manual), se debe agregar el detalle de los vagonesobservados. [Image] El usuario requiere que por cada item se despliegue un menu con una opción que diga "Ver Vagones Observados" - Este mostrará un pop up donde se listará los vagones observados según el registro. Solución: | O64: Soporte
A65: 311 | B65: Ticket 375 - Modulo Pesaje - Vagones observados - no filtra por los estados | C65: Ticket | D65: WAPSA\Sprint - Octubre - 2024 | E65: Nuevo | F65: Cerrado | G65: [Ver. 2.18] | H65: 45541 | I65: 45544 | J65: Web application | L65: 375 | M65: Cristian Pastor Artigas | N65: Descripción: En la pestaña de vagones observados no estáfiltrando correctamente, por ejemplo en Setiembre 2024 se tiene varios vagones pendientesd aprobación por parte del supervisor pero solo aparecen cuando se colocatodos. [Image] Solución: | O65: Soporte
A66: 309 | B66: Ticket 373 - Modulo Mina - Pesaje - Mejora correos supervisores | C66: Ticket | D66: WAPSA\Sprint - Octubre - 2024 | E66: Nuevo | F66: Cerrado | G66: [Ver. 2.18] | H66: 45546 | I66: 45546 | J66: WAPSA web | L66: 373 | M66: Cristian Pastor Artigas | N66: Descripción: * Si hay algo pendiente de aprobación en vagonesobservados debe llegar un correo a los supervisores mina a modo derecordatorio. Este ejemplo es uso de precinto duplicado mesagosto 2024 [Image] Se requiere tener un job para poder reenviar el correo de recordatorio cada 72 h Solución: | O66: Soporte
A67: 312 | B67: Ticket 376 - Modulo Pesaje - Registro cambio check auto/manual peso tara | C67: Ticket | D67: WAPSA\Sprint - Octubre - 2024 | E67: Nuevo | F67: Cerrado | G67: [Ver. 2.18] | H67: 45540 | I67: 45540 | J67: Web Application | L67: 376 | M67: Cristian Pastor Artigas | N67: Descripción: Cuando el usuario ya tiene un registro de pesaje en estado "Peso Bruto/Tara" y este pertenece a un grupo de "Pesaje Manual" el sistema te permite cambiar en la balanza a "Auto" lo cual no debería permitir ya que este puede cambiar el guardado del registro [Image] Solución: @Cristian Pastor Artigas Se revisa caso y se comprueba que las guia generadas durante los pesaje manuales estan correctas; quizas se necesaria una reunion con Carlos Zenteno para comentar este tema. Adjunto Excel con comprobaciones De momento se cierra Ticket. | O67: Soporte
A68: 315 | B68: Ticket 378 - Wapsa - TICA solicita documentación sobre Wapsa | C68: Ticket | D68: WAPSA\Sprint - Septiembre - 2024 | E68: Nuevo | F68: Cerrado | H68: 45541 | J68: WapsaWeb | L68: 378 | M68: Cristian Pastor Artigas | N68: TICA solicita: [Image] 06/09 @Cristian Pastor Artigas Se envia parte de lam documentacion, resta enviar Diagrma de Arquitectura de Wapsa 09/09 @Cristian Pastor Artigas Se envia Documentacion de Arquitectura de Wapsa | O68: Soporte
A69: 246 | B69: Ticket 353 - Mina - Lista de Despachos-Se generó un registro duplicado al preasignar vagón por intervención del usuario | C69: Ticket | D69: WAPSA\Sprint - Septiembre - 2024 | E69: Nuevo | F69: Cerrado | G69: [Ver. 2.17] | H69: 45439 | J69: Wapsa Web | L69: 353 | M69: Cristian Pastor Artigas | N69: Carlos Zenteno reporta: Se tuvo inconveniente con el Wapsa al ingresar pre asignado al guardar un vagon 10008 se demoraba en cargar lo actualice el sistema y generó 2 lotes con el mismo vagon y precinto como se observa en la imagen. [Image] 30/05 @Cristian Pastor Artigas Se replica el caso en Testing. Diagnóstico: el registro se genera al dar dos clicks seguido al boton guardar. Solucion: Se debe bloquear el boton a dar el guardar. Se debe corregir en versión. 30/05 @Cristian Pastor Artigas Corregido en PR 185: Ticket 307 Ticket 346 Ticket 308 . Se tagea Ticket a version 2.17 | O69: Soporte
A70: 310 | B70: Ticket 374 - Modulo Pesaje - Vagones Observados esta mal la descripción del estado | C70: Ticket | D70: WAPSA\Sprint - Septiembre - 2024 | E70: Nuevo | F70: Resuelto | H70: 45547 | I70: 45547 | J70: Web Application | L70: 374 | M70: Cristian Pastor Artigas | N70: Descripción: Al ingresar al detalle de un vagón en vagonesobservados, el punto: “Estado Dif. Peso Tara Supervisor: DENTRO DELRANGO” debe indicar “NO APROBADO” [Image] Revisar porque esta registrandose con ese estado Solución: | O70: Soporte
A71: 234 | B71: Ticket 344 - Alerta despachos pesos 0 no manda datos sobre las IE's | C71: Ticket | D71: WAPSA\Sprint - Junio 2024 | E71: Repetitivo-en-proceso | F71: Cerrado | H71: 45411 | J71: Wapsa Web | K71: 109586 | L71: 344 | M71: Cristian Pastor Artigas | N71: [Image] @Frank Macavilca la IE en cuestion no ha cumplido los 7 dias de registrada hasta la fecha y pos eso no sale en el listado [Image] 04/06 @Cristian Pastor Artigas Se corrige listado para que filtre correctamnete utilizando los lotes actual y el anterior. Se enviara como tikcet. Se envia un formato para firma de AM 11/06 @Cristian Pastor Artigas AM Envia docuemento firmado. Se adjunta 11/06 @Cristian Pastor Artigas Wally solicita en reunion del 11/06, que el listado incluya un lote mas hacia atras del tiempo. Se haran los cambios. S emueve Ticket a estado en Desarrollo 11/06 @Cristian Pastor Artigas Se agrega cambio al script y se envia a TICA 12/06/2023 13:24 pm | O71: Soporte
A72: 247 | B72: Ticket 354-Callao-Lista Despachos-Poblema en ajuste en línea R24-010 - MAYO (Resuelto reimportando) | C72: Ticket | D72: WAPSA\Sprint - Mayo -2024 | E72: Nuevo | F72: Cerrado | H72: 45439 | I72: 45470 | J72: Wapsa Web | L72: 354 | M72: Frank Macavilca | N72: Diego Cardenas Reporta: [Image] [Image] | O72: Soporte
A73: 300 | B73: Ticket 372 - Wapsa Movil - Actualización de Apk en los equipos de Callao(Cotecna) | C73: Ticket | D73: WAPSA\Sprint - Agosto - 2024 | E73: Nuevo | F73: Cerrado | H73: 45527 | I73: 45530 | L73: 372 | M73: Cristian Pastor Artigas | N73: Se inslara el dia Lunes 26/08 | O73: Soporte
A74: 292 | B74: Ticket 369 - Error de bloqueo de algunas tablas de la base de datos Wapsa (Lock) | C74: Ticket | D74: WAPSA\Sprint - Julio - 2024 | F74: Cerrado | H74: 45497 | I74: 45497 | L74: 369 | M74: Cristian Pastor Artigas | N74: Los usuario inidcan que no pueden realizar transacciones sobre el Wapsa. En reunion con se detecta que un usuario que accedio al parece tiene un proceso bloqueado lo que ocasiona bloqueo sobre los demas. EL DBA desbloquea los accesos para que puedan contiuar operando | O74: Soporte
A75: 276 | B75: Ticket 362 - Callao - Lista de Despachos - No se puede Cerrar IE | C75: Ticket | D75: WAPSA\Sprint - Julio - 2024 | E75: Nuevo | F75: Cerrado | H75: 45476 | I75: 45476 | J75: Wapsa Web | L75: 362 | M75: Cristian Pastor Artigas | N75: Wally reporta: [Image] | O75: Soporte
A76: 284 | B76: Ticket 365 - Alerta envio correo IE diferencias pesos TMH Solo envia 1 IE | C76: Ticket | D76: WAPSA\Sprint - Julio - 2024 | E76: Nuevo | F76: Cerrado | H76: 45488 | J76: Wapsa Web | L76: 365 | M76: Cristian Pastor Artigas | N76: Wally Moscoso Reporta [Image] | O76: Soporte
A77: 305 | B77: Ticket 373 - Callao - Asignacion - Ruma no visualizada en el listado para Muestreo | C77: Ticket | D77: WAPSA\Sprint - Agosto - 2024 | E77: Nuevo | F77: Cerrado | H77: 45529 | I77: 45529 | J77: Wapsa Web | L77: 373 | M77: Frank Macavilca | N77: Luis casas reporta Que una ruma nose visualiza en: [Image] 25/08 @Frank Macavilca Solucionado. Configuración de tipo muestro para el almacen modulo "Configuración - Conf. Tipo Muestreo" | O77: Soporte
A78: 325 | B78: Ticket 381 - Wapsa - Callao - Correccion en el listado de vagones disponibles para cuadre | C78: Ticket | D78: WAPSA\Sprint - Octubre - 2024 | E78: Nuevo | F78: Resuelto | H78: 45553 | I78: 45553 | J78: Wapsa Web | K78: 118649 | L78: 381 | M78: Cristian Pastor Artigas | N78: Carlos Linares Reporta que en Callao-Cuadre no lista vagones con inspeccion Esta correccion fue realizada en el pase a produccion de la version Wapsa v2.17 | O78: Soporte
A79: 214 | B79: Ticket 327 - Error en Month Evidence historico de Ruma R24-002 | C79: Ticket | D79: WAPSA\Sprint - Marzo 2024 | F79: Cerrado | H79: 45369 | J79: Wapsa | L79: 315 | M79: Cristian Pastor Artigas | N79: [Image] La ruma 45 es parte del historico de la ruma 002 19/03 @Cristian Pastor Artigas se envia para firmas de Alejandro | O79: Soporte
A80: 199 | B80: Ticket 318 - Aprobacion Inspeccion Vagones | C80: Ticket | D80: WAPSA\Sprint - Febrero 2024 | E80: Nuevo | F80: Cerrado | G80: Consulta | H80: 45327 | I80: 45327 | J80: WAPSA web | L80: 318 | M80: Frank Macavilca | N80: Descripción: El sgte vagón fueaprobado por Edwin Rios, sin embargo, sale mi usuario como si hubiese aprobadola observación. Favor podrían revisar que paso [Image] Solución: En la situación situ diste aprobar primero con esa aprobación se queda el registro asi el otrousuario aprobó luego se queda con tu usuario. Revisando el códigono vemos algún cambio y vemos los otros registros que están siendo guardadoscorrectamente. | O80: Soporte
A81: 204 | B81: Ticket 323 - WAPSA - Modulo impresion ED anulación error | C81: Ticket | D81: WAPSA\Sprint - Febrero 2024 | F81: Cerrado | G81: Consulta | H81: 45331 | I81: 45331 | J81: WAPSA web | L81: 323 | M81: Cristian Pastor Artigas | N81: Descripción: El usuario indica que se tiene una guía en el modulo de entrega directa que se genero correctamente la GRE pero visualmente se ve en el wapsa como estado anulado y sin fecha de impresión Solución: Se verifico el caso y el usuario dio dos veces click ocasionando un error en el WAPSA | O81: Soporte
A82: 205 | B82: Ticket 323 - Wapsa Reporte Asignacion - Muestra el valor incorrecto de TMH Guia T018-0001621 | C82: Ticket | D82: WAPSA\Sprint - Febrero 2024 | F82: Cerrado | H82: 45334 | I82: 45334 | L82: 323 | M82: Cristian Pastor Artigas | N82: Ticket 323 - Wapsa Reporte Asignacion - Muestra el valor incorrecto de TMH Guia T018-0001621 -El reporte suma de forma incorrecta el TMS por esta duplicada la Guia T018-0001621 en Entregas directas. -Se corrige modificando en entrega directa la Guia T018-0001621 a estado =0 | O82: Soporte
A83: 208 | B83: Ticket 325 - El mail de inspección Mina-Callao muestra los checks de inspección incorrectamente | C83: Ticket | D83: WAPSA\Sprint - Marzo 2024 | F83: Cerrado | G83: [Ver.2.14] | H83: 45343 | J83: Wapsa | K83: 100721 | L83: 325 | M83: Cristian Pastor Artigas | N83: Michael Curi ha reportado: [Image][Image] Ticket 325 - El mail de inspección Mina-Callao muestra los checks de inspección incorrectamente El orden en el que se muetran los checks de la inspección dentro del mail no coincide con el de Wapsa. 22/02 Se detecta que tambien ocurre en inspeccion Mina 22/02 Se corrige y se envia formato a Alejandro para la firma y eviarlo como Ticket @Cristian Pastor Artigas 27/02 Se envia Ticket a TICA @Cristian Pastor Artigas 01/03 Alexander envia Ticket a la Mesa de Servicios @Cristian Pastor Artigas 04/03 Se consulta por el estado del Ticker no se obtiene respuesta @Cristian Pastor Artigas 11/03 Se consulta por el estado del Ticker no se obtiene respuesta @Cristian Pastor Artigas | O83: Soporte
A84: 215 | B84: Ticket 329 - Error al listar Stock de Mina | C84: Ticket | D84: WAPSA\Sprint - Marzo 2024 | F84: Cerrado | H84: 45370 | J84: Wapsa | K84: 328 | M84: Frank Macavilca | N84: [Image] 19/03 @Frank Macavilca Detecta que un error en la conexion de Wapsa con la base de datos del servidor PIServer. Se envia correo a Alexander para que verifique esta conexion 25/03 Error fue de la conexión que se tiene con PIServer | O84: Soporte
A85: 206 | B85: Ticket 323 - Wapsa - Callao Muestreo: Se registaron guias con lote CC2402 en vez de CC2401 | C85: Ticket | D85: WAPSA\Sprint - Febrero 2024 | F85: Cerrado | G85: Consulta | H85: 45337 | I85: 45337 | L85: 323 | M85: Cristian Pastor Artigas | N85: [Image] 15/05: Revisar listado de guia; LC inidca que tiene fecha de muestreo del lote CC2402 pero el sistema asigno lote CC2402 15/05: Se revisa el listado y el muestreo se grabo entre las 8 y 8:30 am del dia 26/04 por ende el sistema le asigno el lote 2402 | O85: Soporte
A86: 168 | B86: Ticket 297 - Modulo Callao - Stock Callao - Error valores en TMS | C86: Ticket | D86: WAPSA\Sprint - Febrero 2024 | E86: Nuevo | F86: Cerrado | G86: [Ver.2.13] | H86: 45315 | I86: 45324 | J86: WAPSA web | K86: 96077 | L86: 297 | M86: Cristian Pastor Artigas | N86: /Descripción: Stock Callao (revisará MM). Pendiente Michael tiene que enviar los valores correctos Actualización 29/01: Michael reviso testing, comenta que el resumen en TMS la suma de las rumas no da el resultado total. El Valor final que sale del TMS se debe ver reflejado como valor inicial en el siguiente mes Solución: 31/01/2024 Se tiene solucion del ticket. Se envia formato para firma de Alejandro @Cristian Pastor Artigas 31/10/2023 En firmas Por TICA | O86: Soporte
A87: 172 | B87: Ticket 290 - Modulo Callao - El Wapsa permitió grabar un Numero de Guía Electrónica con la letra T en minúscula en Volteo | C87: Ticket | D87: WAPSA\Sprint - Enero 2024 | E87: Nuevo | F87: Cerrado | G87: [Ver.2.13] | H87: 45315 | I87: 45317 | J87: WAPSA web | K87: #96873 | L87: 290 | M87: Cristian Pastor Artigas | N87: Descripción: El Wapsa permitió grabar un Numero de Guía Electrónica con la letra T en minúscula en Volteo Solución: | O87: Soporte
A88: 170 | B88: Ticket 291 - Modulo Callao - Mail de inspección observada en Callao sin data (mail en blanco) | C88: Ticket | D88: WAPSA\Sprint - Enero 2024 | E88: Nuevo | F88: Cerrado | G88: [Ver.2.13] | H88: 45314 | I88: 45317 | J88: WAPSA web | K88: #97296 | L88: 291 | M88: Cristian Pastor Artigas | N88: Descripción: Mail de inspección observada en Callao sin data (mail en blanco) Solución: | O88: Soporte
A89: 209 | B89: Ticket 326 - Modulo Mina - Stock - la lista demora aprox 8 mintos para mostrar la informacion | C89: Ticket | D89: WAPSA\Sprint - Febrero 2024 | F89: Cerrado | H89: 45348 | I89: 45349 | L89: 326 | M89: Cristian Pastor Artigas | N89: Jorge Garcia reporta que no carga la pantalla del stock Diario. 26/02 Se revisa listado se valida indexado y se envia correo a Jorge para verficar si ya se corrgió el listado @Cristian Pastor Artigas | O89: Soporte
A90: 202 | B90: Ticket 321 - Modulo Callao - Volteo- Diferencia pesos brutosMina-Callao no esta evaluando correctamente cuando es mayor al factor | C90: Ticket | D90: WAPSA\Sprint - Febrero 2024 | F90: Cerrado | G90: [Ver.2.14] | H90: 45329 | K90: WAPSA web | L90: 320 | M90: Cristian Pastor Artigas | N90: Descripción: Modulo Callao - Volteo- Diferencia pesos brutosMina-Callao no esta evaluando correctamente cuando es mayor al factor Solución: Se cambio lógica para corregir este error | O90: Soporte
A91: 201 | B91: Ticket 320 - Modulo Mina - pesaje - Diferencia pesos tara no esta evaluando correctamente cuando es mayor al factor | C91: Ticket | D91: WAPSA\Sprint - Febrero 2024 | E91: Nuevo | F91: Cerrado | G91: [Ver.2.14] | H91: 45329 | K91: WAPSA web | L91: 320 | M91: Frank Macavilca | N91: Descripción: Modulo Mina - pesaje - Diferencia pesos tara no esta evaluando correctamente cuando es mayor al factor Solución: Se cambio lógica para corregir este error | O91: Soporte
A92: 198 | B92: Ticket 319 - Modulo Mina - Mover opciones de aprobacion por guia a la pestaña de observados | C92: Ticket | D92: WAPSA\Sprint - Febrero 2024 | F92: Cerrado | G92: [Ver.2.14] | H92: 45315 | J92: WAPSA web | L92: 296 | M92: Cristian Pastor Artigas | N92: Descripción: Mina/despacho: mover las opciones de click derecho referidas a aprobaciones a la pestaña de observados Solución: Se mueven botones de de aprobaciones a pestaña de observados | O92: Soporte
A93: 164 | B93: Ticket 293 - Modulo mina - los adjuntos para Diferencia de peso tara se estan guardando mal | C93: Ticket | D93: WAPSA\Sprint - Febrero 2024 | E93: Nuevo | F93: Cerrado | G93: [Ver.2.14] | H93: 45315 | J93: WAPSA web | L93: 293 | M93: Cristian Pastor Artigas | N93: Descripción: Mina/despacho: Los casos revisados son de diferencia de peso Tara, los adjuntos se están grabando en Peso Bruto (corregir) Solución: Se realiza correccion @Cristian Pastor Artigas 13/02 Pendiente revisión | O93: Soporte
A94: 165 | B94: Ticket 294 - Modulo Mina - Vista de Vagones observados no filtra ni exporta correctamente | C94: Ticket | D94: WAPSA\Sprint - Febrero 2024 | E94: Nuevo | F94: Cerrado | G94: [Ver.2.14] | H94: 45315 | J94: WAPSA web | L94: 294 | M94: Cristian Pastor Artigas | N94: Descripción: Mina/despacho, vagones observados: No se exporta por completo la lista de vagones despachados observados // vista de aprobación de pesaje manual bruto y tara Solución: Correccion realizada @Cristian Pastor Artigas | O94: Soporte
A95: 195 | B95: Ticket 316 - Modulo Mina - No deja adjuntar las evidencias para duplicidad de precintos | C95: Ticket | D95: WAPSA\Sprint - Febrero 2024 | E95: Nuevo | F95: Cerrado | G95: [Ver.2.14] | H95: 45321 | J95: WAPSA web | L95: 316 | M95: Cristian Pastor Artigas | N95: Descripción: Modulo Mina - No deja adjuntar las evidencias para duplicidad de precintos Solución: @Cristian Pastor Artigas Se implementa el cambio, en espera de programar pase | O95: Soporte
A96: 174 | B96: Ticket 301 - Modulo Callao - DIFERENCIA DE PESOS BRUTOS CALLAO | C96: Ticket | D96: WAPSA\Sprint - Febrero 2024 | E96: Nuevo | F96: Cerrado | G96: [Ver.2.14] | H96: 45315 | J96: WAPSA web | L96: 301 | M96: Cristian Pastor Artigas | N96: Descripción: Hola Cristian después del primer caso de diferencia de pesos (marcado en amarillo), el Wapsa no ha reconocido lo 03 siguientes que figuran en la siguiente lista. Pf revisar urgente que paso. Nota: veo que la única diferencia es la guía electrónica (T).. [Image] [Image] Solución: Se fuerza el cambio del valor iDisplayLength a = 10000 para el método ObtenerListaVolteoObsAlmacenDetallePaginado | O96: Soporte
A97: 162 | B97: Ticket 292 - Error proceso aprobación pesaje Manual - Mina | C97: Ticket | D97: WAPSA\Sprint - Febrero 2024 | E97: Nuevo | F97: Cerrado | G97: [Ver.2.14] | H97: 45315 | I97: 45315 | J97: WAPSA web | L97: 292 | M97: Cristian Pastor Artigas | N97: Descripción: No se puede aprobar o rechazar desde el mail el pesaje manual automático (no funciona al dar click de aprobar o rechazar) | O97: Soporte
A98: 231 | B98: Ticket 341 - Cerrar IE Arrow 198/23 - No se puede por el WAPSA | C98: Ticket | D98: WAPSA\Sprint - Mayo -2024 | E98: Nuevo | F98: Cerrado | H98: 45406 | I98: 45433 | J98: WAPSA Web | L98: 341 | M98: Frank Macavilca | N98: Descripción: Se requiere que la IE "Arrow 198/23" se pueda cerrar. Actualmente no se puede porque no contiene datos y se tiene un validación que solo se puede cerrar una vez cumpla las condiciones de tener pesos y humedades completas Solución: 21/05 @Cristian Pastor Artigas Cerrada via Wapsa | O98: Soporte
A99: 212 | B99: Ticket 327 - Correccion error al hacer la aprobacion de Pesaje Manual Módulo | C99: Ticket | D99: WAPSA\Sprint - Marzo 2024 | F99: Cerrado | G99: [Ver. 2.15] | H99: 45356 | J99: Wapsa web | L99: 327 | M99: Cristian Pastor Artigas | N99: Wally inidca que al aprobar por el correo el Pesaje Manual no cambia de estado. 08/03: Se corrige error de parobacion @Cristian Pastor Artigas 11/03: Se envia a testing para prueba rapida esta ok @Cristian Pastor Artigas | O99: Soporte
A100: 211 | B100: Ticket 330 - El registro de Pesaje de Mina Muestra ventana de diferencias de peso tara al momento de preasignar | C100: Ticket | D100: WAPSA\Sprint - Marzo 2024 | F100: Cerrado | G100: [Ver. 2.15] | H100: 45356 | J100: WAPSA web | L100: 326 | M100: Cristian Pastor Artigas | N100: [Image] 05/03 Error al momento de oreasignar | O100: Soporte
...

Sheet Hoja2
A1: ID | B1: Work Item Type | C1: Title | D1: Iteration Path | E1: Estados | F1: Tags | G1: Start Date | H1: Finish Date | I1: Finish Date Chinalco | J1: Aplicación | K1: Ticket Chinalco | L1: Ticket SyC | M1: Assigned To | N1: Description | O1: Tipo Caso | P1: Tipo Evento | Q1: Tipo Estabilización | R1: Parent | S1: Epic
A2: 191 | B2: Ticket | C2: Ticket 312 - Proyecto WAPSA 2024 - 1 - Ajuste final y Repeso total | D2: WAPSA\Sprint - Septiembre- 2025 | E2: Nuevo | G2: 31/8/2025 7:00:00 p. m. | H2: 14/9/2025 7:00:00 p. m. | I2: 28/12/2025 7:00:00 p. m. | J2: WAPSA web | L2: 312 | N2: Ajuste final y Repeso total 1.1 Ajuste final Modificar lógica para creación de ajuste para validar lo siguiente: al realizar el ajuste la fecha y hora debe ser mayor al último movimiento (ingreso, salida, junta). Modificar la UI para mostrar el mensaje y consumir la validación Realizar pruebas 1.2 REPESO TOTAL Modificar lógica para creación de ajuste para validar lo siguiente: al realizar el ajuste la fecha y hora debe ser mayor al último movimiento (ingreso, salida, junta). Modificar la UI para mostrar el mensaje y consumir la validación Realizar pruebas 1.3 Validaciones adicionales Crear validacion para poder crear un bloqueo de pesos en tmh si se genera un "Ajuste en TMH" Crear validacion para poder crear un bloqueo de pesos en tms si se genera un "Ajuste en TMS" Modificar cada punto de creación de pesos (TMH,TMS) para consumir la validación Modifcar la UI para consumir estas validaciones Realizar pruebas | O2: Nuevo | P2: Requerimiento Nuevo-Area Comercial | Q2: No implica estabilización | R2: 251 | S2: =VLOOKUP(R2,Epics!A:B,2,FALSE) -> Proyecto WAPSA 2024 - 3
A3: 194 | B3: Ticket | C3: Ticket 315 - Wapsa - Proyecto WAPSA 2024 - 1 - Mejoras Logs | D3: WAPSA\Sprint - Octubre - 2025 | E3: Cerrado | F3: [Ver 2.25] | G3: 4/9/2024 7:00:00 p. m. | H3: 7/10/2025 1:54:00 p. m. | I3: 7/10/2025 1:54:00 p. m. | J3: WAPSA web | L3: 315 | M3: Frank Macavilca <dmacavilca@syc-sistemas.com> | N3: Modulo Log 1.1 Listado Log Mejorar el performance del modulo de logs es demasiado lento Desarrollar funcioanlidad para guardar los datos del request cuadno se realizan ejemplo si se guardan leyes que valores estan siendo enviados al WAPSA para grabarse. Modificar scripts para soportar esta nueva columna que obtendrá los datos de datos enviados Crear nuevas tablas para manejar las llaves y adjuntos Modificar la UI para poder ver esta nueva columna Realizar pruebas | O3: Nuevo | P3: Requerimiento Nuevo-Area Comercial | Q3: No implica estabilización | R3: 251 | S3: =VLOOKUP(R3,Epics!A:B,2,FALSE) -> Proyecto WAPSA 2024 - 3
A4: 183 | B4: Ticket | C4: Ticket 304 - Proyecto WAPSA 2024 - 1 - Modificar Proceso Lista despacho | D4: WAPSA\Sprint - Marzo - 2026 | E4: Nuevo | J4: WAPSA web | L4: 304 | N4: Descripción: 1.1 Pesos Lista Despacho Modicar codigo en el momento que se modifiquen pesos se deben eliminar las leyes y humedades existentes. Modificar UI para consumir nuevo proceso Realizar pruebas 1.2 Humedades Lista Despacho Modicar codigo en el momento que se modifiquen pesos se deben eliminar las leyes. Modificar UI para consumir nuevo proceso Realizar pruebas Solución: | O4: Nuevo | P4: Requerimiento Nuevo-Area Comercial | Q4: No implica estabilización | R4: 251 | S4: =VLOOKUP(R4,Epics!A:B,2,FALSE) -> Proyecto WAPSA 2024 - 3
A5: 185 | B5: Ticket | C5: Ticket 306 - Proyecto WAPSA 2024 - 1 - Mantenimiento Equipos-Pesajes | D5: WAPSA\Sprint - Marzo - 2026 | E5: Nuevo | J5: WAPSA web | L5: 306 | N5: Mantenimiento de tablas 1.1 Registro de Equipos Registro de los equipos Configurar cuenta de correo 1.2 Mantenimiento de tablas Tipos de mantenimiento Tipos de averias Empresas Ubicación Registro de la programación 2.1 Registro de programación Registro de programación Registro de evidencias Envío de la notificación 2.2 Registro de mantenimiento correctivo Registro del evento Registro de las evidencias Reportes Reporte de programación Reporte de Mantenimiento Correctivo | O5: Nuevo | P5: Requerimiento Nuevo-Area Comercial | Q5: No implica estabilización | R5: 251 | S5: =VLOOKUP(R5,Epics!A:B,2,FALSE) -> Proyecto WAPSA 2024 - 3
A6: 189 | B6: Ticket | C6: Ticket 310 - Proyecto WAPSA 2024 - 1 - Arribo a Mina y a Callao con GPS | D6: WAPSA\Sprint - Marzo - 2026 | E6: Nuevo | J6: WAPSA web | L6: 310 | N6: Crear una API 1.1 Crear proceso automatico para leer datos del GPS Creacion de scripts Desarrollo del codigo con logica 1.2 Modificar el wapsa Modificar el WAPSA para soportar una lectura del gps o manual Realizar pruebas | O6: Nuevo | P6: Requerimiento Nuevo-Area Comercial | Q6: No implica estabilización | R6: 251 | S6: =VLOOKUP(R6,Epics!A:B,2,FALSE) -> Proyecto WAPSA 2024 - 3
A7: 223 | B7: Ticket | C7: Ticket 333 - Wapsa - General - Proyecto Wapsa - Rountrip con GPS | D7: WAPSA\Sprint - Marzo - 2026 | E7: Nuevo | G7: 9/4/2024 7:00:00 p. m. | J7: Wapsa Web | K7: 333 | N7: 10/04 @Cristian Pastor Artigas Reunion con el proveedor CLS Peru en la cual se concretaron los siguientes puntos: -En la aplicacion de CLS que le permite a MIna monitorear los vagones via GPS se registrar el Nro de Guia de Remision en el campo conductor, de momento manualmente lo hara el equipo de Edwin Rios MCP. -El equipo de Edwin registrara la guias desde el Jueves 11/04 hasta el dia lunes para que luego de eso SyC Sistemas podra 15/04 consultar utilizando el API. -EL dia 15/04 SyC probara haciendo consultas utilizando el API para devolver los datos filtrando por el campo conductor-Guia de remision, -La proxima reunion sera el dia 18 o 19/04 -Se concretara una reunion con Wally a posterior para ver internamnete en Wapsa cuales seran las mejoras una vez podamos consultar la informacion correctamnete desde el API -CLS indico cual es la documentacion que se debe consultar. https://sdk.wialon.com/wiki/en/sidebar/remoteapi/apiref/report/cleanup_result @Cristian Pastor Artigas Video de la reunion en los adjuntos del Ticket 15/04 Edwin Rios inidca que ya se esta cargando los Numeros de Guias desde Mina 16/04 @Cristian Pastor Artigas Se envia consulta a la Empresa del GPS para consultar sobre como obtener los ID's para obtener lueo los reportes 23/04 @Cristian Pastor Artigas CLS responde mail enviando las credenciales de acceso 29/04 @Cristian Pastor Artigas Se envia consulta a CLS porque no se puede obtener la informacion de los puntos del GPS , se solicita reunion | O7: Nuevo | P7: Requerimiento Nuevo-Area Comercial | Q7: No implica estabilización | R7: 251 | S7: =VLOOKUP(R7,Epics!A:B,2,FALSE) -> Proyecto WAPSA 2024 - 3
A8: 248 | B8: Ticket | C8: Ticket 355 Wapsa - General - Proyecto - Agregar grupos de Ensayo en Wapsa | D8: WAPSA\Sprint - Agosto - 2025 | E8: Cerrado | F8: [Ver 2.25] | G8: 2/6/2025 7:00:00 p. m. | H8: 4/8/2025 7:00:00 p. m. | I8: 7/10/2025 1:53:00 p. m. | J8: Wapsa Web | L8: 355 | M8: Cristian Pastor Artigas <cartigas@syc-sistemas.com> | N8: Luis Casas solicita: En la transmision de leyes de Cotecna e importacion: - Habilitar 4 columnas de información en el reporte de H2OyLey Callao de Wapsa; grupos (G1,G2,G3,G4) para recibir la data de Cotecna - Generar el maestro: "Grupos de análisis" para seleccionar a qué grupo pertenece cada analito. - Actualizar el reporte en Excel de H2OyLey Callao incluyendo los Grupos. - Habilitar las 4 columnas en el dashboard (HumedadesyLeyes) 28/05 @Cristian Pastor Artigas Se adjunta documento resultante de la reunion | O8: Nuevo | P8: Requerimiento Nuevo-Area Comercial | Q8: No implica estabilización | R8: 251 | S8: =VLOOKUP(R8,Epics!A:B,2,FALSE) -> Proyecto WAPSA 2024 - 3
A9: 458 | B9: Ticket | C9: Ticket 445- Wapsa - General - Pase a Produccion Wapsa Ver. 2.24 | D9: WAPSA\Sprint - Septiembre- 2025 | E9: Cerrado | F9: [Ver 2.24] | G9: 25/7/2025 5:14:00 p. m. | H9: 25/7/2025 5:14:00 p. m. | I9: 1/9/2025 6:21:00 a. m. | J9: Wapsa Web | L9: 445 | M9: Cristian Pastor Artigas <cartigas@syc-sistemas.com> | N9: Ticket de Soporte: Ticket 443 - Error al listar vagones en arribo mina en el detalle https://dev.azure.com/SycSistemas/WAPSA/_boards/board/t/WAPSA%20Team/Stories?workitem=456 Ticket 442 - Wapsa - Stock Callao - Error en calculo de TMH en listado detalle por día https://dev.azure.com/SycSistemas/WAPSA/_boards/board/t/WAPSA%20Team/Stories?workitem=450 Ticket 440- Wapsa - Mina - UBICACIÓN DE VAGONES - Corrección Listado de Vagones https://dev.azure.com/SycSistemas/WAPSA/_boards/board/t/WAPSA%20Team/Stories?workitem=445 Ticket 441- Wapsa - Mina - Stock - Revisión Lentitud Listado https://dev.azure.com/SycSistemas/WAPSA/_boards/board/t/WAPSA%20Team/Stories?workitem=446 Ticket de Proyectos: Ticket 444- Wapsa - Mina - Pesaje - Lectura del peso utilizando api de PI Server https://dev.azure.com/SycSistemas/WAPSA/_boards/board/t/WAPSA%20Team/Stories?workitem=455 Ticket 425 - Wapsa - Ruma - ENVIÓ DE DATA DE RUMA Y EJE A IMPALA https://dev.azure.com/SycSistemas/WAPSA/_boards/board/t/WAPSA%20Team/Stories?workitem=415 Ticket 429 - Wapsa- General - G. Codigo Establecimiento por cada serie https://dev.azure.com/SycSistemas/WAPSA/_boards/board/t/WAPSA%20Team/Stories?workitem=458 Para Ticket Ticket 429: Crear los codigos de establecimiento en Datos Rumas Guias de Remision Cargar 0000 en todos los clientes Impresion txt: 603 1001 Activacion Impresion por pantalla de TXT GRE PRINTX true IOAV 247 1001 Alerta de Aprobación Ejes de Ruma AAJR NULL ALER Ticket 425 Alerta de Aprobación Ejes de Ruma Destinatarios arios DER artigasc@gmail.com,melendezyessi@gmail.com,a@gmail.com DRE 0 0 1 0 NULL 2025-05-23 19:50:25.433 Chinalco dbWapsa2 2025-05-23 19:45:56.863 WAPSA 0 NULL 0 0 0 0 NULL Para ticket 444 Crear nueovo maestro Tipo Conexión Balanza Mina Datos Conexión Balanza Mina <add key="HostApiPISERVER" value="http://10.251.3.51:8081/last_value" /> <add key="UserApiPISERVER" value="user_wapsa01" /> <add key="PassApiPISERVER" value="GkXpLZ&amp;d66LNAGGPyeS5&amp;m" /> <add key="tagB1" value="PL:245WIT0064_TON_DCS" /> <add key="tagB2" value="PL:400WIT2064_TON_DCS" /> Crear ejes de descarga hasta el 30 Permisos PARA TODO: | O9: Repetitivo-en-proceso | P9: Requerimiento Nuevo-Area Comercial | Q9: No implica estabilización | R9: 252 | S9: =VLOOKUP(R9,Epics!A:B,2,FALSE) -> Pases a Producción
A10: 285 | B10: Ticket | C10: Ticket 366 - Wapsa - General - Solicitud de Pase a Producción Wapsa/WapsaUE v2.17 | D10: WAPSA\Sprint - Septiembre - 2024 | E10: Cerrado | F10: [Ver. 2.17] | G10: 14/7/2024 7:00:00 p. m. | H10: 14/7/2024 7:00:00 p. m. | I10: 26/8/2024 7:00:00 p. m. | J10: Wapsa Web | K10: 102342 | L10: 366 | M10: Cristian Pastor Artigas <cartigas@syc-sistemas.com> | N10: Pase a producción Wapsa V 2.17 Ticket 307 - Proyecto WAPSA 2024 - 2 - Mejoras en el cuadre en Wapsa https://dev.azure.com/SycSistemas/WAPSA/_boards/board/t/WAPSA%20Team/Stories/?workitem=186 Ticket 353 - Mina - Lista de Despachos-Se generó un registro duplicado al preasignar vagón por intervención del usuario https://dev.azure.com/SycSistemas/WAPSA/_boards/board/t/WAPSA%20Team/Stories/?workitem=246 Ticket 346 - Guias Electronicas - Proyecto Mejoras WAPSA - 2 - Nuevo Modulo "Emisión de Guias Impala 01" https://dev.azure.com/SycSistemas/WAPSA/_boards/board/t/WAPSA%20Team/Stories/?workitem=236 Ticket 364 - Callao - Lista de Despachos - El filtro por IE's en estado abierto no muestra las que tiene peso = 0 https://dev.azure.com/SycSistemas/WAPSA/_boards/board/t/WAPSA%20Team/Stories/?workitem=282 Ticket 347 - Guias Electronicas - Proyecto Mejoras WAPSA - 2 - GRE Impresión Guías - Hipervinculos https://dev.azure.com/SycSistemas/WAPSA/_boards/board/t/WAPSA%20Team/Stories/?workitem=237 15/07 @Cristian Pastor Artigas Creando documentos 16/07 @Cristian Pastor Artigas Se envia para firmas de AM 18/07 @Cristian Pastor Artigas Enviado a TICA | O10: Nuevo | P10: Requerimiento Nuevo-Area Comercial | Q10: No implica estabilización | R10: 252 | S10: =VLOOKUP(R10,Epics!A:B,2,FALSE) -> Pases a Producción
A11: 316 | B11: Ticket | C11: Ticket 379 - Wapsa - General - Solicitud de Pase a Producción Wapsa/WapsaUE v2.18 | D11: WAPSA\Sprint - Octubre - 2024 | E11: Cerrado | F11: [Ver. 2.18] | G11: 9/9/2024 7:00:00 p. m. | H11: 9/9/2024 7:00:00 p. m. | I11: 14/10/2024 7:00:00 p. m. | J11: Wapsa Web | K11: 120145 | L11: 379 | M11: Cristian Pastor Artigas <cartigas@syc-sistemas.com> | N11: Pase a producción Wapsa V 2.18 Ticket 302 - Guias Electronicas - Proyecto Mejoras WAPSA - 2 - Entregas Directas - Cambiar como se registra el destinatario, que no sea desde el maestro. https://dev.azure.com/SycSistemas/WAPSA/_boards/board/t/WAPSA%20Team/Stories/?workitem=178 Ticket 372 - Modulo Mina - Pesaje Manual - Mejora-Ver vagones observados https://dev.azure.com/SycSistemas/WAPSA/_boards/board/t/WAPSA%20Team/Stories/?workitem=308 Ticket 373 - Modulo Mina - Pesaje - Mejora correos supervisores https://dev.azure.com/SycSistemas/WAPSA/_boards/board/t/WAPSA%20Team/Stories/?workitem=309 Ticket 375 - Modulo Pesaje - Vagones observados - no filtra por los estados https://dev.azure.com/SycSistemas/WAPSA/_boards/board/t/WAPSA%20Team/Stories/?workitem=311 Ticket 376 - Modulo Pesaje - Registro cambio check auto/manual peso tara https://dev.azure.com/SycSistemas/WAPSA/_boards/board/t/WAPSA%20Team/Stories/?workitem=312 Ticket 383 - Callao - Volteo - Link para descargar PDF en Guias Electronicas | O11: Nuevo | P11: Requerimiento Nuevo-Area Comercial | Q11: No implica estabilización | R11: 252 | S11: =VLOOKUP(R11,Epics!A:B,2,FALSE) -> Pases a Producción
A12: 490 | B12: Ticket | C12: Ticket 458 - Wapsa - General - Pase a Produccion Wapsa v2.25 | D12: WAPSA\Sprint - Noviembre - 2025 | E12: Cerrado | F12: [Ver 2.25] | G12: 3/10/2025 8:28:00 a. m. | H12: 7/10/2025 1:48:00 p. m. | I12: 29/10/2025 4:49:00 a. m. | J12: Wapsa Web | L12: 458 | M12: Cristian Pastor Artigas <cartigas@syc-sistemas.com> | N12: Ticket 451 - Wapsa - Arribo - Ejes Ruma - No se envian los QR dentro del email https://dev.azure.com/SycSistemas/WAPSA/_boards/board/t/WAPSA%20Team/Stories?System.IterationPath=%40currentIteration&workitem=480 Ticket 450 - Wapsa - Ruma - Popup de Ejes de ve muy abajo https://dev.azure.com/SycSistemas/WAPSA/_boards/board/t/WAPSA%20Team/Stories?System.IterationPath=%40currentIteration&workitem=474 Ticket 449 - Wapsa -Monitor - Modificar Monitor Venta y crear Ventas por Evidence https://dev.azure.com/SycSistemas/WAPSA/_boards/board/t/WAPSA%20Team/Stories?System.IterationPath=%40currentIteration&workitem=474 Ticket 428 - F. Grupos de Análisis-Nuevos requerimientos (relacion Ticket 355) https://dev.azure.com/SycSistemas/WAPSA/_boards/board/t/WAPSA%20Team/Stories?System.IterationPath=%40currentIteration&workitem=418 Ticket 424 -Wapsa -General - Ajuste final https://dev.azure.com/SycSistemas/WAPSA/_boards/board/t/WAPSA%20Team/Stories?System.IterationPath=%40currentIteration&workitem=414 Ticket 315 - Wapsa - Proyecto WAPSA 2024 - 1 - Mejoras Logs https://dev.azure.com/SycSistemas/WAPSA/_boards/board/t/WAPSA%20Team/Stories?workitem=194 Ticket 453 - Envio datos WAPSA-SAP https://dev.azure.com/SycSistemas/WAPSA/_boards/board/t/WAPSA%20Team/Stories?workitem=485 | O12: Nuevo | P12: Requerimiento Nuevo-Area Comercial | Q12: Estabilización por proyecto | R12: 252 | S12: =VLOOKUP(R12,Epics!A:B,2,FALSE) -> Pases a Producción
A13: 491 | B13: Ticket | C13: Ticket 459 - Wapsa - General - Pase a Produccion Wapsa ES v4.1 | D13: WAPSA\Sprint - Noviembre - 2025 | E13: Cerrado | F13: [Ver 4.1] | G13: 7/10/2025 1:56:00 p. m. | H13: 7/10/2025 1:56:00 p. m. | I13: 29/10/2025 4:49:00 a. m. | J13: Wapsa ES | L13: 459 | M13: Cristian Pastor Artigas <cartigas@syc-sistemas.com> | N13: Ticket 403 - Wapsa ES - GRE's - Validar que existan datos de balanzas en Wapsa cuando se crea la GRE https://dev.azure.com/SycSistemas/WAPSA/_boards/board/t/WAPSA%20Team/Stories?System.IterationPath=%40currentIteration&workitem=378 Ticket 357 - WapsaES - G. Codigo Establecimiento por cada serie - Caso Impala Wapsa ES https://dev.azure.com/SycSistemas/WAPSA/_boards/board/t/WAPSA%20Team/Stories?System.IterationPath=%40currentIteration&workitem=431 Ticket 385 - Wapsa ES - General - Proyecto 2024 - Crear API para recibir/ver informacion de Grupo Ensayos (Relacion con Ticket 355) https://dev.azure.com/SycSistemas/WAPSA/_boards/board/t/WAPSA%20Team/Stories?System.IterationPath=%40currentIteration&workitem=345 Ticket 453 - Wapsa - Envio datos WAPSA-SAP https://dev.azure.com/SycSistemas/WAPSA/_boards/board/t/WAPSA%20Team/Stories?workitem=485 | O13: Nuevo | P13: Requerimiento Nuevo-Area Comercial | Q13: Estabilización de req. de Mantenimiento | R13: 252 | S13: =VLOOKUP(R13,Epics!A:B,2,FALSE) -> Pases a Producción
A14: 235 | B14: Ticket | C14: Ticket 345 - Wapsa - General - Solicitud de Pase a Producción Wapsa/WapsaUE v2.16 | D14: WAPSA\Sprint - Mayo -2024 | E14: Cerrado | F14: [Ver. 2.16] | G14: 2/5/2024 7:00:00 p. m. | H14: 19/5/2024 7:00:00 p. m. | I14: 14/5/2024 7:00:00 p. m. | J14: Wapsa Web | L14: 345 | M14: Cristian Pastor Artigas <cartigas@syc-sistemas.com> | N14: Pase a producción Wapsa V 2.16 Ticket 330 https://dev.azure.com/SycSistemas/WAPSA/_boards/board/t/WAPSA%20Team/Stories/?workitem=218 Ticket 340 https://dev.azure.com/SycSistemas/WAPSA/_workitems/edit/230 Ticket 339 https://dev.azure.com/SycSistemas/WAPSA/_workitems/edit/229 Ticket 331 https://dev.azure.com/SycSistemas/WAPSA/_workitems/edit/219 Ticket 338 https://dev.azure.com/SycSistemas/WAPSA/_workitems/edit/228 03/05 @Cristian Pastor Artigas se crea y se envía documentación para firmas de AM 03/05 @Cristian Pastor Artigas se envia pase a producción 10/05 @Cristian Pastor Artigas Se sube archivo de Manual de Usuario Actualizado 15/05 @Cristian Pastor Artigas Se suben sustentos Casos de prueba, y Alexander envia scripts a DBA para su ejecucion del pase final, a la espera de definir dia | O14: Nuevo | P14: Requerimiento Nuevo-Area Comercial | Q14: No implica estabilización | R14: 252 | S14: =VLOOKUP(R14,Epics!A:B,2,FALSE) -> Pases a Producción
A15: 245 | B15: Ticket | C15: Ticket 351 - Wapsa - General - Solicitud de Pase a Producción Wapsa/WapsaUE v2.16.1 | D15: WAPSA\Sprint - Mayo -2024 | E15: Cerrado | F15: [2.16.1] | G15: 2/5/2024 7:00:00 p. m. | H15: 28/5/2024 7:00:00 p. m. | I15: 26/5/2024 7:00:00 p. m. | J15: Wapsa Web | L15: 351 | M15: Cristian Pastor Artigas <cartigas@syc-sistemas.com> | N15: Pase a producción Wapsa V 2.16.1 Ticket 350 https://dev.azure.com/SycSistemas/WAPSA/_boards/board/t/WAPSA%20Team/Stories/?workitem=243 Ticket 352 https://dev.azure.com/SycSistemas/WAPSA/_boards/board/t/WAPSA%20Team/Stories/?workitem=244 22/05 @Cristian Pastor Artigas se crea y se envía documentación para firmas de AM 23/05 @Cristian Pastor Artigas Enviado a TICA 27/05 @Cristian Pastor Artigas WM adjunta evidencias de pruebas. Se esta a la espera de definir por parte de TICA el dia y hora de hacer los cambios en producción 29/05 @Cristian Pastor Artigas Cerrado | O15: Nuevo | P15: S&C Sistemas | Q15: Estabilización por proyecto | R15: 252 | S15: =VLOOKUP(R15,Epics!A:B,2,FALSE) -> Pases a Producción
A16: 213 | B16: Ticket | C16: Ticket 326 - Wapsa - General - Pase a Produccion Wapsa/WapsaUE v2.15 | D16: WAPSA\Sprint - Marzo 2024 | E16: Cerrado | F16: [Ver. 2.15] | G16: 13/3/2024 7:00:00 p. m. | H16: 13/3/2024 7:00:00 p. m. | I16: 21/3/2024 7:00:00 p. m. | J16: Wapsa | K16: 102342 | L16: 326 | M16: Cristian Pastor Artigas <cartigas@syc-sistemas.com> | N16: Pase a produccion Version 2.15 Ticket 303 - Proyecto WAPSA 2024 - 1 - Mejoras Embarque a Granel "Extraporturario" Lista despacho. Ticket 305 - Proyecto WAPSA 2024 - 1 - Mejoras Reporte TMH, TMS, HUMEDAD Lista despacho.  Ticket 326 - El registro de Pesaje de Mina Muestra ventana de diferencias de peso tara al momento de preasignar. Ticket 313 - Proyecto WAPSA 2024 - 1 - Aprobación Supervisor por la diferencia de peso tara en mina. Ticket 327 - Corrección error al hacer la aprobación de Pesaje Manual Módulo. Ticket 314 - Proyecto WAPSA 2024 - 1 - Alerta Lista Despacho. 14/03 Se envian documentos para firma de AM @Cristian Pastor Artigas 18/03 AM responde documentos firmados 18/03 Se envia Ticket a TICA para iniciar pase @Cristian Pastor Artigas 20/03 TICA pasa a testing 20/03 Wally revisa y envia correcciones sobre los tickets #192 y #182 20/03 TICA asigna ticket MCP #102342 | O16: Nuevo | P16: Requerimiento Nuevo-Area Comercial | Q16: No implica estabilización | R16: 252 | S16: =VLOOKUP(R16,Epics!A:B,2,FALSE) -> Pases a Producción
A17: 523 | B17: Ticket | C17: Ticket 481 - Wapsa - Pase a Produccion Wapsa v2.28 y WapsaES Ver.4.7 | D17: WAPSA\Sprint - Marzo - 2026 | E17: En Proceso firmas | G17: 20/2/2026 10:19:00 a. m. | L17: 481 | M17: Cristian Pastor Artigas <cartigas@syc-sistemas.com> | N17: Ticket 471 - Wapsa - SAP Envio de datos https://dev.azure.com/SycSistemas/WAPSA/_boards/board/t/WAPSA%20Team/Stories?workitem=507 | O17: Nuevo | P17: S&C Sistemas | Q17: No implica estabilización | R17: 252 | S17: =VLOOKUP(R17,Epics!A:B,2,FALSE) -> Pases a Producción
A18: 410 | B18: Ticket | C18: Ticket 420 - Wapsa - General - Pase a Produccion Wapsa v2.21 Mantenimiento Feb-2025 | D18: WAPSA\Sprint - Marzo - 2025 | E18: Cerrado | F18: [Ver. 2.21] | G18: 16/2/2025 7:00:00 p. m. | H18: 27/2/2025 7:00:00 p. m. | I18: 12/3/2025 7:00:00 p. m. | J18: Wapsa Web | L18: 420 | M18: Cristian Pastor Artigas <cartigas@syc-sistemas.com> | N18: Pase a producción Wapsa V 2.21: Ticket 415 - Wapsa - Callao - Inspeccion - No lista los vagones observados en estado pendiente https://dev.azure.com/SycSistemas/WAPSA/_boards/board/t/WAPSA%20Team/Stories/?workitem=398 Ticket 404- Wapsa - Mina- Despacho - Correo de Dif Peso Tara del Supervisor debe indicar la palabra Supervisor en el asunto https://dev.azure.com/SycSistemas/WAPSA/_boards/board/t/WAPSA%20Team/Stories/?workitem=380 Ticket 414 - Wapsa - Mina - Despacho - Error al intentar al preasignar despacho (Bloqueo de tablas) https://dev.azure.com/SycSistemas/WAPSA/_boards/board/t/WAPSA%20Team/Stories/?workitem=397 Ticket 412 - Wapsa - Mina - Cambiar orden de detalle de convoy para que se muestre por fecha de inspeccion https://dev.azure.com/SycSistemas/WAPSA/_boards/board/t/WAPSA%20Team/Stories/?workitem=391 Ticket 413 - Wapsa - Mina - Agregar columna en la vista y excel que se muestre el precinto de salida Callao (Precinto Cotecna) https://dev.azure.com/SycSistemas/WAPSA/_boards/board/t/WAPSA%20Team/Stories/?workitem=392 | O18: Nuevo | P18: Requerimiento Nuevo-Area Comercial | Q18: No implica estabilización | R18: 252 | S18: =VLOOKUP(R18,Epics!A:B,2,FALSE) -> Pases a Producción
A19: 434 | B19: Ticket | C19: Ticket 434 - Wapsa - General - Pase a Produccion v2.22 - Proyectos Parte 1 | D19: WAPSA\Sprint - Junio - 2025 | E19: Cerrado | F19: [Ver. 2.22] | G19: 24/4/2025 7:00:00 p. m. | H19: 27/4/2025 7:00:00 p. m. | I19: 2/6/2025 7:00:00 p. m. | J19: Wapsa Web | L19: 434 | M19: Cristian Pastor Artigas <cartigas@syc-sistemas.com> | N19: Pase a producción Wapsa V 2.22: Ticket 432- Wapsa - Mina - Despacho - Solicitar 3 adjuntos como minimo al subir evidencias de peso tara manual por evento https://dev.azure.com/SycSistemas/WAPSA/_boards/board/t/WAPSA%20Team/Stories?workitem=432 Ticket 423 - Wapsa - Mina - Pesaje - Modulo Mina - Filtros- Quitar Preautorizados https://dev.azure.com/SycSistemas/WAPSA/_boards/board/t/WAPSA%20Team/Stories?workitem=413 Ticket 422 - Wapsa - Mina - Pesaje - Modulo Mina Pesaje Manual (tara y bruto) supervisor por evento https://dev.azure.com/SycSistemas/WAPSA/_boards/board/t/WAPSA%20Team/Stories?workitem=180 | O19: Nuevo | P19: Requerimiento Nuevo-Area Comercial | Q19: No implica estabilización | R19: 252 | S19: =VLOOKUP(R19,Epics!A:B,2,FALSE) -> Pases a Producción
A20: 441 | B20: Ticket | C20: Ticket 437 - Wapsa - General - Pase a Produccion v2.23 - Nuevo Tipo de GRE "Otros" | D20: WAPSA\Sprint - Junio - 2025 | E20: Cerrado | F20: [Ver. 2.23] | G20: 11/6/2025 8:44:00 a. m. | H20: 11/6/2025 8:44:00 a. m. | I20: 24/6/2025 10:18:00 a. m. | J20: Wapsa Web | L20: 437 | M20: Cristian Pastor Artigas <cartigas@syc-sistemas.com> | N20: Pase a producción Wapsa V 2.23: Ticket 436 - Implementar nuevo caso GRE "Otros" https://dev.azure.com/SycSistemas/WAPSA/_workitems/edit/440 | O20: Nuevo | P20: Requerimiento Nuevo-Area Comercial | Q20: No implica estabilización | R20: 252 | S20: =VLOOKUP(R20,Epics!A:B,2,FALSE) -> Pases a Producción
A21: 442 | B21: Ticket | C21: Ticket 438 - WapsaES - General - Pase a Produccion v4.0 - Nuevo Tipo de GRE "Otros" | D21: WAPSA\Sprint - Junio - 2025 | E21: Cerrado | F21: [Ver 4.0] | G21: 11/6/2025 8:44:00 a. m. | H21: 11/6/2025 8:44:00 a. m. | I21: 19/6/2025 7:00:00 p. m. | J21: Wapsa Web | L21: 437 | M21: Cristian Pastor Artigas <cartigas@syc-sistemas.com> | N21: Pase a producción Wapsa V 2.23: Ticket 436 - Implementar nuevo caso GRE "Otros" https://dev.azure.com/SycSistemas/WAPSA/_workitems/edit/440 | O21: Nuevo | P21: Requerimiento Nuevo-Area Comercial | Q21: No implica estabilización | R21: 252 | S21: =VLOOKUP(R21,Epics!A:B,2,FALSE) -> Pases a Producción
A22: 200 | B22: Ticket | C22: Ticket 318-1 - Wapsa - General - Pase a Producción Wapsa Ver 2.14 | D22: WAPSA\Sprint - Febrero 2024 | E22: Cerrado | F22: [Ver.2.14] | G22: 5/2/2024 7:00:00 p. m. | H22: 3/3/2024 7:00:00 p. m. | I22: 4/3/2024 7:00:00 p. m. | J22: Wapsa Web | K22: #100230 | L22: 319 | M22: Cristian Pastor Artigas <cartigas@syc-sistemas.com> | N22: Pase a produción Wapsa UE y Wapsa Ticket 319 - Modulo Mina - Mover opciones de aprobación por guía a la pestaña de observados Ticket 295 - Modulo Mina Pesaje - Nuevo filtro en la vista de vagones observados Ticket 293 - Modulo mina - los adjuntos para Diferencia de peso tara se estan guardando mal Ticket 294 - Modulo Mina - Vista de Vagones observados no filtra ni exporta correctamente Ticket 316 - Modulo Mina - No deja adjuntar las evidencias para duplicidad de precintos Ticket 301 - Modulo Callao - DIFERENCIA DE PESOS BRUTOS CALLAO Ticket 296 - Modulo Callao Lista Despacho - Corregir "ITEM" cuando das click en ver "Detalle" por una IE 5/02: Recibidos documentos firmado por Alejandro 6/02: Documentos y mail enviados a TICA 9/02: Disponible en Testing para las pruebas 12/02: Pruebas con Wally: -Volteo: Solo se tomará en cuenta para obervar el vagon si es que los pesos brutos si es que la diferencia de pesos de Callao y Mina es inferior al factor. -Inspeccion callao: Correccion de error al agregar sustento al editar el vagon . PR 169: Cambio de Factor y correccion adjuntar editar vagon inspeccion 13/02 Revision con WM se aprueban todas las correciones del CP Se solicita corregir un texto en la evidencias del pesaje de mina 14/02 Correccion texto en la evidencias del pesaje de mina PR 170: Correcciones para texto en adjuntos y corregir error de adjuntado en diferencia de pesos mina 16/02 Se envian a Wally las evidencias del pase. Quedamos a la espera de una ultima prueba al pesaje por parte de Wally para cerrar el pase 19/02 Se solicita a Julio que envie el link para que Wally suba las evidencias. Se queda la espera de fecha del pase 23//02 Alexander asigna el pase a Produccion a Saul para que inidque el dia y hora. 26/02 El pase es reasignado a Julio, en un mail indica que esta por firmas de documentos. 27/02 @Cristian Pastor Artigas Se solicita actualizacion de estado del pase 01/03 Julio realiza pase pero solo de Wapsa falta WapsaEU @Cristian Pastor Artigas | O22: Nuevo | P22: Requerimiento Nuevo-Area Comercial | Q22: No implica estabilización | R22: 252 | S22: =VLOOKUP(R22,Epics!A:B,2,FALSE) -> Pases a Producción
A23: 207 | B23: Ticket | C23: Ticket 324 - Wapsa ES - General - Pase a Produccion Wapsa Servicio Ver. 2.4 | D23: WAPSA\Sprint - Febrero 2024 | E23: Cerrado | F23: [Ver.2.4] | G23: 15/2/2024 7:00:00 p. m. | H23: 20/2/2024 7:00:00 p. m. | I23: 21/2/2024 7:00:00 p. m. | J23: Wapsa ES | L23: 324 | M23: Cristian Pastor Artigas <cartigas@syc-sistemas.com> | N23: Pase a Produccion Wapsa Servicio Ver. 2.4 15/02: Se moven cambio para preparar version PR 171: Correccion servicio ver 2.4 16/02: @Cristian Pastor Artigas Se envian formatos a firma de AM 20/02 Aprobo Alexander el pase 22/02 TICA realizo el pase a Produccion son documentacion de casos de pruebas @Cristian Pastor Artigas | O23: Nuevo | P23: Requerimiento Nuevo-Area Comercial | Q23: No implica estabilización | R23: 252 | S23: =VLOOKUP(R23,Epics!A:B,2,FALSE) -> Pases a Producción
A24: 508 | B24: Ticket | C24: Ticket 472 - Wapsa - General - Pase a Produccion Wapsa v2.27 | D24: WAPSA\Sprint - Enero - 2026 | E24: Cerrado | G24: 28/12/2025 7:00:00 p. m. | H24: 31/12/2025 3:41:00 p. m. | I24: 23/1/2026 3:41:00 p. m. | J24: Wapsa Web | K24: 166255 | L24: 472 | M24: Cristian Pastor Artigas <cartigas@syc-sistemas.com> | N24: Ticket 471 - Wapsa - SAP Envio de datos https://dev.azure.com/SycSistemas/WAPSA/_boards/board/t/WAPSA%20Team/Stories?workitem=507 | O24: Nuevo | P24: S&C Sistemas | Q24: No implica estabilización | R24: 252 | S24: =VLOOKUP(R24,Epics!A:B,2,FALSE) -> Pases a Producción
A25: 509 | B25: Ticket | C25: Ticket 473 - WapsaES - General - Pase a Produccion Wapsa v4.6 | D25: WAPSA\Sprint - Enero - 2026 | E25: Cerrado | G25: 28/12/2025 7:00:00 p. m. | H25: 30/12/2025 7:00:00 p. m. | I25: 23/1/2026 3:44:00 p. m. | J25: Wapsa ES | K25: 166255 | L25: 473 | M25: Cristian Pastor Artigas <cartigas@syc-sistemas.com> | N25: Ticket 471 - Wapsa - SAP Envio de datos https://dev.azure.com/SycSistemas/WAPSA/_boards/board/t/WAPSA%20Team/Stories?workitem=507 | O25: Nuevo | P25: Requerimiento Nuevo-Area Comercial | Q25: No implica estabilización | R25: 252 | S25: =VLOOKUP(R25,Epics!A:B,2,FALSE) -> Pases a Producción
A26: 505 | B26: Ticket | C26: Ticket 469 - Wapsa - Pase a producción Fix. Operaciones Stock v2.25.3 | D26: WAPSA\Sprint - Diciembre - 2025 | E26: Cerrado | F26: v2.25.3 | G26: 27/11/2025 7:00:00 p. m. | H26: 1/12/2025 2:11:00 p. m. | J26: Wapsa Web | L26: 469 | O26: Nuevo | P26: S&C Sistemas | Q26: Estabilización de req. de Mantenimiento | R26: 252 | S26: =VLOOKUP(R26,Epics!A:B,2,FALSE) -> Pases a Producción
A27: 506 | B27: Ticket | C27: Ticket 470 - Wapsa - General - Pase a Produccion Wapsa v2.26 | D27: WAPSA\Sprint - Diciembre - 2025 | E27: Cerrado | G27: 1/12/2025 10:18:00 a. m. | H27: 30/11/2025 7:00:00 p. m. | I27: 4/12/2025 7:00:00 p. m. | L27: 470 | M27: Cristian Pastor Artigas <cartigas@syc-sistemas.com> | N27: Ticket 460 - Wapsa - Mina - Politica de reintentos/Cambio Conexion al momento de captura de peso Mina https://dev.azure.com/SycSistemas/WAPSA/_workitems/edit/492 Ticket 467 - Wapsa - Habilitar las 4 columnas en el dashboard (HumedadesyLeyes) X https://dev.azure.com/SycSistemas/WAPSA/_boards/board/t/WAPSA%20Team/Stories?workitem=506 Ticket 466 - Wapsa - Monitor - Ajuste en sumatoria de totales de Dashboard de Despachos X https://dev.azure.com/SycSistemas/WAPSA/_boards/board/t/WAPSA%20Team/Stories?workitem=502 Ticket 462 - Wapsa - Callao - Nuevas columas Reporte de H2OyLey Callao https://dev.azure.com/SycSistemas/WAPSA/_boards/board/t/WAPSA%20Team/Stories?workitem=497 Ticket 461 - Wapsa - Mina - Revision Correlativo de Sublote Pesaje https://dev.azure.com/SycSistemas/WAPSA/_boards/board/t/WAPSA%20Team/Stories?workitem=499 Ticket 464 - Wapsa - Gestor de Guias de Remision - Filtro Otros https://dev.azure.com/SycSistemas/WAPSA/_boards/board/t/WAPSA%20Team/Stories?workitem=500 | O27: Nuevo | P27: S&C Sistemas | Q27: No implica estabilización | R27: 252 | S27: =VLOOKUP(R27,Epics!A:B,2,FALSE) -> Pases a Producción
A28: 369 | B28: Ticket | C28: Ticket 400 - Wapsa - General - Pase a Produccion Wapsa v2.19 | D28: WAPSA\Sprint - Diciembre - 2024 | E28: Cerrado | F28: [Ver. 2.19] | G28: 2/12/2024 7:00:00 p. m. | H28: 2/12/2024 7:00:00 p. m. | I28: 29/12/2024 7:00:00 p. m. | J28: Wapsa Web | K28: 126994 | L28: 400 | M28: Cristian Pastor Artigas <cartigas@syc-sistemas.com> | N28: Pase a producción Wapsa V 2.19: Ticket 393 - Wapsa - Mina - Wapsa no debe permitir registrar pesos al momento de preasignar y mejorar columnas del listado https://dev.azure.com/SycSistemas/WAPSA/_boards/board/t/WAPSA%20Team/Stories/?workitem=355 PR 216: Ticket 393 - Wapsa - Mina - Wapsa no debe permitir registrar pesos al momento de preasignar y mejorar columnas del listado Ticket 387 - Wapsa - Callao- Asignacion- La reasignación no se genera correctamente y no se muestra en los reportes de stock https://dev.azure.com/SycSistemas/WAPSA/_boards/board/t/WAPSA%20Team/Stories/?workitem=347 PR 217: Ticket 387 - Wapsa - Callao- Asignacion- La reasignación no se genera correctamente y no se muestra en los reportes de stock Ticket 396 - Wapsa - Mina - Agregar Vagones sin destare por pesaje manual Lote CT 2410 https://dev.azure.com/SycSistemas/WAPSA/_boards/board/t/WAPSA%20Team/Stories/?workitem=361 Ticket 394 Wapsa - Callao - Operaciones - Ventana de error al listar de la pestaña operaciones https://dev.azure.com/SycSistemas/WAPSA/_boards/board/t/WAPSA%20Team/Stories/?workitem=359 PR 218: Ticket 394 Wapsa - Callao - Operaciones - Ventana de error al listar de la pestaña operaciones Ticket 398 - Wapsa - Mina - Mejorar ventanas de bloqueo/cargando al registrar o actualizar un pesaje https://dev.azure.com/SycSistemas/WAPSA/_boards/board/t/WAPSA%20Team/Stories/?workitem=367 PR 220: Ticket 398 - Wapsa - Mina - Mejorar ventanas de bloqueo/cargando al registrar o actualizar un pesaje Ticket 395 - Wapsa - Mina- Despacho - Error al intentar asignar peso tara a un despacho (Bloqueo de tablas) https://dev.azure.com/SycSistemas/WAPSA/_boards/board/t/WAPSA%20Team/Stories/?workitem=360 PR 219: Ticket 395 - Wapsa - Mina- Despacho - Error al intentar asignar peso tara a un despacho (Bloqueo de tablas) Ticket Incluido fuera de los formatos: Ticket 405 - Wapsa - Callao - Ajuste Mensual - No totaliza correctamente el TMS https://dev.azure.com/SycSistemas/WAPSA/_boards/board/t/WAPSA%20Team/Stories/?workitem=381 PR 222: Correccion para totalizar TMS ajuste mensual ! | O28: Nuevo | P28: Requerimiento Nuevo-Area Comercial | Q28: No implica estabilización | R28: 252 | S28: =VLOOKUP(R28,Epics!A:B,2,FALSE) -> Pases a Producción
A29: 385 | B29: Ticket | C29: Ticket 410 - Wapsa - General - Pase a Produccion Wapsa v2.20 | D29: WAPSA\Sprint - Diciembre - 2024 | E29: Cerrado | F29: [Ver. 2.20] | G29: 2/12/2024 7:00:00 p. m. | H29: 2/12/2024 7:00:00 p. m. | I29: 8/1/2025 7:00:00 p. m. | J29: Wapsa Web | L29: 410 | M29: Cristian Pastor Artigas <cartigas@syc-sistemas.com> | N29: Pase a producción Wapsa V 2.20: Ticket 409 - Callao - Traslado entre Estab.-Lista de Despachos - Error al importar despachos https://dev.azure.com/SycSistemas/WAPSA/_boards/board/t/WAPSA%20Team/Stories/?workitem=386 PR 223: Cambios bug fix TEE importar humedades | O29: Nuevo | P29: Requerimiento Nuevo-Area Comercial | Q29: No implica estabilización | R29: 252 | S29: =VLOOKUP(R29,Epics!A:B,2,FALSE) -> Pases a Producción
A30: 290 | B30: Ticket | C30: Ticket 367 - Wapsa Movil - General - Solicitud de Pase a Producción Servicio Movil Wapsa v1.1 | D30: WAPSA\Sprint - Agosto - 2024 | E30: Cerrado | F30: [Ver. 1.1] | G30: 17/7/2024 7:00:00 p. m. | H30: 17/7/2024 7:00:00 p. m. | I30: 7/8/2024 7:00:00 p. m. | J30: Wapsa Web | L30: 367 | M30: Cristian Pastor Artigas <cartigas@syc-sistemas.com> | N30: Pase a producción Servicio Movil Wapsa v1.1 Ticket 346 - Proyecto WAPSA 2024 - 2 - Mejoras en el Inspeccion WAPSA movil https://dev.azure.com/SycSistemas/WAPSA/_boards/board/t/WAPSA%20Team/Stories/?workitem=238 Ticket 308 - Proyecto WAPSA 2024 - 2 - Mejoras en el cuadre en Wapsa Movil https://dev.azure.com/SycSistemas/WAPSA/_boards/board/t/WAPSA%20Team/Stories/?workitem=187 18/07 @Cristian Pastor Artigas Se envia para firma de AM | O30: Nuevo | P30: Requerimiento Nuevo-Area Comercial | Q30: No implica estabilización | R30: 252 | S30: =VLOOKUP(R30,Epics!A:B,2,FALSE) -> Pases a Producción
A31: 314 | B31: Ticket | C31: Ticket 377 - Wapsa BI - General - Ejecución Manual - Resta copiar guias sin volteo en el reporte de datos de mina | D31: WAPSA\Sprint - Octubre - 2024 | E31: Cerrado | G31: 4/9/2024 7:00:00 p. m. | H31: 4/9/2024 7:00:00 p. m. | I31: 15/9/2024 7:00:00 p. m. | J31: Wapsa BI | K31: 118265 | L31: 377 | M31: Cristian Pastor Artigas <cartigas@syc-sistemas.com> | N31: Luis casas reporta: 1. Falta informacion de Pesos de mina en Reporte de Mina 05/09 @Cristian Pastor Artigas Para firmas | O31: Repetitivo-en-proceso | P31: S&C Sistemas | Q31: Estabilización por proyecto | R31: 253 | S31: =VLOOKUP(R31,Epics!A:B,2,FALSE) -> WAPSA BI
A32: 241 | B32: Ticket | C32: Ticket 348 - Wapsa BI - General - Valores repetidos en Reporte de Pesos y Leyes del BI | D32: WAPSA\Sprint - Mayo -2024 | E32: Cerrado | G32: 15/5/2024 7:00:00 p. m. | H32: 27/5/2024 7:00:00 p. m. | I32: 28/5/2024 7:00:00 p. m. | J32: Wapsa BI | K32: 107784 | L32: 348 | M32: Cristian Pastor Artigas <cartigas@syc-sistemas.com> | N32: Luis Casas inidca que la data del reporte se duplica por lote 15/05 @Cristian Pastor Artigas Se corrige script en BD BI y se prerara script para ejecucion manuald e Wapsa 16/05 @Cristian Pastor Artigas Se prepara formato de Ticket y se envia a AM 16/05 @Cristian Pastor Artigas Enviado a TICA 29/05 @Cristian Pastor Artigas Ejecutado y Cerrado | O32: Nuevo | P32: S&C Sistemas | Q32: Estabilización por proyecto | R32: 253 | S32: =VLOOKUP(R32,Epics!A:B,2,FALSE) -> WAPSA BI
A33: 169 | B33: Ticket | C33: Ticket 298 - WAPSA BI - General - Reproceso del dashboard del 01 al 07 enero | D33: WAPSA\Sprint - Marzo 2024 | E33: Cerrado | G33: 23/1/2024 7:00:00 p. m. | H33: 26/2/2024 7:00:00 p. m. | I33: 3/3/2024 7:00:00 p. m. | J33: WAPSA BI | L33: 298 | M33: Cristian Pastor Artigas <cartigas@syc-sistemas.com> | N33: Descripción: Reproceso del dashboard del 01 al 07 enero Sin permisos a la base de datos 30/01 Se tuvo problemas con el usuario 07/02 Se revisa y e total de Guias de enero coinciden con los de Wapsa Se programa reunion con Luis Casas para revisar su BI 08/02 Luego de la reunion se detecta que es un error de rango de fechas en la busqueda de datos en el Wapsa; se corrige y se deja ejecutando para el lote 2301 a la espera de la validacion de LC 16/02 Se tiene script pero el usaurio esta bloqueado para hacer las pruebas 27/02 Se envia script en base de BI y se validara en la siguiente ejecucion automatica. | O33: Nuevo | P33: S&C Sistemas | Q33: Estabilización por proyecto | R33: 253 | S33: =VLOOKUP(R33,Epics!A:B,2,FALSE) -> WAPSA BI
A34: 203 | B34: Ticket | C34: Ticket 322 - Wapsa BI - General - Reproceso de tabla de Humedades, pesos y leyes Correccion en Wapsa | D34: WAPSA\Sprint - Marzo 2024 | E34: Cerrado | G34: 8/2/2024 7:00:00 p. m. | H34: 8/2/2024 7:00:00 p. m. | I34: 18/3/2024 7:00:00 p. m. | J34: Wapsa BI | K34: 100715 | L34: 322 | M34: Cristian Pastor Artigas <cartigas@syc-sistemas.com> | N34: Ticket 322 - Wapsa BI - Reproceso de tabla de Humedades, pesos y leyes. Script de actualizacion de copia de datos para ejecucion a demanda de humedades, pesos y leyes 20/02 Este ticket depende del 298 se debe enviar el mismo script a Pord de Wapsa 27/02 Se preparan formatos para la firma y enviar ticket 29/02 Enviado a TICA @Cristian Pastor Artigas 01/03 Alexander envia Ticket a Mesa de Servicios @Cristian Pastor Artigas 04/03 Se consulta por el estado del Ticker no se obtiene respuesta @Cristian Pastor Artigas 11/03 Se consulta por el estado del Ticker no se obtiene respuesta @Cristian Pastor Artigas | O34: Nuevo | P34: Requerimiento Nuevo-Area Comercial | Q34: Estabilización por proyecto | R34: 253 | S34: =VLOOKUP(R34,Epics!A:B,2,FALSE) -> WAPSA BI
A35: 216 | B35: Ticket | C35: Ticket 328 - Wapsa BI - General - Error ejecucion a demanda Humedades, pesos y leyes | D35: WAPSA\Sprint - Abril -2024 | E35: Cerrado | G35: 18/3/2024 7:00:00 p. m. | H35: 18/3/2024 7:00:00 p. m. | I35: 1/4/2024 7:00:00 p. m. | J35: Wapsa BI | K35: 103122 | L35: 328 | M35: Cristian Pastor Artigas <cartigas@syc-sistemas.com> | N35: 19/03 Se envia para firma de Alejandro | O35: Nuevo | P35: S&C Sistemas | Q35: Estabilización por proyecto | R35: 253 | S35: =VLOOKUP(R35,Epics!A:B,2,FALSE) -> WAPSA BI
A36: 226 | B36: Ticket | C36: Ticket 336 - Wapsa BI - General - La ejecucion a demanda del reporte de BI de Pesos y Leyes no actualiza data | D36: WAPSA\Sprint - Abril -2024 | E36: Cerrado | G36: 14/4/2024 7:00:00 p. m. | H36: 3/5/2024 7:00:00 p. m. | I36: 3/5/2024 7:00:00 p. m. | J36: Wapsa BI | K36: 105868 | L36: 336 | M36: Cristian Pastor Artigas <cartigas@syc-sistemas.com> | N36: El error no se puede replicar en ningun ambiente. 10/04 @Cristian Pastor Artigas Por ende se solicita reunion a Alexander con el DBA 19/04 @Cristian Pastor Artigas Luego de la revision con el DBA se detecta que el script de mover datos de Wapsa a BI esta correcto, se concluye que la falta de data es un problema de logica del script 19/04 @Cristian Pastor Artigas Se soluciona error cambiando el filtro del script para utilizar a la fecha de proceso de MIna y no de Volteo 19/04 @Cristian Pastor Artigas Se preparara formato para enviar ticket 23/04 @Cristian Pastor Artigas Se envia formato para firma de Alejandro 24/04 @Cristian Pastor Artigas Se envio a TICA 01/05 @Cristian Pastor Artigas Alexander envia para formas internas 04/05 @Cristian Pastor Artigas Ticket Ejecutado | O36: Repetitivo-en-proceso | P36: S&C Sistemas | Q36: Estabilización por proyecto | R36: 253 | S36: =VLOOKUP(R36,Epics!A:B,2,FALSE) -> WAPSA BI
A37: 474 | B37: Ticket | C37: Ticket 449 - Wapsa -Monitor - Modificar Monitor Venta y crear Ventas por Evidence | D37: WAPSA\Sprint - Octubre - 2025 | E37: Cerrado | F37: [Ver 2.25] | G37: 11/9/2025 7:17:00 a. m. | H37: 7/10/2025 1:54:00 p. m. | I37: 7/10/2025 1:54:00 p. m. | J37: Wapsa Web | L37: 449 | M37: Cristian Pastor Artigas <cartigas@syc-sistemas.com> | O37: Nuevo | P37: Requerimiento Nuevo-Area Comercial | Q37: Estabilización de req. de Mantenimiento | R37: 457 | S37: =VLOOKUP(R37,Epics!A:B,2,FALSE) -> Proyecto WAPSA 2025 - 2
A38: 484 | B38: Ticket | C38: Ticket 452 - Guia Remisión Electronica nuevos casos | D38: WAPSA\Sprint - Marzo - 2026 | E38: Nuevo | J38: Wapsa Web | L38: 452 | N38: Descripción: | O38: Nuevo | P38: Requerimiento Nuevo-Area Comercial | Q38: No implica estabilización | R38: 457 | S38: =VLOOKUP(R38,Epics!A:B,2,FALSE) -> Proyecto WAPSA 2025 - 2
A39: 485 | B39: Ticket | C39: Ticket 453 - Wapsa - Envio datos WAPSA-SAP | D39: WAPSA\Sprint - Marzo - 2026 | E39: Cerrado | F39: [Ver 2.25] | G39: 30/9/2025 7:00:00 p. m. | H39: 7/10/2025 10:50:00 a. m. | I39: 7/10/2025 1:55:00 p. m. | J39: Wapsa Web | L39: 453 | M39: Frank Macavilca <dmacavilca@syc-sistemas.com> | N39: Descripción: Modulo Mina: Modulo Callao : Modulo Ejecución Manual Envió a SAP: | O39: Nuevo | P39: Requerimiento Nuevo-Area Comercial | Q39: No implica estabilización | R39: 457 | S39: =VLOOKUP(R39,Epics!A:B,2,FALSE) -> Proyecto WAPSA 2025 - 2
A40: 486 | B40: Ticket | C40: Ticket 454 - Guia Remisión Electronica nuevos casos | D40: WAPSA\Sprint - Marzo - 2026 | E40: Nuevo | J40: Wapsa Web | L40: 454 | N40: Descripción: | O40: Nuevo | P40: Requerimiento Nuevo-Area Comercial | Q40: No implica estabilización | R40: 457 | S40: =VLOOKUP(R40,Epics!A:B,2,FALSE) -> Proyecto WAPSA 2025 - 2
A41: 507 | B41: Ticket | C41: Ticket 471 - Wapsa - SAP Envio de datos | D41: WAPSA\Sprint - Marzo - 2026 | E41: Nuevo | F41: [Ver. 2.27]; [Ver. 2.28] | G41: 30/11/2025 7:00:00 p. m. | J41: Wapsa Web | L41: 471 | M41: Frank Macavilca <dmacavilca@syc-sistemas.com> | O41: Nuevo | P41: Requerimiento Nuevo-Area Comercial | Q41: No implica estabilización | R41: 457 | S41: =VLOOKUP(R41,Epics!A:B,2,FALSE) -> Proyecto WAPSA 2025 - 2
A42: 487 | B42: Ticket | C42: Ticket 455 - SAP FASE COMPLEMENTARIA | D42: WAPSA\Sprint - Diciembre - 2025 | E42: Resuelto | G42: 1/10/2025 7:00:00 p. m. | H42: 17/12/2025 7:00:00 p. m. | I42: 17/12/2025 7:00:00 p. m. | J42: Wapsa Web | L42: 455 | M42: Frank Macavilca <dmacavilca@syc-sistemas.com> | N42: Descripción: | O42: Nuevo | P42: Requerimiento Nuevo-Area Comercial | Q42: No implica estabilización | R42: 457 | S42: =VLOOKUP(R42,Epics!A:B,2,FALSE) -> Proyecto WAPSA 2025 - 2
A43: 455 | B43: Ticket | C43: Ticket 444- Wapsa - Mina - Pesaje - Lectura del peso utilizando api de PI Server | D43: WAPSA\Sprint - Agosto - 2025 | E43: Cerrado | F43: [Ver 2.24] | G43: 16/7/2025 5:26:00 p. m. | H43: 16/7/2025 5:26:00 p. m. | J43: Wapsa Web | L43: 444 | M43: Cristian Pastor Artigas <cartigas@syc-sistemas.com> | N43: Detalles de la API: Endpoint: http://10.251.3.51:8081/last_value Método: POST Body : { "tag": "PL:245WIT0064_TON_DCS" } Credenciales (Basic Auth): Usuario: user_wapsa01 Contraseña: GkXpLZ&d66LNAGGPyeS5&m Servidor: 10.251.3.51 Puerto: 8081 | O43: Nuevo | P43: Requerimiento Nuevo-Area Comercial | Q43: Estabilización de req. de Mantenimiento | R43: 457 | S43: =VLOOKUP(R43,Epics!A:B,2,FALSE) -> Proyecto WAPSA 2025 - 2
A44: 186 | B44: Ticket | C44: Ticket 307 - Wapsa - Callao - Cuadre - Proyecto WAPSA 2024 - 2 - Mejoras en el cuadre en Wapsa | D44: WAPSA\Sprint - Septiembre - 2024 | E44: Cerrado | F44: [Ver. 2.17] | G44: 5/5/2024 7:00:00 p. m. | H44: 12/5/2024 7:00:00 p. m. | I44: 9/5/2024 7:00:00 p. m. | J44: WAPSA Web | L44: 307 | M44: Cristian Pastor Artigas <cartigas@syc-sistemas.com> | N44: 1.1 Callao-Cuadre scripts Modificación de scripts 1.2 Callao-Cuadre interfaz Modificar interfaz para colocar la columna(Ruma) nuevas en la grilla Modificar "input select" para filtrar solo vagones en arribo y agregar al vagon la ruma Pruebas Logs Modificar script del log para mostrar los estados correctamente y describir los datos de los errores Pruebas en el modulo 06/05 @Cristian Pastor Artigas Se realizan los cambios 10/05 @Cristian Pastor Artigas Se realizan cambios en la App movil para igualar con el Wapsa Web | O44: Nuevo | P44: Requerimiento Nuevo-Area Comercial | Q44: No implica estabilización | R44: 210 | S44: =VLOOKUP(R44,Epics!A:B,2,FALSE) -> Proyecto WAPSA 2024 - 2
A45: 236 | B45: Ticket | C45: Ticket 346 - Wapsa - Callao - Emision Guias Impala 01 - Guias Electronicas - Proyecto Mejoras WAPSA - 2 - Nuevo Modulo "Emisión de Guias Impala 01" | D45: WAPSA\Sprint - Septiembre - 2024 | E45: Cerrado | F45: [Ver. 2.17] | G45: 14/5/2024 7:00:00 p. m. | H45: 3/7/2024 7:00:00 p. m. | I45: 3/9/2024 7:00:00 p. m. | J45: WAPSA web | L45: 346 | M45: Cristian Pastor Artigas <cartigas@syc-sistemas.com> | N45: Descripción: Solución: 20/05 @Cristian Pastor Artigas Se realiza creacion de modulo agregando las vistas y controlador, de momento muestra la misma informacion del que modulo de ED 28/05 @Cristian Pastor Artigas Se finaliza desarrollo y se enviará a testing para revision con Michael 29/05 @Cristian Pastor Artigas Se envia a testing para pruebas. A la espera que TICA actualice el ambien para verlo con MC. 11/06 @Cristian Pastor Artigas Se cambia a estado en desarrollo. Se revisa con Wally y se solicita cambiar: Origen por: ALMACÉN DE MCP (MARIÁTEGUI) Destino: IMPALA 01 Guías de Venta por solo Guía Se debe enviar formato de PDF de GUIA MCP (Antiguo) para que MC proponga los cambios al formato. Se debe enviar formato el TXT de la GRE para que MC lo valide con NeoGrid y envie sus comentarios. 11/06 @Cristian Pastor Artigas Se realizan los cambios. PR 189: Principal PR Modulo de Impresion de Guias Impala 01 Ticket 346 y Parte 1 Ticket 356 Se envian formatos para validacion de MC Se deja Ticket en Desarollo hasta obtener respuesta de MC 09/07 @Cristian Pastor Artigas Se envia a testing cambis en TXT y PDF y para validacion final a MC. | O45: Nuevo | P45: Requerimiento Nuevo-Area Comercial | Q45: No implica estabilización | R45: 210 | S45: =VLOOKUP(R45,Epics!A:B,2,FALSE) -> Proyecto WAPSA 2024 - 2
A46: 178 | B46: Ticket | C46: Ticket 302 - Wapsa - Callao - Gestor Guías Remisión - Guias Electronicas - Proyecto Mejoras WAPSA - 2 - Entregas Directas - Cambiar como se registra el destinatario, que no sea desde el maestro. (mejora posterior | D46: WAPSA\Sprint - Octubre - 2024 | E46: Cerrado | F46: [Ver. 2.18] | G46: 2/6/2024 7:00:00 p. m. | H46: 17/9/2024 7:00:00 p. m. | I46: 14/10/2024 7:00:00 p. m. | J46: WAPSA web | L46: 302 | M46: Cristian Pastor Artigas <cartigas@syc-sistemas.com> | N46: los Descripción: o Para entregas directas: Cambiar como se registra el destinatario, que no sea desde el maetro. (mejora posterior) Solución: 03/06 @Cristian Pastor Artigas -Creado Lote automatico 28/06 @Cristian Pastor Artigas Punto 1,2,3,4 Terminado 02/07 @Cristian Pastor Artigas En proceso Punto 5, Se revisó requerimiento con Michael. esta al 100% 24/07 @Cristian Pastor Artigas Se implementa cambio en el servicio externo para que grabe correctamente el tipo de Venta de las GRE emitidas por Impala | O46: Nuevo | P46: Requerimiento Nuevo-Area Comercial | Q46: No implica estabilización | R46: 210 | S46: =VLOOKUP(R46,Epics!A:B,2,FALSE) -> Proyecto WAPSA 2024 - 2
A47: 218 | B47: Ticket | C47: Ticket 330 - Wapsa - Callao - Lista Despacho - Mejora WAPSA Lista Despacho Diferencias Peso - Embarque Granel | D47: WAPSA\Sprint - Mayo -2024 | E47: Cerrado | F47: [Ver. 2.16] | G47: 31/3/2024 7:00:00 p. m. | H47: 6/4/2024 7:00:00 p. m. | I47: 6/5/2024 7:00:00 p. m. | J47: WAPSA web | L47: 330 | M47: Cristian Pastor Artigas <cartigas@syc-sistemas.com> | N47: Descripción: Se requiere que el WAPSA en la lista despacho se tenga un nuevo filtro para saber si estan observador por el nuevo factor para los casos de "Embarque a Granel" y adicional se requeire cambio de los titulos. Diferencia Balanzas (Almacén 2 - Almacen) Si / No Diferencia Balanzas (Puerto - Almacen) Si / No Ahora: Extraportuario Nuevo: Extraportuario / Balanza 2 Ahora: Almacen Nuevo: Almacen / Balanza 1 Solicitado por Wally Moscoso 20/03 Solución: @Cristian Pastor Artigas Se crea nuevas columnas en el listado y excel con la logica para mostrar el valor de Si/No, pendiente el filtro @Cristian Pastor Artigas Se crea filtro 02/04 @Cristian Pastor Artigas Se envia a 06/04 Wally para revision inidca lo siguiente: -Ajustar nombre de columnas -Agregar una configuracion para indicar el codigo del la IE a partir de la cual debe iniciar a funcionar el filtro de diferencias @Cristian Pastor Artigas Se crea configuracion para que el usuario pueda indicar la IE, se ajustan nombres de campos | O47: Nuevo | P47: Requerimiento Nuevo-Area Comercial | Q47: No implica estabilización | R47: 210 | S47: =VLOOKUP(R47,Epics!A:B,2,FALSE) -> Proyecto WAPSA 2024 - 2
A48: 239 | B48: Ticket | C48: Ticket 347 - Wapsa - General - Actualizar documentacion de Wapsa | D48: WAPSA\Sprint - Mayo -2024 | E48: Cerrado | G48: 6/5/2024 7:00:00 p. m. | H48: 9/5/2024 7:00:00 p. m. | I48: 9/5/2024 7:00:00 p. m. | J48: Wapsa Web | L48: 347 | M48: Cristian Pastor Artigas <cartigas@syc-sistemas.com> | N48: Actualizar documentacion de Wapsa (Manual de Usuario) @Cristian Pastor Artigas Se actualiza el manual y se adjunta en el ticket https://dev.azure.com/SycSistemas/WAPSA/_boards/board/t/WAPSA%20Team/Stories/?workitem=235 | O48: Nuevo | P48: Externos | Q48: No implica estabilización | R48: 210 | S48: =VLOOKUP(R48,Epics!A:B,2,FALSE) -> Proyecto WAPSA 2024 - 2
A49: 240 | B49: Ticket | C49: Tickets 347 - Wapsa - General - Actualizar Manual Usuario de Wapsa | D49: WAPSA\Sprint - Mayo -2024 | E49: Cerrado | G49: 6/5/2024 7:00:00 p. m. | H49: 9/5/2024 7:00:00 p. m. | I49: 9/5/2024 7:00:00 p. m. | J49: Wapsa Web | L49: 347 | M49: Cristian Pastor Artigas <cartigas@syc-sistemas.com> | N49: Por solicitud de TICA(Alexander) en reunion del 07/05 se solicita actualizar el Manual de Usuario de Wapsa 07/05 @Cristian Pastor Artigas Se actualiza manual y se sube al servidor de SyC | O49: Nuevo | P49: Externos | Q49: No implica estabilización | R49: 210 | S49: =VLOOKUP(R49,Epics!A:B,2,FALSE) -> Proyecto WAPSA 2024 - 2
A50: 250 | B50: Ticket | C50: Ticket 356 - WapsaES - General - Servicios Web Callao | D50: WAPSA\Sprint - Enero - 2026 | E50: En Desarrollo | F50: [Ver. 1.3] | G50: 3/6/2024 7:00:00 p. m. | J50: Wapsa ES | L50: 356 | M50: Cristian Pastor Artigas <cartigas@syc-sistemas.com> | N50: Descripción: Solución: 05/06 @Cristian Pastor Artigas Se modifica servicio primeros cambios Volteo Callao. 10/06 @Cristian Pastor Artigas Se crean lo cambios para que marque con diferencias cuando el peso de Callao excede el de Mina segun factor. 14/06 @Cristian Pastor Artigas Se revisa y se hacen los cambios para el servicio de recepcion de pesos para: Contenerdor Directo, Extraportuario, Traslado Entre establacimientos y Granel Resta revisar Humedades 19/06 @Cristian Pastor Artigas Esta creado un servicio para los pesos pero puede cambiarse a que se reciban por la GRE, falta definir si Impala enviara la IE por el servicio de GRE. Reunion 20/06 20/06 @Cristian Pastor Artigas En reunion: Se envia informacion a impala sobre los servicios y a lo interno van a definir los tiempos que tomaría el desarrollo. Impala queda en enviarnos el TAG dentro del cual no esta enviando la IE d eImpala al momento de crear la GRE. A la espera de la informacion de Impala para hacer los cambio en servicio de la GRE para grabar los pesos. | O50: Nuevo | P50: Requerimiento Nuevo-Area Comercial | Q50: No implica estabilización | R50: 210 | S50: =VLOOKUP(R50,Epics!A:B,2,FALSE) -> Proyecto WAPSA 2024 - 2
A51: 187 | B51: Ticket | C51: Ticket 308 - Wapsa Movil - Callao - Cuadre - Proyecto WAPSA 2024 - 2 - Mejoras en el cuadre en Wapsa Movil | D51: WAPSA\Sprint - Agosto - 2024 | E51: En Produccion | F51: [Ver. 1.3] | G51: 8/5/2024 7:00:00 p. m. | H51: 12/5/2024 7:00:00 p. m. | I51: 7/8/2024 7:00:00 p. m. | J51: WAPSA movil | L51: 309 | M51: Cristian Pastor Artigas <cartigas@syc-sistemas.com> | N51: 2.1 Callao-Cuadre interfaz Modificar aplicación para agregar el cambio Modificar "input select" para filtrar solo vagones en arribo y agregar al vagon la ruma Realizar pruebas @Cristian Pastor Artigas Se implementan los cambios | O51: Nuevo | P51: Requerimiento Nuevo-Area Comercial | Q51: No implica estabilización | R51: 210 | S51: =VLOOKUP(R51,Epics!A:B,2,FALSE) -> Proyecto WAPSA 2024 - 2
A52: 237 | B52: Ticket | C52: Ticket 347 - Wapsa - Callao - Gestor Guías Remisión - Guias Electronicas - Proyecto Mejoras WAPSA - 2 - GRE Impresión Guías - Hipervinculos | D52: WAPSA\Sprint - Agosto - 2024 | E52: Cerrado | F52: [Ver. 2.17] | G52: 27/5/2024 7:00:00 p. m. | H52: 9/7/2024 7:00:00 p. m. | I52: 16/7/2024 7:00:00 p. m. | J52: WAPSA web | L52: 347 | M52: Frank Macavilca <dmacavilca@syc-sistemas.com> | N52: Descripción: Solución: | O52: Nuevo | P52: Requerimiento Nuevo-Area Comercial | Q52: No implica estabilización | R52: 210 | S52: =VLOOKUP(R52,Epics!A:B,2,FALSE) -> Proyecto WAPSA 2024 - 2
A53: 238 | B53: Ticket | C53: Ticket 346 - Wapsa Movil - General - Proyecto WAPSA 2024 - 2 - Mejoras en el Inspeccion WAPSA movil | D53: WAPSA\Sprint - Agosto - 2024 | E53: Cerrado | F53: [Ver. 1.1] | G53: 8/5/2024 7:00:00 p. m. | H53: 9/5/2024 7:00:00 p. m. | I53: 7/8/2024 7:00:00 p. m. | J53: Wapsa Movil | L53: 346 | M53: Cristian Pastor Artigas <cartigas@syc-sistemas.com> | N53: La inspeccion en la app movil no funciona solo permite registrar inspecciones sin fotos. 10/05 @Cristian Pastor Artigas Se corrige: -Registro de Convoy -Listar vagones para inspeccion' -Registro de Vagones con sustentos -Se iguala el flujo de registro de vagones observados para que genere la aprobacion con la foto que se toma con la camara, con el flujo del Wapsa Web -Listado de Vagones por convoy ! | O53: Nuevo | P53: Requerimiento Nuevo-Area Comercial | Q53: No implica estabilización | R53: 210 | S53: =VLOOKUP(R53,Epics!A:B,2,FALSE) -> Proyecto WAPSA 2024 - 2
A54: 414 | B54: Ticket | C54: Ticket 424 -Wapsa -General - Ajuste final | D54: WAPSA\Sprint - Octubre - 2025 | E54: Cerrado | F54: [Ver 2.25] | G54: 31/8/2025 7:00:00 p. m. | H54: 1/9/2025 7:00:00 p. m. | I54: 7/10/2025 1:53:00 p. m. | J54: WAPSA web | L54: 423 | M54: Frank Macavilca <dmacavilca@syc-sistemas.com> | O54: Nuevo | P54: Requerimiento Nuevo-Area Comercial | Q54: No implica estabilización | R54: 412 | S54: =VLOOKUP(R54,Epics!A:B,2,FALSE) -> Proyecto WAPSA 2025 - 1
A55: 418 | B55: Ticket | C55: Ticket 428 - F. Grupos de Análisis-Nuevos requerimientos (relacion Ticket 355) | D55: WAPSA\Sprint - Octubre - 2025 | E55: Cerrado | F55: [Ver 2.25] | G55: 5/8/2025 7:00:00 p. m. | H55: 31/8/2025 7:00:00 p. m. | I55: 7/10/2025 1:54:00 p. m. | J55: Wapsa Web | L55: 428 | M55: Cristian Pastor Artigas <cartigas@syc-sistemas.com> | N55: Adcionales parte 1: 1. Hay que considerar qué en el campo de cada G, el laboratorio enviará un solo valor, los analitos de cada grupo deben configurarse aparte, en la vista de Wapsa solo debe ir el valor enviado por Cotecna. 2. Añadir las siguientes columnas: a. Entre el Campo # y Lote Añadir una columna de la Ruma. b. En el reporte de Excel, adicional a la ruma, añadir al final de los campos actuales: Calidad, Almacén , TMH Mina, H2O Mina, TMS Mina, As Mina, F Mina, Zn Mina 3. En el reporte de “Diferencia de Leyes” se deberá calcular la diferencia entre agrupaciones (G y Lote Callao) de acuerdo con las fórmulas del Excel adjunto. 4. En la Lista de asignaciones añadir un filtro de los valores del campo “Estado” 5. En el “Reporte de asignación” detallado (dentro de cada ruma): para el reporte en Excel y en la vista de Wapsa ordenar las columnas de analitos como sigue: Callao: Ag, As, Cu, Zn, MgO, F, Bi, Pb, Sb Mina: Ag, As, Cu, Zn, MgO, F, Fe, Mo 6. En el “Reporte de rumas” para el reporte en Excel y en la vista de Wapsa ordenar las columnas de analitos como sigue: Ag, As, Cu, Zn, MgO, F Adicionales parte 2: 3. En el reporte de “Diferencia de Leyes” se deberá calcular la diferencia entre agrupaciones (G y Lote Callao) de acuerdo con las fórmulas del Excel adjunto. | O55: Nuevo | P55: Requerimiento Nuevo-Area Comercial | Q55: Estabilización de req. de Mantenimiento | R55: 412 | S55: =VLOOKUP(R55,Epics!A:B,2,FALSE) -> Proyecto WAPSA 2025 - 1
A56: 431 | B56: Ticket | C56: Ticket 357 - WapsaES - G. Codigo Establecimiento por cada serie - Caso Impala Wapsa ES | D56: WAPSA\Sprint - Octubre - 2025 | E56: Cerrado | F56: [Ver 4.1] | G56: 23/3/2025 7:00:00 p. m. | H56: 15/6/2025 7:00:00 p. m. | I56: 7/10/2025 2:33:00 p. m. | J56: Wapsa ES | L56: 428 | M56: Cristian Pastor Artigas <cartigas@syc-sistemas.com> | O56: Nuevo | P56: Requerimiento Nuevo-Area Comercial | Q56: No implica estabilización | R56: 412 | S56: =VLOOKUP(R56,Epics!A:B,2,FALSE) -> Proyecto WAPSA 2025 - 1
A57: 413 | B57: Ticket | C57: Ticket 423 - Wapsa - Mina - Pesaje - Modulo Mina - Filtros- Quitar Preautorizados | D57: WAPSA\Sprint - Mayo - 2025 | E57: Resuelto | F57: [Ver. 2.22] | G57: 8/3/2025 7:00:00 p. m. | H57: 9/3/2025 7:00:00 p. m. | I57: 2/6/2025 7:00:00 p. m. | J57: Wapsa Web | L57: 423 | M57: Cristian Pastor Artigas <cartigas@syc-sistemas.com> | N57: @Cristian Pastor Artigas En pruebas finales | O57: Nuevo | P57: Requerimiento Nuevo-Area Comercial | Q57: No implica estabilización | R57: 412 | S57: =VLOOKUP(R57,Epics!A:B,2,FALSE) -> Proyecto WAPSA 2025 - 1
A58: 416 | B58: Ticket | C58: Ticket 426 - D. Logs | D58: WAPSA\Sprint - Marzo - 2026 | E58: Nuevo | G58: 31/12/2025 7:00:00 p. m. | H58: 30/1/2026 7:00:00 p. m. | I58: 30/1/2026 7:00:00 p. m. | J58: Wapsa Web | L58: 425 | M58: Cristian Pastor Artigas <cartigas@syc-sistemas.com> | N58: Esto ya esta resuelto revisado 16/03 los logs del WAPSA ahora se ven los datos enviados en de leyes mina y callao | O58: Nuevo | P58: Requerimiento Nuevo-Area Comercial | Q58: No implica estabilización | R58: 412 | S58: =VLOOKUP(R58,Epics!A:B,2,FALSE) -> Proyecto WAPSA 2025 - 1
A59: 417 | B59: Ticket | C59: Ticket 427 - WapsaES - Servicios Web Callao | D59: WAPSA\Sprint - Diciembre - 2025 | E59: Cerrado | G59: 26/11/2025 2:51:00 a. m. | H59: 5/12/2025 2:51:00 a. m. | I59: 5/12/2025 2:51:00 a. m. | J59: Wapsa ES | L59: 426 | M59: Cristian Pastor Artigas <cartigas@syc-sistemas.com> | N59: //Cambios 26/01 Creación de Proyecto para procesar archivos CSV Descripción General Desarrollo de un proyecto .NET 4.7.2 para procesar automáticamente archivos CSV provenientes de FTP, con el objetivo de registrar información de Pesos y Humedades en las tablas de WAPSA para los módulos de Recepción (Volteo) y Despacho (Lista Despacho). &#128203; Tareas 1. Configuración Inicial del Proyecto Objetivo: Establecer la base del proyecto con las dependencias necesarias. Crear nuevo proyecto .NET Framework 4.7.2 Configurar dependencias nativas para conexiones a base de datos (sin librerías externas o customizadas) Establecer estructura de proyecto limpia y organizada Configurar gestión de configuraciones (connection strings, rutas FTP, etc.) 2. Desarrollo - Módulo Recepción (Volteo) Objetivo: Implementar la lógica para procesar datos de Pesos y Humedades del módulo de Recepción. 2.1 Componente de Lectura FTP Implementar servicio para conectarse al servidor FTP Desarrollar lógica para detectar y descargar archivos CSV nuevos Implementar parseo y validación de estructura CSV 2.2 Procesamiento de Pesos - Recepción Extraer campos correspondientes del CSV según especificaciones Mapear datos a las tablas de WAPSA establecidas Implementar lógica de grabación en base de datos Manejo de errores y logs de procesamiento 2.3 Procesamiento de Humedades - Recepción Extraer campos correspondientes del CSV según especificaciones Mapear datos a las tablas de WAPSA establecidas Implementar lógica de grabación en base de datos Manejo de errores y logs de procesamiento 2.4 Pruebas - Módulo Recepción Realizar pruebas unitarias de componentes Validar integridad de datos grabados Probar escenarios de error y manejo de excepciones 3. Desarrollo - Módulo Despacho (Lista Despacho) Objetivo: Implementar la lógica para procesar datos de Pesos y Humedades del módulo de Despacho. 3.1 Procesamiento de Pesos - Despacho por Tipo de Contenedor Contenedor Extraportuario y Directo: Extraer campos específicos del CSV Procesar y grabar en tablas WAPSA correspondientes Contenedor Granel: Extraer campos específicos del CSV Procesar y grabar en tablas WAPSA correspondientes Contenedor Traslados Externos: Extraer campos específicos del CSV Procesar y grabar en tablas WAPSA correspondientes 3.2 Procesamiento de Humedades - Despacho Extraer campos de humedades del CSV Implementar lógica de procesamiento Grabar información en tablas WAPSA correspondientes Manejo de errores y logs 3.3 Pruebas - Módulo Despacho Realizar pruebas para cada tipo de contenedor Validar correcta grabación de datos por tipo Probar escenarios de error y manejo de excepciones Validación integral del flujo completo &#128295; Consideraciones Técnicas Framework: .NET 4.7.2 Conexión BD: Usar componentes nativos de .NET (sin librerías externas) Origen de datos: Archivos CSV desde servidor FTP Destino: Tablas WAPSA (Recepción y Despacho) Logging: Implementar registro de operaciones y errores ✅ Criterios de Aceptación Proyecto .NET 4.7.2 correctamente configurado Conexión FTP funcional y lectura de archivos CSV Procesamiento correcto de Pesos y Humedades para Recepción Procesamiento correcto de Pesos y Humedades para Despacho (todos los tipos de contenedor) Datos grabados correctamente en tablas WAPSA Pruebas realizadas y documentadas Manejo de errores implementado Código limpio y documentado | O59: Nuevo | P59: Requerimiento Nuevo-Area Comercial | Q59: No implica estabilización | R59: 412 | S59: =VLOOKUP(R59,Epics!A:B,2,FALSE) -> Proyecto WAPSA 2025 - 1
A60: 415 | B60: Ticket | C60: Ticket 425 - Wapsa - Ruma - ENVIÓ DE DATA DE RUMA Y EJE A IMPALA | D60: WAPSA\Sprint - Agosto - 2025 | E60: Cerrado | F60: [Ver 2.24] | G60: 15/4/2025 7:00:00 p. m. | H60: 15/6/2025 7:00:00 p. m. | J60: WAPSA web | L60: 424 | M60: Cristian Pastor Artigas <cartigas@syc-sistemas.com> | O60: Nuevo | P60: Requerimiento Nuevo-Area Comercial | Q60: No implica estabilización | R60: 412 | S60: =VLOOKUP(R60,Epics!A:B,2,FALSE) -> Proyecto WAPSA 2025 - 1
A61: 419 | B61: Ticket | C61: Ticket 429 - Wapsa- General - G. Codigo Establecimiento por cada serie | D61: WAPSA\Sprint - Agosto - 2025 | E61: Cerrado | F61: [Ver 2.24] | G61: 23/3/2025 7:00:00 p. m. | H61: 14/6/2025 7:00:00 p. m. | J61: Wapsa Web | L61: 428 | M61: Cristian Pastor Artigas <cartigas@syc-sistemas.com> | O61: Nuevo | P61: Requerimiento Nuevo-Area Comercial | Q61: No implica estabilización | R61: 412 | S61: =VLOOKUP(R61,Epics!A:B,2,FALSE) -> Proyecto WAPSA 2025 - 1
A62: 180 | B62: Ticket | C62: Ticket 422 - Wapsa - Mina - Pesaje - Modulo Mina Pesaje Manual (tara y bruto) supervisor por evento | D62: WAPSA\Sprint - Abril - 2025 | E62: Resuelto | F62: [Ver. 2.22] | G62: 25/2/2025 7:00:00 p. m. | H62: 10/3/2025 7:00:00 p. m. | I62: 2/6/2025 7:00:00 p. m. | J62: Wapsa Web | L62: 422 | M62: Cristian Pastor Artigas <cartigas@syc-sistemas.com> | N62: @Cristian Pastor Artigas desarrollo finalizado pendientes pruebas finales de ambois flujos Tara y bruto | O62: Nuevo | P62: Requerimiento Nuevo-Area Comercial | Q62: No implica estabilización | R62: 412 | S62: =VLOOKUP(R62,Epics!A:B,2,FALSE) -> Proyecto WAPSA 2025 - 1
A63: 459 | B63: Ticket | C63: Ticket 446 - Muestreo Callao problema Lote Callao | D63: WAPSA\Sprint - Septiembre- 2025 | E63: Cerrado | G63: 26/7/2025 3:31:00 a. m. | H63: 4/8/2025 7:00:00 p. m. | I63: 4/8/2025 7:00:00 p. m. | J63: WAPSA Web | L63: 446 | N63: Descripción: Arreglar porque esta generando el nuevo lote callao basado en la fecha de registro y no en la fecha de muestreo Adicionalmente, para la opcion "Modificar lote callao" extender la funcionalidad para que al generar nuevo lote el usuario pueda decir que lote nuevo necsita agregar ejemplo Actualmente: Usuario coloca "Generar nuevo Lote Callao" El sistema crea un nuevo lote callao para el lote actual Mejora: Usuario coloca "Generar nuevo Lote callao" se muestra los "Lotes" donde va poder seleccionar en cual se crear un nuevo lote callao adicional El sistema crear un nuevo luego callao segun el lote seleccionado Solución: | O63: Nuevo | P63: S&C Sistemas | Q63: No implica estabilización | R63: 161 | S63: =VLOOKUP(R63,Epics!A:B,2,FALSE) -> Soporte
A64: 465 | B64: Ticket | C64: Ticket 448 - Despachos fuera de rango e fechas-Aprobacion guia T018-026595 | D64: WAPSA\Sprint - Septiembre- 2025 | E64: Cerrado | G64: 17/8/2025 7:00:00 p. m. | H64: 1/10/2025 7:00:00 p. m. | I64: 30/9/2025 7:00:00 p. m. | J64: Wapsa Web | L64: 448 | O64: Nuevo | P64: S&C Sistemas | Q64: No implica estabilización | R64: 161 | S64: =VLOOKUP(R64,Epics!A:B,2,FALSE) -> Soporte
A65: 488 | B65: Ticket | C65: Ticket 457 - Wapsa - General - Pase a Produccion Emision de GRE Otros con RUC v2.24.1 | D65: WAPSA\Sprint - Septiembre- 2025 | E65: Cerrado | F65: [Ver. 2.24.1] | G65: 26/9/2025 7:09:00 a. m. | H65: 27/9/2025 7:00:00 p. m. | I65: 29/10/2025 4:48:00 a. m. | J65: Wapsa Web | L65: 457 | M65: Cristian Pastor Artigas <cartigas@syc-sistemas.com> | N65: Ticket 457 - Wapsa - GRE - Fallo al generar TXT en GRE Remanentes https://dev.azure.com/SycSistemas/WAPSA/_boards/board/t/WAPSA%20Team/Stories?workitem=489 | O65: Repetitivo-en-proceso | P65: S&C Sistemas | Q65: No implica estabilización | R65: 161 | S65: =VLOOKUP(R65,Epics!A:B,2,FALSE) -> Soporte
A66: 246 | B66: Ticket | C66: Ticket 353 - Wapsa - Mina - Pesaje - Lista de Despachos-Se generó un registro duplicado al preasignar vagón por intervención del usuario | D66: WAPSA\Sprint - Septiembre - 2024 | E66: Cerrado | F66: [Ver. 2.17] | G66: 26/5/2024 7:00:00 p. m. | H66: 29/5/2024 7:00:00 p. m. | I66: 18/8/2024 7:00:00 p. m. | J66: Wapsa Web | L66: 353 | M66: Cristian Pastor Artigas <cartigas@syc-sistemas.com> | N66: Carlos Zenteno reporta: Se tuvo inconveniente con el Wapsa al ingresar pre asignado al guardar un vagon 10008 se demoraba en cargar lo actualice el sistema y generó 2 lotes con el mismo vagon y precinto como se observa en la imagen. 30/05 @Cristian Pastor Artigas Se replica el caso en Testing. Diagnóstico: el registro se genera al dar dos clicks seguido al boton guardar. Solucion: Se debe bloquear el boton a dar el guardar. Se debe corregir en versión. 30/05 @Cristian Pastor Artigas Corregido en PR 185: Ticket 307 Ticket 346 Ticket 308 . Se tagea Ticket a version 2.17 | O66: Nuevo | P66: Error del usuario | Q66: Estabilización de req. de Mantenimiento | R66: 161 | S66: =VLOOKUP(R66,Epics!A:B,2,FALSE) -> Soporte
A67: 297 | B67: Ticket | C67: Ticket 371 - Wapsa BI - General - Ejecución Manual - Corregir y cargar data antigua de leyes y datos del Volteo del 2018-2024 | D67: WAPSA\Sprint - Septiembre - 2024 | E67: Cerrado | G67: 13/8/2024 7:00:00 p. m. | H67: 13/8/2024 7:00:00 p. m. | I67: 3/9/2024 7:00:00 p. m. | J67: Wapsa BI | K67: 117280 | L67: 371 | M67: Cristian Pastor Artigas <cartigas@syc-sistemas.com> | N67: Luis casas reporta: 1. Desde hace una semana aprox, no se está cargando la información automáticamente, se está ejecutando manualmente. 2. En la tabla HumedadesPesosyLeyes no hay información de antes de Noviembre 2023: 3. En la misma tabla anterior el valor vcLoteCallao está cargando a su vez el sublote en algunas guías, debería ser solo el valor del mes. 27/08 @Cristian Pastor Artigas Falta enviar scripts en ticket para ejecución manual 02/09 @Cristian Pastor Artigas Ticket enviados para firmas 02/09 @Cristian Pastor Artigas Enviado a TICA | O67: Repetitivo-en-proceso | P67: S&C Sistemas | Q67: Estabilización por proyecto | R67: 161 | S67: =VLOOKUP(R67,Epics!A:B,2,FALSE) -> Soporte
A68: 310 | B68: Ticket | C68: Ticket 374 - Wapsa - Mina - Pesaje - Vagones Observados esta mal la descripción del estado | D68: WAPSA\Sprint - Septiembre - 2024 | E68: Resuelto | G68: 11/9/2024 7:00:00 p. m. | H68: 11/9/2024 7:00:00 p. m. | I68: 9/10/2024 7:00:00 p. m. | J68: Wapsa Web | L68: 374 | M68: Cristian Pastor Artigas <cartigas@syc-sistemas.com> | N68: Descripción: Al ingresar al detalle de un vagón en vagones observados, el punto: “Estado Dif. Peso Tara Supervisor: DENTRO DEL RANGO” debe indicar “NO APROBADO” Revisar porque esta registrandose con ese estado Solución: | O68: Nuevo | P68: Requerimiento Nuevo-Area Comercial | Q68: No implica estabilización | R68: 161 | S68: =VLOOKUP(R68,Epics!A:B,2,FALSE) -> Soporte
A69: 315 | B69: Ticket | C69: Ticket 378 - Wapsa - General - TICA solicita documentación sobre Wapsa | D69: WAPSA\Sprint - Septiembre - 2024 | E69: Cerrado | G69: 5/9/2024 7:00:00 p. m. | H69: 5/9/2024 7:00:00 p. m. | I69: 5/9/2024 7:00:00 p. m. | J69: Wapsa Web | L69: 378 | M69: Cristian Pastor Artigas <cartigas@syc-sistemas.com> | N69: TICA solicita: 06/09 @Cristian Pastor Artigas Se envia parte de lam documentacion, resta enviar Diagrma de Arquitectura de Wapsa 09/09 @Cristian Pastor Artigas Se envia Documentacion de Arquitectura de Wapsa | O69: Nuevo | P69: Externos | Q69: No implica estabilización | R69: 161 | S69: =VLOOKUP(R69,Epics!A:B,2,FALSE) -> Soporte
A70: 332 | B70: Ticket | C70: Ticket 382 - Wapsa - Mina - C.Stock - Listado de Stock demora para mostrar información | D70: WAPSA\Sprint - Septiembre - 2024 | E70: Cerrado | G70: 23/9/2024 7:00:00 p. m. | H70: 23/9/2024 7:00:00 p. m. | I70: 23/9/2024 7:00:00 p. m. | J70: Wapsa Web | L70: 382 | M70: Cristian Pastor Artigas <cartigas@syc-sistemas.com> | N70: Jorge Garcia Reporta: | O70: Nuevo | P70: Servidor MCP | Q70: No implica estabilización | R70: 161 | S70: =VLOOKUP(R70,Epics!A:B,2,FALSE) -> Soporte
A71: 345 | B71: Ticket | C71: Ticket 385 - Wapsa ES - General - Proyecto 2024 - Crear API para recibir/ver informacion de Grupo Ensayos (Relacion con Ticket 355) | D71: WAPSA\Sprint - Octubre - 2025 | E71: Cerrado | F71: [Ver 2.25]; [Ver 4.1] | G71: 13/10/2024 7:00:00 p. m. | H71: 4/9/2025 6:24:00 a. m. | I71: 7/10/2025 2:33:00 p. m. | J71: Wapsa ES | L71: 385 | M71: Cristian Pastor Artigas <cartigas@syc-sistemas.com> | N71: 17/10 @Cristian Pastor Artigas Cambios en Testing. Se envia correo a cotecna informando que ya esta ok | O71: Nuevo | P71: Requerimiento Nuevo-Area Comercial | Q71: No implica estabilización | R71: 161 | S71: =VLOOKUP(R71,Epics!A:B,2,FALSE) -> Soporte
A72: 378 | B72: Ticket | C72: Ticket 403 - Wapsa ES - GRE's - Validar que existan datos de balanzas en Wapsa cuando se crea la GRE | D72: WAPSA\Sprint - Octubre - 2025 | E72: Cerrado | F72: [Ver 4.1] | G72: 17/12/2024 7:00:00 p. m. | H72: 4/9/2025 6:16:00 a. m. | I72: 7/10/2025 2:33:00 p. m. | J72: Wapsa ES | L72: 403 | M72: Cristian Pastor Artigas <cartigas@syc-sistemas.com> | N72: Mjorar mensajes de error si es que no existe una balanza creada al momento de registrar la GRE | O72: Nuevo | P72: Requerimiento Nuevo-Area Comercial | Q72: No implica estabilización | R72: 161 | S72: =VLOOKUP(R72,Epics!A:B,2,FALSE) -> Soporte
A73: 479 | B73: Ticket | C73: Ticket 450 - Wapsa - Ruma - Popup de Ejes de ve muy abajo | D73: WAPSA\Sprint - Octubre - 2025 | E73: Resuelto | F73: [Ver 2.25] | G73: 15/9/2025 7:56:00 a. m. | H73: 2/10/2025 7:20:00 a. m. | I73: 7/10/2025 1:54:00 p. m. | J73: Wapsa Web | L73: 450 | O73: Nuevo | P73: S&C Sistemas | Q73: Estabilización de req. de Mantenimiento | R73: 161 | S73: =VLOOKUP(R73,Epics!A:B,2,FALSE) -> Soporte
A74: 480 | B74: Ticket | C74: Ticket 451 - Wapsa - Arribo - Ejes Ruma - No se envian los QR dentro del email | D74: WAPSA\Sprint - Octubre - 2025 | E74: Cerrado | F74: [Ver 2.25] | G74: 15/9/2025 7:56:00 a. m. | H74: 2/10/2025 2:25:00 p. m. | I74: 7/10/2025 1:54:00 p. m. | J74: Wapsa Web | L74: 451 | M74: Cristian Pastor Artigas <cartigas@syc-sistemas.com> | O74: Nuevo | P74: S&C Sistemas | Q74: Estabilización de req. de Mantenimiento | R74: 161 | S74: =VLOOKUP(R74,Epics!A:B,2,FALSE) -> Soporte
A75: 489 | B75: Ticket | C75: Ticket 456 - Wapsa - GRE - Fallo al generar TXT en GRE Remanentes y Otros | D75: WAPSA\Sprint - Octubre - 2025 | E75: Cerrado | F75: [Ver. 2.24.1] | G75: 24/9/2025 7:00:00 p. m. | H75: 26/9/2025 7:10:00 a. m. | I75: 7/10/2025 1:54:00 p. m. | J75: Wapsa Web | L75: 456 | M75: Cristian Pastor Artigas <cartigas@syc-sistemas.com> | N75: Emite incorrectamnete las guias de: Remanentes: -RepesoVenta -EmbarqueGranel -RemanentesTransportadoras -DevoluciónContenedor -VagonesLimpieza | O75: Nuevo | P75: S&C Sistemas | Q75: Estabilización de req. de Mantenimiento | R75: 161 | S75: =VLOOKUP(R75,Epics!A:B,2,FALSE) -> Soporte
A76: 308 | B76: Ticket | C76: Ticket 372 - Wapsa - Mina - Pesaje - Pesaje Manual - Mejora-Ver vagones observados | D76: WAPSA\Sprint - Octubre - 2024 | E76: Cerrado | F76: [Ver. 2.18] | G76: 12/9/2024 7:00:00 p. m. | H76: 23/9/2024 7:00:00 p. m. | I76: 14/10/2024 7:00:00 p. m. | J76: Wapsa Web | L76: 372 | M76: Cristian Pastor Artigas <cartigas@syc-sistemas.com> | N76: Descripción: En la lista de vagones que han sido aprobados para no destarar (pesaje manual), se debe agregar el detalle de los vagones observados. El usuario requiere que por cada item se despliegue un menu con una opción que diga "Ver Vagones Observados" - Este mostrará un pop up donde se listará los vagones observados según el registro. Solución: | O76: Nuevo | P76: Requerimiento Nuevo-Area Comercial | Q76: No implica estabilización | R76: 161 | S76: =VLOOKUP(R76,Epics!A:B,2,FALSE) -> Soporte
A77: 309 | B77: Ticket | C77: Ticket 373 - Wapsa - Mina - Pesaje - Mejora correos supervisores | D77: WAPSA\Sprint - Octubre - 2024 | E77: Cerrado | F77: [Ver. 2.18] | G77: 10/9/2024 7:00:00 p. m. | H77: 10/9/2024 7:00:00 p. m. | I77: 14/10/2024 7:00:00 p. m. | J77: WAPSA web | L77: 373 | M77: Cristian Pastor Artigas <cartigas@syc-sistemas.com> | N77: Descripción: Si hay algo pendiente de aprobación en vagones observados debe llegar un correo a los supervisores mina a modo de recordatorio. Este ejemplo es uso de precinto duplicado mes agosto 2024 Se requiere tener un job para poder reenviar el correo de recordatorio cada 72 h Solución: | O77: Nuevo | P77: Requerimiento Nuevo-Area Comercial | Q77: No implica estabilización | R77: 161 | S77: =VLOOKUP(R77,Epics!A:B,2,FALSE) -> Soporte
A78: 311 | B78: Ticket | C78: Ticket 375 - Wapsa - Mina - Pesaje - Vagones observados - no filtra por los estados | D78: WAPSA\Sprint - Octubre - 2024 | E78: Cerrado | F78: [Ver. 2.18] | G78: 5/9/2024 7:00:00 p. m. | H78: 8/9/2024 7:00:00 p. m. | I78: 14/10/2024 7:00:00 p. m. | J78: Wapsa Web | L78: 375 | M78: Cristian Pastor Artigas <cartigas@syc-sistemas.com> | N78: Descripción: En la pestaña de vagones observados no está filtrando correctamente, por ejemplo en Setiembre 2024 se tiene varios vagones pendientes d aprobación por parte del supervisor pero solo aparecen cuando se coloca todos. Solución: | O78: Nuevo | P78: S&C Sistemas | Q78: Estabilización por proyecto | R78: 161 | S78: =VLOOKUP(R78,Epics!A:B,2,FALSE) -> Soporte
A79: 312 | B79: Ticket | C79: Ticket 376 - Wapsa - Mina - Pesaje - Registro cambio check auto/manual peso tara | D79: WAPSA\Sprint - Octubre - 2024 | E79: Cerrado | F79: [Ver. 2.18] | G79: 4/9/2024 7:00:00 p. m. | H79: 4/9/2024 7:00:00 p. m. | I79: 14/10/2024 7:00:00 p. m. | J79: Wapsa Web | L79: 376 | M79: Cristian Pastor Artigas <cartigas@syc-sistemas.com> | N79: Descripción: Cuando el usuario ya tiene un registro de pesaje en estado "Peso Bruto/Tara" y este pertenece a un grupo de "Pesaje Manual" el sistema te permite cambiar en la balanza a "Auto" lo cual no debería permitir ya que este puede cambiar el guardado del registro Solución: @Cristian Pastor Artigas Se revisa caso y se comprueba que las guia generadas durante los pesaje manuales estan correctas; quizas se necesaria una reunion con Carlos Zenteno para comentar este tema. Adjunto Excel con comprobaciones De momento se cierra Ticket. | O79: Nuevo | P79: A&S | Q79: Estabilización de req. de Mantenimiento | R79: 161 | S79: =VLOOKUP(R79,Epics!A:B,2,FALSE) -> Soporte
A80: 325 | B80: Ticket | C80: Ticket 381 - Wapsa - Callao - Cuadre - Correccion en el listado de vagones disponibles para cuadre | D80: WAPSA\Sprint - Octubre - 2024 | E80: Cerrado | G80: 17/9/2024 7:00:00 p. m. | H80: 17/9/2024 7:00:00 p. m. | I80: 10/10/2024 7:00:00 p. m. | J80: Wapsa Web | K80: 118649 | L80: 381 | M80: Cristian Pastor Artigas <cartigas@syc-sistemas.com> | N80: Carlos Linares Reporta que en Callao-Cuadre no lista vagones con inspeccion Esta correccion fue realizada en el pase a produccion de la version Wapsa v2.17 | O80: Nuevo | P80: S&C Sistemas | Q80: Estabilización de req. de Mantenimiento | R80: 161 | S80: =VLOOKUP(R80,Epics!A:B,2,FALSE) -> Soporte
A81: 333 | B81: Ticket | C81: Ticket 383 - Wapsa - Callao - Volteo - Link para descargar PDF en Guias Electronicas | D81: WAPSA\Sprint - Octubre - 2024 | E81: Cerrado | F81: [Ver. 2.18] | G81: 24/9/2024 7:00:00 p. m. | H81: 29/9/2024 7:00:00 p. m. | I81: 14/10/2024 7:00:00 p. m. | J81: Wapsa Web | L81: 383 | M81: Cristian Pastor Artigas <cartigas@syc-sistemas.com> | N81: Agregar link en las guias T018 para descargar PDF en Guias Electronicas | O81: Nuevo | P81: Requerimiento Nuevo-Area Comercial | Q81: No implica estabilización | R81: 161 | S81: =VLOOKUP(R81,Epics!A:B,2,FALSE) -> Soporte
A82: 344 | B82: Ticket | C82: Ticket 384 - Wapsa - Mina - Pesaje - Despachos - No se genero la GRE T018-0014158(salto en el correlativo) | D82: WAPSA\Sprint - Octubre - 2024 | E82: Cerrado | G82: 13/10/2024 7:00:00 p. m. | H82: 20/10/2024 7:00:00 p. m. | I82: 20/10/2024 7:00:00 p. m. | J82: Wapsa Web | L82: 384 | M82: Cristian Pastor Artigas <cartigas@syc-sistemas.com> | N82: Wally Reporta | O82: Nuevo | P82: S&C Sistemas | Q82: Estabilización por proyecto | R82: 161 | S82: =VLOOKUP(R82,Epics!A:B,2,FALSE) -> Soporte
A83: 461 | B83: Ticket | C83: Ticket 447 - Error calculo Stock Inicial Agosto | D83: WAPSA\Sprint - Noviembre - 2025 | E83: Cerrado | G83: 1/8/2025 7:00:00 p. m. | H83: 25/11/2025 7:00:00 p. m. | J83: WAPSA Web | L83: 447 | N83: Descripción: El usuario detecto que el stock inicial esta diferente al dia anterior del 01/08 al 31/08 Solución: | O83: Nuevo | P83: S&C Sistemas | Q83: No implica estabilización | R83: 161 | S83: =VLOOKUP(R83,Epics!A:B,2,FALSE) -> Soporte
A84: 324 | B84: Ticket | C84: Ticket 380 - Wapsa - Callao - Lista Despacho - Consulta sobre Cierre IE con peso 0 (YCC0172/23) | D84: WAPSA\Sprint - Noviembre - 2024 | E84: Cerrado | G84: 17/9/2024 7:00:00 p. m. | H84: 17/9/2024 7:00:00 p. m. | I84: 17/9/2024 7:00:00 p. m. | J84: Wapsa Web | L84: 380 | M84: Cristian Pastor Artigas <cartigas@syc-sistemas.com> | N84: Wally Reporta | O84: Nuevo | P84: A&S | Q84: Estabilización de req. de Mantenimiento | R84: 161 | S84: =VLOOKUP(R84,Epics!A:B,2,FALSE) -> Soporte
A85: 346 | B85: Ticket | C85: Ticket 386 - Wapsa - Mina - Pesaje - El correo de despachos pendientes por aprobación del sup. llega vacio | D85: WAPSA\Sprint - Noviembre - 2024 | E85: Cerrado | G85: 24/10/2024 7:00:00 p. m. | H85: 24/10/2024 7:00:00 p. m. | I85: 10/11/2024 7:00:00 p. m. | J85: Wapsa web | K85: 122042 | L85: 386 | M85: Cristian Pastor Artigas <cartigas@syc-sistemas.com> | N85: Diego cardenas reporta: 28/10 @Cristian Pastor Artigas Enviado a TICA | O85: Nuevo | P85: S&C Sistemas | Q85: Estabilización de req. de Mantenimiento | R85: 161 | S85: =VLOOKUP(R85,Epics!A:B,2,FALSE) -> Soporte
A86: 347 | B86: Ticket | C86: Ticket 387 - Wapsa - Callao - Asignacion - La reasignación no se genera correctamente y no se muestra en los reportes de stock | D86: WAPSA\Sprint - Noviembre - 2024 | E86: Resuelto | F86: [Ver. 2.19] | G86: 27/10/2024 7:00:00 p. m. | H86: 10/11/2024 7:00:00 p. m. | I86: 29/12/2024 7:00:00 p. m. | J86: Wapsa Web | L86: 387 | M86: Cristian Pastor Artigas <cartigas@syc-sistemas.com> | N86: Al aprobarse una reasignacion esta no genera una operacion interna que origina que se pueda ver en los reportes y falla, por el momento puede verse en el modulo de Asignación. -Error al aprobar un pesaje Manual por Modulo -Finalizado | O86: Nuevo | P86: Requerimiento Nuevo-Area Comercial | Q86: No implica estabilización | R86: 161 | S86: =VLOOKUP(R86,Epics!A:B,2,FALSE) -> Soporte
A87: 349 | B87: Ticket | C87: Ticket 388 - Wapsa - Mina - Pesaje - Correcciones listado de vagones observados y columna peso tara supervisor | D87: WAPSA\Sprint - Noviembre - 2024 | E87: Cerrado | G87: 30/10/2024 7:00:00 p. m. | H87: 30/10/2024 7:00:00 p. m. | I87: 20/11/2024 7:00:00 p. m. | J87: Wapsa Web | K87: 123056 | L87: 388 | M87: Cristian Pastor Artigas <cartigas@syc-sistemas.com> | N87: Carlos Zenteno Reporta Se agrega script de solucion del ticket Ticket 389 - Wapsa - Mina - Pesaje- Cambia columna Aprobacion pesaje Manual tara cuando es con pesaje manual pre aprobado https://dev.azure.com/SycSistemas/WAPSA/_boards/board/t/WAPSA%20Team/Stories/?workitem=350 | O87: Nuevo | P87: S&C Sistemas | Q87: Estabilización por proyecto | R87: 161 | S87: =VLOOKUP(R87,Epics!A:B,2,FALSE) -> Soporte
A88: 350 | B88: Ticket | C88: Ticket 389 - Wapsa - Mina - Pesaje - Cambia columna Aprobacion pesaje Manual tara cuando es con pesaje manual pre aprobado | D88: WAPSA\Sprint - Noviembre - 2024 | E88: Cerrado | G88: 30/10/2024 7:00:00 p. m. | H88: 18/11/2024 7:00:00 p. m. | I88: 29/12/2024 7:00:00 p. m. | J88: Wapsa Web | L88: 389 | M88: Cristian Pastor Artigas <cartigas@syc-sistemas.com> | N88: Carlos zenteno Solicita 11/11 @Cristian Pastor Artigas se envia solucion en Ticket https://dev.azure.com/SycSistemas/WAPSA/_boards/board/t/WAPSA%20Team/Stories/?workitem=349 | O88: Nuevo | P88: Requerimiento Nuevo-Area Comercial | Q88: No implica estabilización | R88: 161 | S88: =VLOOKUP(R88,Epics!A:B,2,FALSE) -> Soporte
A89: 352 | B89: Ticket | C89: Ticket 390 - Wapsa - Mina - Pesaje - Error Sublote 1068 Wapsa muestra que no pertenece a ningun lote y no se puede pesar el bruto | D89: WAPSA\Sprint - Noviembre - 2024 | E89: Cerrado | G89: 10/11/2024 7:00:00 p. m. | H89: 10/11/2024 7:00:00 p. m. | I89: 10/11/2024 7:00:00 p. m. | J89: Wapsa Web | L89: 390 | M89: Cristian Pastor Artigas <cartigas@syc-sistemas.com> | N89: Carlos Zenteno reporta 11/11 @Cristian Pastor Artigas Se envia correccion dentro de ticket 388 https://dev.azure.com/SycSistemas/WAPSA/_boards/board/t/WAPSA%20Team/Stories/?workitem=349 | O89: Nuevo | P89: A&S | Q89: Estabilización de req. de Mantenimiento | R89: 161 | S89: =VLOOKUP(R89,Epics!A:B,2,FALSE) -> Soporte
A90: 354 | B90: Ticket | C90: Ticket 391 - Wapsa - Mina - Pesaje - Error con guia T018-0013488 Sublote: 1863 Lote: CT2409 cambiar estado aprobado | D90: WAPSA\Sprint - Noviembre - 2024 | E90: Cerrado | G90: 30/10/2024 7:00:00 p. m. | H90: 18/11/2024 7:00:00 p. m. | I90: 29/12/2024 7:00:00 p. m. | J90: Wapsa Web | K90: 123862 | L90: 391 | M90: Cristian Pastor Artigas <cartigas@syc-sistemas.com> | N90: -La guía T018-0013488 Sublote: 1863 Lote: CT2409 Se colocó en Estado Dif. Peso Tara Supervisor = Pendiente, pero por lo que veo Jorge Garcia ya la aprobó así que habrá que esperar un siguiente ticket para que se solucione del todo y ya no aparezca pendien | O90: Nuevo | P90: A&S | Q90: Estabilización de req. de Mantenimiento | R90: 161 | S90: =VLOOKUP(R90,Epics!A:B,2,FALSE) -> Soporte
A91: 355 | B91: Ticket | C91: Ticket 393 - Wapsa - Mina - Pesaje - Wapsa no debe permitir registrar pesos al momento de preasignar y mejorar columnas del listado | D91: WAPSA\Sprint - Noviembre - 2024 | E91: Resuelto | F91: [Ver. 2.19] | G91: 18/11/2024 7:00:00 p. m. | H91: 18/11/2024 7:00:00 p. m. | I91: 5/1/2025 7:00:00 p. m. | J91: Wapsa Web | L91: 393 | M91: Cristian Pastor Artigas <cartigas@syc-sistemas.com> | N91: Reportado por Carlos Zenteno Correciones/Mejora: La columna Estado Dif. Peso Taray Estado Dif. Peso Tara Supervisor ahora indicará PESO DENTRO DEL RANGO no hay diferencias Las columnas Tipo Pesaje Manul Tara y Tipo Pesaje Manual Bruto ahor seran renombradas a Tipo Pesaje Tara y Tipo Pesaje bruto y servirá para indicar no solo que tipo de peso manual se utilizo sino tambien cuando se ha usado la balanza. Esta correccion de columnas debe realizarse para el excel que se exporta en el modulo de Pesaje Manual Finalizado: | O91: Nuevo | P91: Requerimiento Nuevo-Area Comercial | Q91: No implica estabilización | R91: 161 | S91: =VLOOKUP(R91,Epics!A:B,2,FALSE) -> Soporte
A92: 356 | B92: Ticket | C92: Ticket 392 - Wapsa - Mina - Pesaje - Mail - Faltante de Stock en Mina correo llega con un dia incorrecto en el texto | D92: WAPSA\Sprint - Noviembre - 2024 | E92: Cerrado | G92: 12/11/2024 7:00:00 p. m. | H92: 21/11/2024 7:00:00 p. m. | I92: 25/11/2024 7:00:00 p. m. | J92: Wapsa Web | K92: 123862 | L92: 392 | M92: Cristian Pastor Artigas <cartigas@syc-sistemas.com> | N92: Carlos Zenteno Reporta: | O92: Nuevo | P92: Requerimiento Nuevo-Area Comercial | Q92: No implica estabilización | R92: 161 | S92: =VLOOKUP(R92,Epics!A:B,2,FALSE) -> Soporte
A93: 359 | B93: Ticket | C93: Ticket 394 - Wapsa - Callao - Operaciones - Ventana de error al listar de la pestaña operaciones | D93: WAPSA\Sprint - Noviembre - 2024 | E93: Resuelto | F93: [Ver. 2.19] | G93: 10/11/2024 7:00:00 p. m. | H93: 10/11/2024 7:00:00 p. m. | I93: 29/12/2024 7:00:00 p. m. | J93: Wapsa Web | L93: 394 | M93: Cristian Pastor Artigas <cartigas@syc-sistemas.com> | N93: Wally reporta | O93: Nuevo | P93: A&S | Q93: Estabilización de req. de Mantenimiento | R93: 161 | S93: =VLOOKUP(R93,Epics!A:B,2,FALSE) -> Soporte
A94: 360 | B94: Ticket | C94: Ticket 395 - Wapsa - Mina - Pesaje - Despacho - Error al intentar asignar peso tara a un despacho (Bloqueo de tablas) | D94: WAPSA\Sprint - Noviembre - 2024 | E94: Resuelto | F94: [Ver. 2.19] | G94: 21/11/2024 7:00:00 p. m. | H94: 21/11/2024 7:00:00 p. m. | I94: 29/12/2024 7:00:00 p. m. | J94: Wapsa Web | L94: 395 | M94: Cristian Pastor Artigas <cartigas@syc-sistemas.com> | N94: Carlos Zenteno reporta System.Exception: Execution Timeout Expired. The timeout period elapsed prior to completion of the operation or the server is not responding. Operation cancelled by user. Se terminó la instrucción. at WebMasterPla.Data.Conection.gDatos.TraerValor(Int32 IdUsuario, Int32 IdContratista, String ProcedimientoAlmacenado, Dictionary`2 parametros) at Chinalco.DespachoDAO.DespachosDAO.Actualizar(gDatos objCon, Despacho objentidad) in D:\MCPProjects\MCPWebProjects\WAPSA\Chinalco.DespachoDAO\DespachoDAO.cs:line 377 at Chinalco.DespachoBAL.clsGestionarDespachoBAL.Guardar(Despacho obj) in D:\MCPProjects\MCPWebProjects\WAPSA\Chinalco.Despacho\DespachoBAL.cs:line 606 @Cristian Pastor Artigas Se crea ticket para capturar el error, esta a la espera de ejecucion del ticket 392 | O94: Nuevo | P94: A&S | Q94: Estabilización de req. de Mantenimiento | R94: 161 | S94: =VLOOKUP(R94,Epics!A:B,2,FALSE) -> Soporte
A95: 361 | B95: Ticket | C95: Ticket 396 - Wapsa - Mina - Pesaje - Agregar Vagones sin destare por pesaje manual Lote CT 2410 | D95: WAPSA\Sprint - Noviembre - 2024 | E95: Resuelto | F95: [Ver. 2.19] | G95: 1/12/2024 7:00:00 p. m. | H95: 6/1/2025 7:00:00 p. m. | I95: 14/1/2025 7:00:00 p. m. | J95: Wapsa Web | L95: 396 | M95: Cristian Pastor Artigas <cartigas@syc-sistemas.com> | N95: Carlos Zenteno envia vagones sin destare para que sean agregardos al sistema bajo el pesaje manual Estos es un error de Wapsa que no los asigno al momento del pesaje y debe hacerse en un tivket modificando la columna TipoPesoManual Archivos en adjuntos Estimado Luis: Se adjunta la lista de vagones que fueron cargados sin destare. 08/11/24, Turno “B”. https://dev.azure.com/SycSistemas/833274e7-44d5-4093-8f90-9bab7903e605/_apis/wit/attachments/697ec761-0121-45b9-8297-702c85d99b18?fileName=rptDespachoDiario%2008.11.24_B.xlsx&download=true&api-version=5.0-preview.2 Estimado Luis: Se adjunta la lista de vagones que fueron cargados sin destare. 09/11/24, Turno “B”. https://dev.azure.com/SycSistemas/833274e7-44d5-4093-8f90-9bab7903e605/_apis/wit/attachments/f3f84e59-3d4d-474b-a0d0-3e27e03448bd?fileName=rptDespachoDiario%2009.11.24_B.xlsx&download=true&api-version=5.0-preview.2 Estimado Luis: Se adjunta la lista de vagones que fueron cargados sin destare. 10/11/24, Turno “B”. https://dev.azure.com/SycSistemas/833274e7-44d5-4093-8f90-9bab7903e605/_apis/wit/attachments/8746da6f-cb67-44ab-a2ff-531aa30a8132?fileName=rptDespachoDiario%2010.11.B.xlsx&download=true&api-version=5.0-preview.2 Estimado Luis: Se adjunta la lista de vagones que fueron cargados sin destare. 11/11/24, Turno “B”. https://dev.azure.com/SycSistemas/833274e7-44d5-4093-8f90-9bab7903e605/_apis/wit/attachments/e4fcbea8-7409-4319-8c1c-fef366e93b2e?fileName=rptDespachoDiario%2011.11.B.xlsx&download=true&api-version=5.0-preview.2 Estimado Luis: Se adjunta la lista de vagones que fueron cargados sin destare. 12/11/24, Turno “B”. https://dev.azure.com/SycSistemas/833274e7-44d5-4093-8f90-9bab7903e605/_apis/wit/attachments/f3fb234a-af27-4ffc-987b-dcd24bd1731a?fileName=rptDespachoDiario%2012.11.B.xlsx&download=true&api-version=5.0-preview.2 @Cristian Pastor Artigas Dentro de este ultimo formato ( 12/11/24, Turno “B”. ) se envia la guia T018-0016428 pero fue excluida para agregar al pesaje manual porque se compruba por la base de datos que se uso la balanza las taras son diferentes; @Cristian Pastor Artigas Finalizado script se tagea para enviar con la version | O95: Nuevo | P95: Requerimiento Nuevo-Area Comercial | Q95: No implica estabilización | R95: 161 | S95: =VLOOKUP(R95,Epics!A:B,2,FALSE) -> Soporte
A96: 367 | B96: Ticket | C96: Ticket 398 - Wapsa - Mina - Pesaje - Mejorar ventanas de bloqueo/cargando al registrar o actualizar un pesaje | D96: WAPSA\Sprint - Noviembre - 2024 | E96: Resuelto | F96: [Ver. 2.19] | G96: 27/11/2024 7:00:00 p. m. | H96: 27/11/2024 7:00:00 p. m. | I96: 29/12/2024 7:00:00 p. m. | J96: Wapsa Web | L96: 398 | M96: Cristian Pastor Artigas <cartigas@syc-sistemas.com> | N96: Corregir para que Wapsa muestre siempre pantalla de bloqueo/cargando cuando se el usuario hace click en guardar o enviar en un pesaje en los 3 pasos: Preasignar, peso tara y peso bruto. @Cristian Pastor Artigas 28/11 corregido en branch featured/Ticket398Mejorarventanasbloqueo-cargando | O96: Nuevo | P96: Requerimiento Nuevo-Area Comercial | Q96: No implica estabilización | R96: 161 | S96: =VLOOKUP(R96,Epics!A:B,2,FALSE) -> Soporte
A97: 384 | B97: Ticket | C97: Ticket 408 - Wapsa - Callao - Ajuste Mensual - Mail - Correo sobre Faltante de Stock en Mina cambio de horario de recepcion | D97: WAPSA\Sprint - Noviembre - 2024 | E97: Cerrado | G97: 6/1/2025 7:00:00 p. m. | H97: 6/1/2025 7:00:00 p. m. | I97: 23/1/2025 7:00:00 p. m. | J97: Wapsa Web | K97: 127796 | L97: 408 | M97: Cristian Pastor Artigas <cartigas@syc-sistemas.com> | N97: Carlos Zenteno Reporta: | O97: Nuevo | P97: A&S | Q97: Estabilización de req. de Mantenimiento | R97: 161 | S97: =VLOOKUP(R97,Epics!A:B,2,FALSE) -> Soporte
A98: 219 | B98: Ticket | C98: Ticket 331 - Wapsa - Callao - Volteo - Nuevos campos de auditoria | D98: WAPSA\Sprint - Mayo -2024 | E98: Cerrado | F98: [Ver. 2.16] | G98: 6/4/2024 7:00:00 p. m. | H98: 7/4/2024 7:00:00 p. m. | I98: 6/5/2024 7:00:00 p. m. | J98: Wapsa Web | L98: 331 | M98: Cristian Pastor Artigas <cartigas@syc-sistemas.com> | N98: Agregar dos columnas para que el proceso pueda ser auditado directamente 08/04 @Cristian Pastor Artigas se crea columnas de auditoria adicionales en branch https://dev.azure.com/SycSistemas/833274e7-44d5-4093-8f90-9bab7903e605/_git/WAPSA?version=GBcambios/filtra_lista_despacho | O98: Nuevo | P98: Requerimiento Nuevo-Area Comercial | Q98: No implica estabilización | R98: 161 | S98: =VLOOKUP(R98,Epics!A:B,2,FALSE) -> Soporte
A99: 225 | B99: Ticket | C99: Ticket 335 - Wapsa - Callao - Lista Despacho - Mejora Alerta IE's sin leyes | D99: WAPSA\Sprint - Mayo -2024 | E99: Cerrado | G99: 14/4/2024 7:00:00 p. m. | H99: 23/5/2024 7:00:00 p. m. | I99: 23/5/2024 7:00:00 p. m. | J99: WAPSA Web | K99: 107778 | L99: 335 | M99: Cristian Pastor Artigas <cartigas@syc-sistemas.com> | N99: Descripción: 1. Debe estar alineada al semáforo, si está en rojo o amarillo debe de listarse 2. Si estuvo en verde y pasa a amarillo o rojo debe de volver a listarse. Solución: 23/04 @Cristian Pastor Artigas Script modifcado para listar todas las IE's en rojo o amarillo 06/05 @Cristian Pastor Artigas En espera de crear formato para enviar ticket 15/05 @Cristian Pastor Artigas Se envia documento para firma de Alejandro 16/05 @Cristian Pastor Artigas Se envia a TICA | O99: Nuevo | P99: Requerimiento Nuevo-Area Comercial | Q99: No implica estabilización | R99: 161 | S99: =VLOOKUP(R99,Epics!A:B,2,FALSE) -> Soporte
A100: 228 | B100: Ticket | C100: Ticket 338 - Wapsa - Mina - Pesaje - Lista de Despacho- Cambiar Texto de Estado de Dif. Peso Tara | D100: WAPSA\Sprint - Mayo -2024 | E100: Cerrado | F100: [Ver. 2.16] | G100: 17/4/2024 7:00:00 p. m. | H100: 17/4/2024 7:00:00 p. m. | I100: 6/5/2024 7:00:00 p. m. | J100: Wapsa Web | L100: 338 | M100: Cristian Pastor Artigas <cartigas@syc-sistemas.com> | N100: Cuando se genera un pesaje cuyo peso tara no genera diferencia el sistema le asigna el texto APROBADO, deberia indicar DENTRO DEL RANGO 18/04 @Cristian Pastor Artigas Se graba en inicialmente en Dentro del Rango pero se cambiar a Aprobado una vez se registra el Peso Bruto por que se esta cambiando de valor una variable que no debe 18/04 @Cristian Pastor Artigas Se colocara como cambio en proxima version de Wapsa | O100: Nuevo | P100: Requerimiento Nuevo-Area Comercial | Q100: No implica estabilización | R100: 161 | S100: =VLOOKUP(R100,Epics!A:B,2,FALSE) -> Soporte
...
